Workbook

Sheet Inicio
B2: RODDOS — CONTROL FINANCIERO
B3: ="Mes de control: "&TEXT(Control!A4,"mmmm yyyy") -> Mes de control: julio 2026
B5: PRESUPUESTO DEL MES | C5: EJECUTADO | D5: DISPONIBLE | E5: % EJECUTADO | F5: CAJA DISPONIBLE | G5: DIF. VS BANCO
B6: =Control!B48 -> 2.8967115e+08 | C6: =Control!C48 -> 2.1769249e+08 | D6: =Control!D48 -> 71978663 | E6: =Control!E48 -> 0.75151594 | F6: =Control!H54 -> 6.7596705e+08 | G6: =Control!H56 -> -13.19
B7: INGRESO REAL (MES) | C7: INGRESO PROYECTADO | D7: % CUMPLIMIENTO
B8: =SUMIFS(TablaIngresos[[Valor]:[Valor]],TablaIngresos[[Mes]:[Mes]],Control!$A$4) -> 78863402 | C8: =IFERROR(INDEX('Proyeccion ingresos'!$F$17:$AT$17,MATCH(Control!$A$4,'Proyeccion ingresos'!$F$1:$AT$1,0)),"") -> 91413182 | D8: =IF(OR(C8="",C8=0),"",B8/C8) -> 0.86271367
B9: RESUMEN DEL MES POR GRUPO
B10: Grupo | C10: Presupuesto | D10: Ejecutado | E10: Disponible | F10: % Ejec.
B11: Costo de producto | C11: =Control!B11 -> 2200000 | D11: =Control!C11 -> 10465680 | E11: =Control!D11 -> -8265680 | F11: =Control!E11 -> 4.7571273
B12: Operación | C12: =Control!B24 -> 27500000 | D12: =Control!C24 -> 6365783.4 | E12: =Control!D24 -> 21134217 | F12: =Control!E24 -> 0.23148303
B13: Nómina | C13: =Control!B32 -> 1.6777115e+08 | D13: =Control!C32 -> 1.4924143e+08 | E13: =Control!D32 -> 18529723 | F13: =Control!E32 -> 0.88955358
B14: Deudas y obligaciones | C14: =Control!B39 -> 73200000 | D14: =Control!C39 -> 36853261 | E14: =Control!D39 -> 36346739 | F14: =Control!E39 -> 0.50345985
B15: Otros y varios | C15: =Control!B47 -> 19000000 | D15: =Control!C47 -> 14766336 | E15: =Control!D47 -> 4233664.4 | F15: =Control!E47 -> 0.77717556
B16: TOTAL | C16: =Control!B48 -> 2.8967115e+08 | D16: =Control!C48 -> 2.1769249e+08 | E16: =Control!D48 -> 71978663 | F16: =Control!E48 -> 0.75151594
B19: PENDIENTES POR CLASIFICAR
B20: Movimientos: | C20: =COUNTIF(TablaEgresos[Categoría],"Por clasificar") -> 72
B21: Valor total: | C21: =SUMIF(TablaEgresos[Categoría],"Por clasificar",TablaEgresos[Valor]) -> 74512398
B24: IR A: | C24: Control | D24: Presupuesto | E24: Egresos | F24: Ingresos

Sheet Control
A1: CONTROL DE EGRESOS VS PRESUPUESTO
A3: Mes de control | B3: Presupuesto del mes | C3: Ejecutado | D3: Disponible | E3: % Ejecutado | F3: Caja disponible
A4: 46204 | B4: =B48 -> 2.8967115e+08 | C4: =C48 -> 2.1769249e+08 | D4: =D48 -> 71978663 | E4: =E48 -> 0.75151594 | F4: =H54 -> 6.7596705e+08
A6: Categoría | B6: Presupuesto | C6: Ejecutado | D6: Disponible | E6: % Ejecutado | M6: Grupo | N6: Presupuesto | O6: Ejecutado
A7: COSTO DE PRODUCTO | M7: Costo prod. | N7: =B11 -> 2200000 | O7: =C11 -> 10465680
A8: Producto | B8: =IFERROR(INDEX(Presupuesto!$F$7:$CO$46,MATCH($A8,Presupuesto!$A$7:$A$46,0),MATCH($A$4,Presupuesto!$F$4:$CO$4,0)),0) -> 0 | C8: =SUMIFS(TablaEgresos[Valor],TablaEgresos[Categoría],$A8,TablaEgresos[Mes],$A$4) -> 0 | D8: =B8-C8 -> 0 | E8: =IF(B8=0,"",C8/B8) | M8: Operación | N8: =B24 -> 27500000 | O8: =C24 -> 6365783.4
A9: SOAT/Matrículas | B9: =IFERROR(INDEX(Presupuesto!$F$7:$CO$46,MATCH($A9,Presupuesto!$A$7:$A$46,0),MATCH($A$4,Presupuesto!$F$4:$CO$4,0)),0) -> 0 | C9: =SUMIFS(TablaEgresos[Valor],TablaEgresos[Categoría],$A9,TablaEgresos[Mes],$A$4) -> 10465680 | D9: =B9-C9 -> -10465680 | E9: =IF(B9=0,"",C9/B9) | M9: Nómina | N9: =B32 -> 1.6777115e+08 | O9: =C32 -> 1.4924143e+08
A10: Seguros (Hunter) | B10: =IFERROR(INDEX(Presupuesto!$F$7:$CO$46,MATCH($A10,Presupuesto!$A$7:$A$46,0),MATCH($A$4,Presupuesto!$F$4:$CO$4,0)),0) -> 2200000 | C10: =SUMIFS(TablaEgresos[Valor],TablaEgresos[Categoría],$A10,TablaEgresos[Mes],$A$4) -> 0 | D10: =B10-C10 -> 2200000 | E10: =IF(B10=0,"",C10/B10) -> 0 | M10: Deudas | N10: =B39 -> 73200000 | O10: =C39 -> 36853261
A11: Subtotal Costo de producto | B11: =SUM(B8:B10) -> 2200000 | C11: =SUM(C8:C10) -> 10465680 | D11: =SUM(D8:D10) -> -8265680 | E11: =IF(B11=0,"",C11/B11) -> 4.7571273 | M11: Otros | N11: =B47 -> 19000000 | O11: =C47 -> 14766336
A12: OPERACIÓN
A13: Arriendos | B13: =IFERROR(INDEX(Presupuesto!$F$7:$CO$46,MATCH($A13,Presupuesto!$A$7:$A$46,0),MATCH($A$4,Presupuesto!$F$4:$CO$4,0)),0) -> 8000000 | C13: =SUMIFS(TablaEgresos[Valor],TablaEgresos[Categoría],$A13,TablaEgresos[Mes],$A$4) -> 0 | D13: =B13-C13 -> 8000000 | E13: =IF(B13=0,"",C13/B13) -> 0
A14: Tecnología y software | B14: =IFERROR(INDEX(Presupuesto!$F$7:$CO$46,MATCH($A14,Presupuesto!$A$7:$A$46,0),MATCH($A$4,Presupuesto!$F$4:$CO$4,0)),0) -> 4000000 | C14: =SUMIFS(TablaEgresos[Valor],TablaEgresos[Categoría],$A14,TablaEgresos[Mes],$A$4) -> 4808607.4 | D14: =B14-C14 -> -808607.42 | E14: =IF(B14=0,"",C14/B14) -> 1.2021519 | M14: Mes | N14: Caja fin de mes
A15: Mobiliario/planta/equipo | B15: =IFERROR(INDEX(Presupuesto!$F$7:$CO$46,MATCH($A15,Presupuesto!$A$7:$A$46,0),MATCH($A$4,Presupuesto!$F$4:$CO$4,0)),0) -> 0 | C15: =SUMIFS(TablaEgresos[Valor],TablaEgresos[Categoría],$A15,TablaEgresos[Mes],$A$4) -> 71100 | D15: =B15-C15 -> -71100 | E15: =IF(B15=0,"",C15/B15) | M15: =J51 -> 46082 | N15: =SUMIFS(TablaIngresos[Valor],TablaIngresos[Mes],"<="&$M15)-SUMIFS(TablaEgresos[Valor],TablaEgresos[Mes],"<="&$M15) -> 1241164.1
A16: Servicios públicos y telecom | B16: =IFERROR(INDEX(Presupuesto!$F$7:$CO$46,MATCH($A16,Presupuesto!$A$7:$A$46,0),MATCH($A$4,Presupuesto!$F$4:$CO$4,0)),0) -> 900000 | C16: =SUMIFS(TablaEgresos[Valor],TablaEgresos[Categoría],$A16,TablaEgresos[Mes],$A$4) -> 0 | D16: =B16-C16 -> 900000 | E16: =IF(B16=0,"",C16/B16) -> 0 | M16: =J52 -> 46113 | N16: =SUMIFS(TablaIngresos[Valor],TablaIngresos[Mes],"<="&$M16)-SUMIFS(TablaEgresos[Valor],TablaEgresos[Mes],"<="&$M16) -> 21955335
A17: Mercado y aseo | B17: =IFERROR(INDEX(Presupuesto!$F$7:$CO$46,MATCH($A17,Presupuesto!$A$7:$A$46,0),MATCH($A$4,Presupuesto!$F$4:$CO$4,0)),0) -> 600000 | C17: =SUMIFS(TablaEgresos[Valor],TablaEgresos[Categoría],$A17,TablaEgresos[Mes],$A$4) -> 106278 | D17: =B17-C17 -> 493722 | E17: =IF(B17=0,"",C17/B17) -> 0.17713 | M17: =J53 -> 46143 | N17: =SUMIFS(TablaIngresos[Valor],TablaIngresos[Mes],"<="&$M17)-SUMIFS(TablaEgresos[Valor],TablaEgresos[Mes],"<="&$M17) -> 7358445.7
A18: Cafetería | B18: =IFERROR(INDEX(Presupuesto!$F$7:$CO$46,MATCH($A18,Presupuesto!$A$7:$A$46,0),MATCH($A$4,Presupuesto!$F$4:$CO$4,0)),0) -> 500000 | C18: =SUMIFS(TablaEgresos[Valor],TablaEgresos[Categoría],$A18,TablaEgresos[Mes],$A$4) -> 176200 | D18: =B18-C18 -> 323800 | E18: =IF(B18=0,"",C18/B18) -> 0.3524 | M18: =J54 -> 46174 | N18: =SUMIFS(TablaIngresos[Valor],TablaIngresos[Mes],"<="&$M18)-SUMIFS(TablaEgresos[Valor],TablaEgresos[Mes],"<="&$M18) -> 8.1479614e+08
A19: Transporte/peajes/combustible/parqueo | B19: =IFERROR(INDEX(Presupuesto!$F$7:$CO$46,MATCH($A19,Presupuesto!$A$7:$A$46,0),MATCH($A$4,Presupuesto!$F$4:$CO$4,0)),0) -> 1500000 | C19: =SUMIFS(TablaEgresos[Valor],TablaEgresos[Categoría],$A19,TablaEgresos[Mes],$A$4) -> 1203598 | D19: =B19-C19 -> 296402.04 | E19: =IF(B19=0,"",C19/B19) -> 0.80239864 | M19: =J55 -> 46204 | N19: =SUMIFS(TablaIngresos[Valor],TablaIngresos[Mes],"<="&$M19)-SUMIFS(TablaEgresos[Valor],TablaEgresos[Mes],"<="&$M19) -> 6.7596705e+08
A20: Papelería | B20: =IFERROR(INDEX(Presupuesto!$F$7:$CO$46,MATCH($A20,Presupuesto!$A$7:$A$46,0),MATCH($A$4,Presupuesto!$F$4:$CO$4,0)),0) -> 0 | C20: =SUMIFS(TablaEgresos[Valor],TablaEgresos[Categoría],$A20,TablaEgresos[Mes],$A$4) -> 0 | D20: =B20-C20 -> 0 | E20: =IF(B20=0,"",C20/B20)
A21: Marketing y publicidad | B21: =IFERROR(INDEX(Presupuesto!$F$7:$CO$46,MATCH($A21,Presupuesto!$A$7:$A$46,0),MATCH($A$4,Presupuesto!$F$4:$CO$4,0)),0) -> 0 | C21: =SUMIFS(TablaEgresos[Valor],TablaEgresos[Categoría],$A21,TablaEgresos[Mes],$A$4) -> 0 | D21: =B21-C21 -> 0 | E21: =IF(B21=0,"",C21/B21)
A22: Gastos de representación | B22: =IFERROR(INDEX(Presupuesto!$F$7:$CO$46,MATCH($A22,Presupuesto!$A$7:$A$46,0),MATCH($A$4,Presupuesto!$F$4:$CO$4,0)),0) -> 0 | C22: =SUMIFS(TablaEgresos[Valor],TablaEgresos[Categoría],$A22,TablaEgresos[Mes],$A$4) -> 0 | D22: =B22-C22 -> 0 | E22: =IF(B22=0,"",C22/B22)
A23: Renting | B23: =IFERROR(INDEX(Presupuesto!$F$7:$CO$46,MATCH($A23,Presupuesto!$A$7:$A$46,0),MATCH($A$4,Presupuesto!$F$4:$CO$4,0)),0) -> 12000000 | C23: =SUMIFS(TablaEgresos[Valor],TablaEgresos[Categoría],$A23,TablaEgresos[Mes],$A$4) -> 0 | D23: =B23-C23 -> 12000000 | E23: =IF(B23=0,"",C23/B23) -> 0
A24: Subtotal Operación | B24: =SUM(B13:B23) -> 27500000 | C24: =SUM(C13:C23) -> 6365783.4 | D24: =SUM(D13:D23) -> 21134217 | E24: =IF(B24=0,"",C24/B24) -> 0.23148303
A25: NÓMINA
A26: Sueldos empleados | B26: =IFERROR(INDEX(Presupuesto!$F$7:$CO$46,MATCH($A26,Presupuesto!$A$7:$A$46,0),MATCH($A$4,Presupuesto!$F$4:$CO$4,0)),0) -> 10000000 | C26: =SUMIFS(TablaEgresos[Valor],TablaEgresos[Categoría],$A26,TablaEgresos[Mes],$A$4) -> 9656272.8 | D26: =B26-C26 -> 343727.24 | E26: =IF(B26=0,"",C26/B26) -> 0.96562728
A27: Sueldos directivos | B27: =IFERROR(INDEX(Presupuesto!$F$7:$CO$46,MATCH($A27,Presupuesto!$A$7:$A$46,0),MATCH($A$4,Presupuesto!$F$4:$CO$4,0)),0) -> 36791951 | C27: =SUMIFS(TablaEgresos[Valor],TablaEgresos[Categoría],$A27,TablaEgresos[Mes],$A$4) -> 20291951 | D27: =B27-C27 -> 16500000 | E27: =IF(B27=0,"",C27/B27) -> 0.55153235
A28: Bonificaciones | B28: =IFERROR(INDEX(Presupuesto!$F$7:$CO$46,MATCH($A28,Presupuesto!$A$7:$A$46,0),MATCH($A$4,Presupuesto!$F$4:$CO$4,0)),0) -> 82000000 | C28: =SUMIFS(TablaEgresos[Valor],TablaEgresos[Categoría],$A28,TablaEgresos[Mes],$A$4) -> 80314004 | D28: =B28-C28 -> 1685995.6 | E28: =IF(B28=0,"",C28/B28) -> 0.97943908
A29: Beneficios Heads | B29: =IFERROR(INDEX(Presupuesto!$F$7:$CO$46,MATCH($A29,Presupuesto!$A$7:$A$46,0),MATCH($A$4,Presupuesto!$F$4:$CO$4,0)),0) -> 0 | C29: =SUMIFS(TablaEgresos[Valor],TablaEgresos[Categoría],$A29,TablaEgresos[Mes],$A$4) -> 0 | D29: =B29-C29 -> 0 | E29: =IF(B29=0,"",C29/B29)
A30: Planillas nuevas | B30: =IFERROR(INDEX(Presupuesto!$F$7:$CO$46,MATCH($A30,Presupuesto!$A$7:$A$46,0),MATCH($A$4,Presupuesto!$F$4:$CO$4,0)),0) -> 0 | C30: =SUMIFS(TablaEgresos[Valor],TablaEgresos[Categoría],$A30,TablaEgresos[Mes],$A$4) -> 0 | D30: =B30-C30 -> 0 | E30: =IF(B30=0,"",C30/B30)
A31: Planillas anteriores | B31: =IFERROR(INDEX(Presupuesto!$F$7:$CO$46,MATCH($A31,Presupuesto!$A$7:$A$46,0),MATCH($A$4,Presupuesto!$F$4:$CO$4,0)),0) -> 38979200 | C31: =SUMIFS(TablaEgresos[Valor],TablaEgresos[Categoría],$A31,TablaEgresos[Mes],$A$4) -> 38979200 | D31: =B31-C31 -> 0 | E31: =IF(B31=0,"",C31/B31) -> 1
A32: Subtotal Nómina | B32: =SUM(B26:B31) -> 1.6777115e+08 | C32: =SUM(C26:C31) -> 1.4924143e+08 | D32: =SUM(D26:D31) -> 18529723 | E32: =IF(B32=0,"",C32/B32) -> 0.88955358
A33: DEUDAS Y OBLIGACIONES
A34: Préstamos | B34: =IFERROR(INDEX(Presupuesto!$F$7:$CO$46,MATCH($A34,Presupuesto!$A$7:$A$46,0),MATCH($A$4,Presupuesto!$F$4:$CO$4,0)),0) -> 21000000 | C34: =SUMIFS(TablaEgresos[Valor],TablaEgresos[Categoría],$A34,TablaEgresos[Mes],$A$4) -> 17653261 | D34: =B34-C34 -> 3346739 | E34: =IF(B34=0,"",C34/B34) -> 0.84063147
A35: Deudas tarjetas de crédito | B35: =IFERROR(INDEX(Presupuesto!$F$7:$CO$46,MATCH($A35,Presupuesto!$A$7:$A$46,0),MATCH($A$4,Presupuesto!$F$4:$CO$4,0)),0) -> 9200000 | C35: =SUMIFS(TablaEgresos[Valor],TablaEgresos[Categoría],$A35,TablaEgresos[Mes],$A$4) -> 9200000 | D35: =B35-C35 -> 0 | E35: =IF(B35=0,"",C35/B35) -> 1
A36: Garantía cupo | B36: =IFERROR(INDEX(Presupuesto!$F$7:$CO$46,MATCH($A36,Presupuesto!$A$7:$A$46,0),MATCH($A$4,Presupuesto!$F$4:$CO$4,0)),0) -> 14000000 | C36: =SUMIFS(TablaEgresos[Valor],TablaEgresos[Categoría],$A36,TablaEgresos[Mes],$A$4) -> 0 | D36: =B36-C36 -> 14000000 | E36: =IF(B36=0,"",C36/B36) -> 0
A37: Deudas impuestos | B37: =IFERROR(INDEX(Presupuesto!$F$7:$CO$46,MATCH($A37,Presupuesto!$A$7:$A$46,0),MATCH($A$4,Presupuesto!$F$4:$CO$4,0)),0) -> 9000000 | C37: =SUMIFS(TablaEgresos[Valor],TablaEgresos[Categoría],$A37,TablaEgresos[Mes],$A$4) -> 0 | D37: =B37-C37 -> 9000000 | E37: =IF(B37=0,"",C37/B37) -> 0
A38: Deudas proveedores anteriores | B38: =IFERROR(INDEX(Presupuesto!$F$7:$CO$46,MATCH($A38,Presupuesto!$A$7:$A$46,0),MATCH($A$4,Presupuesto!$F$4:$CO$4,0)),0) -> 20000000 | C38: =SUMIFS(TablaEgresos[Valor],TablaEgresos[Categoría],$A38,TablaEgresos[Mes],$A$4) -> 9999999.8 | D38: =B38-C38 -> 10000000 | E38: =IF(B38=0,"",C38/B38) -> 0.49999999
A39: Subtotal Deudas | B39: =SUM(B34:B38) -> 73200000 | C39: =SUM(C34:C38) -> 36853261 | D39: =SUM(D34:D38) -> 36346739 | E39: =IF(B39=0,"",C39/B39) -> 0.50345985
A40: OTROS Y VARIOS
A41: Otros gastos | B41: =IFERROR(INDEX(Presupuesto!$F$7:$CO$46,MATCH($A41,Presupuesto!$A$7:$A$46,0),MATCH($A$4,Presupuesto!$F$4:$CO$4,0)),0) -> 19000000 | C41: =SUMIFS(TablaEgresos[Valor],TablaEgresos[Categoría],$A41,TablaEgresos[Mes],$A$4) -> 10084789 | D41: =B41-C41 -> 8915210.7 | E41: =IF(B41=0,"",C41/B41) -> 0.53077839
A42: Gastos notariales | B42: =IFERROR(INDEX(Presupuesto!$F$7:$CO$46,MATCH($A42,Presupuesto!$A$7:$A$46,0),MATCH($A$4,Presupuesto!$F$4:$CO$4,0)),0) -> 0 | C42: =SUMIFS(TablaEgresos[Valor],TablaEgresos[Categoría],$A42,TablaEgresos[Mes],$A$4) -> 3686613 | D42: =B42-C42 -> -3686613 | E42: =IF(B42=0,"",C42/B42)
A43: Gastos bancarios | B43: =IFERROR(INDEX(Presupuesto!$F$7:$CO$46,MATCH($A43,Presupuesto!$A$7:$A$46,0),MATCH($A$4,Presupuesto!$F$4:$CO$4,0)),0) -> 0 | C43: =SUMIFS(TablaEgresos[Valor],TablaEgresos[Categoría],$A43,TablaEgresos[Mes],$A$4) -> 29701 | D43: =B43-C43 -> -29701 | E43: =IF(B43=0,"",C43/B43)
A44: Gastos financieros | B44: =IFERROR(INDEX(Presupuesto!$F$7:$CO$46,MATCH($A44,Presupuesto!$A$7:$A$46,0),MATCH($A$4,Presupuesto!$F$4:$CO$4,0)),0) -> 0 | C44: =SUMIFS(TablaEgresos[Valor],TablaEgresos[Categoría],$A44,TablaEgresos[Mes],$A$4) -> 0 | D44: =B44-C44 -> 0 | E44: =IF(B44=0,"",C44/B44)
A45: Impuestos | B45: =IFERROR(INDEX(Presupuesto!$F$7:$CO$46,MATCH($A45,Presupuesto!$A$7:$A$46,0),MATCH($A$4,Presupuesto!$F$4:$CO$4,0)),0) -> 0 | C45: =SUMIFS(TablaEgresos[Valor],TablaEgresos[Categoría],$A45,TablaEgresos[Mes],$A$4) -> 859232.27 | D45: =B45-C45 -> -859232.27 | E45: =IF(B45=0,"",C45/B45)
A46: Por clasificar | B46: =IFERROR(INDEX(Presupuesto!$F$7:$CO$46,MATCH($A46,Presupuesto!$A$7:$A$46,0),MATCH($A$4,Presupuesto!$F$4:$CO$4,0)),0) -> 0 | C46: =SUMIFS(TablaEgresos[Valor],TablaEgresos[Categoría],$A46,TablaEgresos[Mes],$A$4) -> 106000 | D46: =B46-C46 -> -106000 | E46: =IF(B46=0,"",C46/B46)
A47: Subtotal Otros | B47: =SUM(B41:B46) -> 19000000 | C47: =SUM(C41:C46) -> 14766336 | D47: =SUM(D41:D46) -> 4233664.4 | E47: =IF(B47=0,"",C47/B47) -> 0.77717556
A48: TOTAL | B48: =B11+B24+B32+B39+B47 -> 2.8967115e+08 | C48: =C11+C24+C32+C39+C47 -> 2.1769249e+08 | D48: =D11+D24+D32+D39+D47 -> 71978663 | E48: =IF(B48=0,"",C48/B48) -> 0.75151594
G50: CAJA DEL MES | J50: SALDO BANCO FIN DE MES
G51: Saldo inicial del mes | H51: =SUMIFS(TablaIngresos[Valor],TablaIngresos[Mes],"<"&$A$4)-SUMIFS(TablaEgresos[Valor],TablaEgresos[Mes],"<"&$A$4) -> 8.1479614e+08 | J51: 46082 | K51: 1241164.1
G52: (+) Ingresos del mes | H52: =SUMIFS(TablaIngresos[Valor],TablaIngresos[Mes],$A$4) -> 78863402 | J52: 46113 | K52: 21955334
G53: (-) Egresos del mes | H53: =C48 -> 2.1769249e+08 | J53: 46143 | K53: 7358444
G54: Caja disponible (auto) | H54: =H51+H52-H53 -> 6.7596705e+08 | J54: 46174 | K54: 8.1479614e+08
G55: Saldo según banco (fin de mes) | H55: =IFERROR(IF(INDEX($K$51:$K$72,MATCH($A$4,$J$51:$J$72,0))=0,"",INDEX($K$51:$K$72,MATCH($A$4,$J$51:$J$72,0))),"") -> 675967040 | J55: 46204 | K55: 675967040
G56: Diferencia vs banco | H56: =IF(H55="","",H55-H54) -> -13.19 | J56: 46235
J57: 46266
J58: 46296
J59: 46327
J60: 46357
J61: 46388
J62: 46419
J63: 46447
J64: 46478
J65: 46508
J66: 46539
J67: 46569
J68: 46600
... J72: 46722

Sheet Pagos semana
A1: PAGOS DE LA PRÓXIMA SEMANA — IMPACTO EN CAJA Y PRESUPUESTO
A3: Caja disponible hoy | B3: =Control!$H$54 -> 6.7596705e+08
A4: Mes de control | B4: =Control!$A$4 -> 46204
A5: (+) Ingresos esperados semana (promedio real del mes, editable) | B5: =ROUND(SUMIFS(TablaIngresos[[Valor]:[Valor]],TablaIngresos[[Mes]:[Mes]],Control!$A$4)/MAX(1,(MIN(TODAY(),EOMONTH(Control!$A$4,0))-Control!$A$4+1)/7),-3) -> 32473000
A7: Pago / concepto | B7: Categoría | C7: Fecha | D7: Valor | E7: Disponible categoría (mes) | F7: Restante en categoría | G7: ¿Se ajusta al presupuesto? | H7: Caja después del pago
A8: Pago deuda Raul | B8: Préstamos | C8: 46224 | D8: 5000000 | E8: =IF(OR($B8="",$D8=""),"",IFERROR(INDEX(Control!$D$8:$D$46,MATCH($B8,Control!$A$8:$A$46,0)),0)) -> 3346739 | F8: =IF($E8="","",$E8-SUMIFS($D$8:$D8,$B$8:$B8,$B8)) -> -1653261 | G8: =IF($F8="","",IF($F8>=0,"✔ Cabe","✖ Excede "&TEXT(-$F8,"$#.##0"))) -> ✖ Excede $1.653.261 | H8: =IF($D8="","",$B$3-SUM($D$8:$D8)) -> 6.7096705e+08
A9: Pago deuda Maya | B9: Préstamos | C9: 46234 | D9: 495000 | E9: =IF(OR($B9="",$D9=""),"",IFERROR(INDEX(Control!$D$8:$D$46,MATCH($B9,Control!$A$8:$A$46,0)),0)) -> 3346739 | F9: =IF($E9="","",$E9-SUMIFS($D$8:$D9,$B$8:$B9,$B9)) -> -2148261 | G9: =IF($F9="","",IF($F9>=0,"✔ Cabe","✖ Excede "&TEXT(-$F9,"$#.##0"))) -> ✖ Excede $2.148.261 | H9: =IF($D9="","",$B$3-SUM($D$8:$D9)) -> 6.7047205e+08
A10: Pago deuda Luis Moreno | B10: Deudas proveedores anteriores | C10: 46224 | D10: 5000000 | E10: =IF(OR($B10="",$D10=""),"",IFERROR(INDEX(Control!$D$8:$D$46,MATCH($B10,Control!$A$8:$A$46,0)),0)) -> 10000000 | F10: =IF($E10="","",$E10-SUMIFS($D$8:$D10,$B$8:$B10,$B10)) -> 5000000.2 | G10: =IF($F10="","",IF($F10>=0,"✔ Cabe","✖ Excede "&TEXT(-$F10,"$#.##0"))) -> ✔ Cabe | H10: =IF($D10="","",$B$3-SUM($D$8:$D10)) -> 6.6547205e+08
A11: Compra maleta RODDOS | B11: Otros gastos | C11: 46220 | D11: 250000 | E11: =IF(OR($B11="",$D11=""),"",IFERROR(INDEX(Control!$D$8:$D$46,MATCH($B11,Control!$A$8:$A$46,0)),0)) -> 8915210.7 | F11: =IF($E11="","",$E11-SUMIFS($D$8:$D11,$B$8:$B11,$B11)) -> 8665210.7 | G11: =IF($F11="","",IF($F11>=0,"✔ Cabe","✖ Excede "&TEXT(-$F11,"$#.##0"))) -> ✔ Cabe | H11: =IF($D11="","",$B$3-SUM($D$8:$D11)) -> 6.6522205e+08
A12: Renting | B12: Renting | C12: 46224 | D12: 8900000 | E12: =IF(OR($B12="",$D12=""),"",IFERROR(INDEX(Control!$D$8:$D$46,MATCH($B12,Control!$A$8:$A$46,0)),0)) -> 12000000 | F12: =IF($E12="","",$E12-SUMIFS($D$8:$D12,$B$8:$B12,$B12)) -> 3100000 | G12: =IF($F12="","",IF($F12>=0,"✔ Cabe","✖ Excede "&TEXT(-$F12,"$#.##0"))) -> ✔ Cabe | H12: =IF($D12="","",$B$3-SUM($D$8:$D12)) -> 6.5632205e+08
A13: Pago deuda mama | B13: Préstamos | C13: 46220 | D13: 3000000 | E13: =IF(OR($B13="",$D13=""),"",IFERROR(INDEX(Control!$D$8:$D$46,MATCH($B13,Control!$A$8:$A$46,0)),0)) -> 3346739 | F13: =IF($E13="","",$E13-SUMIFS($D$8:$D13,$B$8:$B13,$B13)) -> -5148261 | G13: =IF($F13="","",IF($F13>=0,"✔ Cabe","✖ Excede "&TEXT(-$F13,"$#.##0"))) -> ✖ Excede $5.148.261 | H13: =IF($D13="","",$B$3-SUM($D$8:$D13)) -> 6.5332205e+08
A14: SOAT/Matricula | B14: SOAT/Matrículas | C14: 46226 | D14: 7500000 | E14: =IF(OR($B14="",$D14=""),"",IFERROR(INDEX(Control!$D$8:$D$46,MATCH($B14,Control!$A$8:$A$46,0)),0)) -> -10465680 | F14: =IF($E14="","",$E14-SUMIFS($D$8:$D14,$B$8:$B14,$B14)) -> -17965680 | G14: =IF($F14="","",IF($F14>=0,"✔ Cabe","✖ Excede "&TEXT(-$F14,"$#.##0"))) -> ✖ Excede $17.965.680 | H14: =IF($D14="","",$B$3-SUM($D$8:$D14)) -> 6.4582205e+08
A15: Impuestos | B15: Impuestos | C15: 46224 | D15: 11500000 | E15: =IF(OR($B15="",$D15=""),"",IFERROR(INDEX(Control!$D$8:$D$46,MATCH($B15,Control!$A$8:$A$46,0)),0)) -> -859232.27 | F15: =IF($E15="","",$E15-SUMIFS($D$8:$D15,$B$8:$B15,$B15)) -> -12359232 | G15: =IF($F15="","",IF($F15>=0,"✔ Cabe","✖ Excede "&TEXT(-$F15,"$#.##0"))) -> ✖ Excede $12.359.232 | H15: =IF($D15="","",$B$3-SUM($D$8:$D15)) -> 6.3432205e+08
A16: Arriendo | B16: Arriendos | C16: 46234 | D16: 8320000 | E16: =IF(OR($B16="",$D16=""),"",IFERROR(INDEX(Control!$D$8:$D$46,MATCH($B16,Control!$A$8:$A$46,0)),0)) -> 8000000 | F16: =IF($E16="","",$E16-SUMIFS($D$8:$D16,$B$8:$B16,$B16)) -> -320000 | G16: =IF($F16="","",IF($F16>=0,"✔ Cabe","✖ Excede "&TEXT(-$F16,"$#.##0"))) -> ✖ Excede $320.000 | H16: =IF($D16="","",$B$3-SUM($D$8:$D16)) -> 6.2600205e+08
A17: Servicios | B17: Servicios públicos y telecom | C17: 46234 | D17: 900000 | E17: =IF(OR($B17="",$D17=""),"",IFERROR(INDEX(Control!$D$8:$D$46,MATCH($B17,Control!$A$8:$A$46,0)),0)) -> 900000 | F17: =IF($E17="","",$E17-SUMIFS($D$8:$D17,$B$8:$B17,$B17)) -> 0 | G17: =IF($F17="","",IF($F17>=0,"✔ Cabe","✖ Excede "&TEXT(-$F17,"$#.##0"))) -> ✔ Cabe | H17: =IF($D17="","",$B$3-SUM($D$8:$D17)) -> 6.2510205e+08
A18: Pasantes | B18: Sueldos empleados | C18: 46220 | D18: 1200000 | E18: =IF(OR($B18="",$D18=""),"",IFERROR(INDEX(Control!$D$8:$D$46,MATCH($B18,Control!$A$8:$A$46,0)),0)) -> 343727.24 | F18: =IF($E18="","",$E18-SUMIFS($D$8:$D18,$B$8:$B18,$B18)) -> -856272.76 | G18: =IF($F18="","",IF($F18>=0,"✔ Cabe","✖ Excede "&TEXT(-$F18,"$#.##0"))) -> ✖ Excede $856.273 | H18: =IF($D18="","",$B$3-SUM($D$8:$D18)) -> 6.2390205e+08
A19: Palenca | B19: Tecnología y software | C19: 46234 | D19: 890000 | E19: =IF(OR($B19="",$D19=""),"",IFERROR(INDEX(Control!$D$8:$D$46,MATCH($B19,Control!$A$8:$A$46,0)),0)) -> -808607.42 | F19: =IF($E19="","",$E19-SUMIFS($D$8:$D19,$B$8:$B19,$B19)) -> -1698607.4 | G19: =IF($F19="","",IF($F19>=0,"✔ Cabe","✖ Excede "&TEXT(-$F19,"$#.##0"))) -> ✖ Excede $1.698.607 | H19: =IF($D19="","",$B$3-SUM($D$8:$D19)) -> 6.2301205e+08
... A22: Hunter | B22: Seguros (Hunter) | C22: 46226 | D22: 6500000 | E22: =IF(OR($B22="",$D22=""),"",IFERROR(INDEX(Control!$D$8:$D$46,MATCH($B22,Control!$A$8:$A$46,0)),0)) -> 2200000 | F22: =IF($E22="","",$E22-SUMIFS($D$8:$D22,$B$8:$B22,$B22)) -> -10800000 | G22: =IF($F22="","",IF($F22>=0,"✔ Cabe","✖ Excede "&TEXT(-$F22,"$#.##0"))) -> ✖ Excede $10.800.000 | H22: =IF($D22="","",$B$3-SUM($D$8:$D22)) -> 6.0801205e+08
A24: IMPACTO PROYECTADO
A25: Total pagos planeados | B25: =SUM($D$8:$D$22) -> 67955000
A26: Caja hoy | B26: =$B$3 -> 6.7596705e+08
A27: (+) Ingresos esperados semana | B27: =$B$5 -> 32473000
A28: (−) Pagos planeados | B28: =$B$25 -> 67955000
A29: Caja proyectada tras pagos | B29: =B26+B27-B28 -> 6.4048505e+08
A30: Presupuesto general del mes tras estos pagos | B30: =IF(Control!$B$48=0,"",(Control!$C$48+$B$25)/Control!$B$48) -> 0.98610955 | C30: ="Ejecutado + planeado: "&TEXT(Control!$C$48+$B$25,"$#.##0")&" de "&TEXT(Control!$B$48,"$#.##0")&" — quedarían "&TEXT(Control!$B$48-Control!$C$48-$B$25,"$#.##0") -> Ejecutado + planeado: $285.647.488 de $289.671.151 — quedarían $4.023.663

Sheet Presupuesto
A1: PRESUPUESTO Y SEGUIMIENTO — MAR 2026 A DIC 2027
A2: Azul = presupuesto definido (editable). Cursiva = proyección automática (promedio + tendencia; puedes sobreescribirla). El panel izquierdo usa solo meses completos.
A3: Último mes completo: | B3: =EOMONTH(TODAY(),-2)+1 -> 46174
F4: =B$51 -> 46082 | J4: =C$51 -> 46113 | N4: =D$51 -> 46143 | R4: =E$51 -> 46174 | V4: =F$51 -> 46204 | Z4: =G$51 -> 46235 | AD4: =H$51 -> 46266 | AH4: =I$51 -> 46296 | AL4: =J$51 -> 46327 | AP4: =K$51 -> 46357 | AT4: =L$51 -> 46388 | AX4: =M$51 -> 46419 | BB4: =N$51 -> 46447 | BF4: =O$51 -> 46478 | BJ4: =P$51 -> 46508 | BN4: =Q$51 -> 46539 | BR4: =R$51 -> 46569 | BV4: =S$51 -> 46600 | BZ4: =T$51 -> 46631 | CD4: =U$51 -> 46661 | CH4: =V$51 -> 46692 | CL4: =W$51 -> 46722
A5: Categoría | B5: Prom. últ. 3M | C5: Tendencia $/mes | D5: Crec. %/mes | E5: Sugerido mes sig. | F5: Presupuesto | G5: Ejecutado | H5: Disponible | I5: % | J5: Presupuesto | K5: Ejecutado | L5: Disponible | M5: % | N5: Presupuesto | O5: Ejecutado | P5: Disponible | Q5: % | R5: Presupuesto | S5: Ejecutado | T5: Disponible | U5: % | V5: Presupuesto | W5: Ejecutado | X5: Disponible | Y5: % | Z5: Presupuesto | AA5: Ejecutado | AB5: Disponible | AC5: % | AD5: Presupuesto | AE5: Ejecutado | AF5: Disponible | AG5: % | AH5: Presupuesto | AI5: Ejecutado | AJ5: Disponible | AK5: % | AL5: Presupuesto | AM5: Ejecutado | AN5: Disponible | AO5: % | AP5: Presupuesto | AQ5: Ejecutado | AR5: Disponible | AS5: % | AT5: Presupuesto | AU5: Ejecutado | AV5: Disponible | AW5: % | AX5: Presupuesto | AY5: Ejecutado | AZ5: Disponible | BA5: % | BB5: Presupuesto | BC5: Ejecutado | BD5: Disponible | BE5: % | BF5: Presupuesto | BG5: Ejecutado | BH5: Disponible | BI5: % | BJ5: Presupuesto | BK5: Ejecutado | BL5: Disponible | BM5: % | BN5: Presupuesto | BO5: Ejecutado | BP5: Disponible | BQ5: % | BR5: Presupuesto | BS5: Ejecutado | BT5: Disponible | BU5: % | BV5: Presupuesto | BW5: Ejecutado | BX5: Disponible | BY5: % | BZ5: Presupuesto | CA5: Ejecutado | CB5: Disponible | CC5: % | CD5: Presupuesto | CE5: Ejecutado | CF5: Disponible | CG5: % | CH5: Presupuesto | CI5: Ejecutado | CJ5: Disponible | CK5: % | CL5: Presupuesto | CM5: Ejecutado | CN5: Disponible | CO5: %
A6: COSTO DE PRODUCTO
A7: Producto | B7: =IFERROR(AVERAGE(INDEX($B65:$W65,MATCH($B$3,$B$51:$W$51,0)-2):INDEX($B65:$W65,MATCH($B$3,$B$51:$W$51,0))),0) -> 61333333 | C7: =IFERROR(SLOPE(INDEX($B65:$W65,1):INDEX($B65:$W65,MATCH($B$3,$B$51:$W$51,0)),INDEX($B$50:$W$50,1):INDEX($B$50:$W$50,MATCH($B$3,$B$51:$W$51,0))),0) -> 9199999.8 | D7: =IF($B7=0,"",$C7/$B7) -> 0.15 | E7: =MAX(0,ROUND($B7+$C7*3,-3)) -> 88933000 | G7: =SUMIFS(TablaEgresos[Valor],TablaEgresos[Categoría],$A7,TablaEgresos[Mes],F$4) -> 0 | H7: =IF(F7="","",F7-G7) | I7: =IF(OR(F7="",F7=0),"",G7/F7) | K7: =SUMIFS(TablaEgresos[Valor],TablaEgresos[Categoría],$A7,TablaEgresos[Mes],J$4) -> 1.15e+08 | L7: =IF(J7="","",J7-K7) | M7: =IF(OR(J7="",J7=0),"",K7/J7) | O7: =SUMIFS(TablaEgresos[Valor],TablaEgresos[Categoría],$A7,TablaEgresos[Mes],N$4) -> 0 | P7: =IF(N7="","",N7-O7) | Q7: =IF(OR(N7="",N7=0),"",O7/N7) | S7: =SUMIFS(TablaEgresos[Valor],TablaEgresos[Categoría],$A7,TablaEgresos[Mes],R$4) -> 68999999 | T7: =IF(R7="","",R7-S7) | U7: =IF(OR(R7="",R7=0),"",S7/R7) | V7: 0 | W7: =SUMIFS(TablaEgresos[Valor],TablaEgresos[Categoría],$A7,TablaEgresos[Mes],V$4) -> 0 | X7: =IF(V7="","",V7-W7) -> 0 | Y7: =IF(OR(V7="",V7=0),"",W7/V7) | Z7: 0 | AA7: =SUMIFS(TablaEgresos[Valor],TablaEgresos[Categoría],$A7,TablaEgresos[Mes],Z$4) -> 0 | AB7: =IF(Z7="","",Z7-AA7) -> 0 | AC7: =IF(OR(Z7="",Z7=0),"",AA7/Z7) | AD7: 145471312 | AE7: =SUMIFS(TablaEgresos[Valor],TablaEgresos[Categoría],$A7,TablaEgresos[Mes],AD$4) -> 0 | AF7: =IF(AD7="","",AD7-AE7) -> 145471312 | AG7: =IF(OR(AD7="",AD7=0),"",AE7/AD7) -> 0 | AH7: 149030808 | AI7: =SUMIFS(TablaEgresos[Valor],TablaEgresos[Categoría],$A7,TablaEgresos[Mes],AH$4) -> 0 | AJ7: =IF(AH7="","",AH7-AI7) -> 149030808 | AK7: =IF(OR(AH7="",AH7=0),"",AI7/AH7) -> 0 | AL7: 255668507 | AM7: =SUMIFS(TablaEgresos[Valor],TablaEgresos[Categoría],$A7,TablaEgresos[Mes],AL$4) -> 0 | AN7: =IF(AL7="","",AL7-AM7) -> 255668507 | AO7: =IF(OR(AL7="",AL7=0),"",AM7/AL7) -> 0 | AP7: 380000000 | AQ7: =SUMIFS(TablaEgresos[Valor],TablaEgresos[Categoría],$A7,TablaEgresos[Mes],AP$4) -> 0 | AR7: =IF(AP7="","",AP7-AQ7) -> 380000000 | AS7: =IF(OR(AP7="",AP7=0),"",AQ7/AP7) -> 0 | AT7: =MAX(0,ROUND($B7+$C7*((YEAR(AT$4)-YEAR($B$3))*12+MONTH(AT$4)-MONTH($B$3)+1),-3)) -> 134933000 | AU7: =SUMIFS(TablaEgresos[Valor],TablaEgresos[Categoría],$A7,TablaEgresos[Mes],AT$4) -> 0 | AV7: =IF(AT7="","",AT7-AU7) -> 134933000 | AW7: =IF(OR(AT7="",AT7=0),"",AU7/AT7) -> 0 | AX7: =MAX(0,ROUND($B7+$C7*((YEAR(AX$4)-YEAR($B$3))*12+MONTH(AX$4)-MONTH($B$3)+1),-3)) -> 144133000 | AY7: =SUMIFS(TablaEgresos[Valor],TablaEgresos[Categoría],$A7,TablaEgresos[Mes],AX$4) -> 0 | AZ7: =IF(AX7="","",AX7-AY7) -> 144133000 | BA7: =IF(OR(AX7="",AX7=0),"",AY7/AX7) -> 0 | BB7: =MAX(0,ROUND($B7+$C7*((YEAR(BB$4)-YEAR($B$3))*12+MONTH(BB$4)-MONTH($B$3)+1),-3)) -> 153333000 | BC7: =SUMIFS(TablaEgresos[Valor],TablaEgresos[Categoría],$A7,TablaEgresos[Mes],BB$4) -> 0 | BD7: =IF(BB7="","",BB7-BC7) -> 153333000 | BE7: =IF(OR(BB7="",BB7=0),"",BC7/BB7) -> 0 | BF7: =MAX(0,ROUND($B7+$C7*((YEAR(BF$4)-YEAR($B$3))*12+MONTH(BF$4)-MONTH($B$3)+1),-3)) -> 162533000 | BG7: =SUMIFS(TablaEgresos[Valor],TablaEgresos[Categoría],$A7,TablaEgresos[Mes],BF$4) -> 0 | BH7: =IF(BF7="","",BF7-BG7) -> 162533000 | BI7: =IF(OR(BF7="",BF7=0),"",BG7/BF7) -> 0 | BJ7: =MAX(0,ROUND($B7+$C7*((YEAR(BJ$4)-YEAR($B$3))*12+MONTH(BJ$4)-MONTH($B$3)+1),-3)) -> 171733000 | BK7: =SUMIFS(TablaEgresos[Valor],TablaEgresos[Categoría],$A7,TablaEgresos[Mes],BJ$4) -> 0 | BL7: =IF(BJ7="","",BJ7-BK7) -> 171733000 | BM7: =IF(OR(BJ7="",BJ7=0),"",BK7/BJ7) -> 0 | BN7: =MAX(0,ROUND($B7+$C7*((YEAR(BN$4)-YEAR($B$3))*12+MONTH(BN$4)-MONTH($B$3)+1),-3)) -> 180933000 | BO7: =SUMIFS(TablaEgresos[Valor],TablaEgresos[Categoría],$A7,TablaEgresos[Mes],BN$4) -> 0 | BP7: =IF(BN7="","",BN7-BO7) -> 180933000 | BQ7: =IF(OR(BN7="",BN7=0),"",BO7/BN7) -> 0 | BR7: =MAX(0,ROUND($B7+$C7*((YEAR(BR$4)-YEAR($B$3))*12+MONTH(BR$4)-MONTH($B$3)+1),-3)) -> 190133000 | BS7: =SUMIFS(TablaEgresos[Valor],TablaEgresos[Categoría],$A7,TablaEgresos[Mes],BR$4) -> 0 | BT7: =IF(BR7="","",BR7-BS7) -> 190133000 | BU7: =IF(OR(BR7="",BR7=0),"",BS7/BR7) -> 0 | BV7: =MAX(0,ROUND($B7+$C7*((YEAR(BV$4)-YEAR($B$3))*12+MONTH(BV$4)-MONTH($B$3)+1),-3)) -> 199333000 | BW7: =SUMIFS(TablaEgresos[Valor],TablaEgresos[Categoría],$A7,TablaEgresos[Mes],BV$4) -> 0 | BX7: =IF(BV7="","",BV7-BW7) -> 199333000 | BY7: =IF(OR(BV7="",BV7=0),"",BW7/BV7) -> 0 | BZ7: =MAX(0,ROUND($B7+$C7*((YEAR(BZ$4)-YEAR($B$3))*12+MONTH(BZ$4)-MONTH($B$3)+1),-3)) -> 208533000 | CA7: =SUMIFS(TablaEgresos[Valor],TablaEgresos[Categoría],$A7,TablaEgresos[Mes],BZ$4) -> 0 | CB7: =IF(BZ7="","",BZ7-CA7) -> 208533000 | CC7: =IF(OR(BZ7="",BZ7=0),"",CA7/BZ7) -> 0 | CD7: =MAX(0,ROUND($B7+$C7*((YEAR(CD$4)-YEAR($B$3))*12+MONTH(CD$4)-MONTH($B$3)+1),-3)) -> 217733000 | CE7: =SUMIFS(TablaEgresos[Valor],TablaEgresos[Categoría],$A7,TablaEgresos[Mes],CD$4) -> 0 | CF7: =IF(CD7="","",CD7-CE7) -> 217733000 | CG7: =IF(OR(CD7="",CD7=0),"",CE7/CD7) -> 0 | CH7: =MAX(0,ROUND($B7+$C7*((YEAR(CH$4)-YEAR($B$3))*12+MONTH(CH$4)-MONTH($B$3)+1),-3)) -> 226933000 | CI7: =SUMIFS(TablaEgresos[Valor],TablaEgresos[Categoría],$A7,TablaEgresos[Mes],CH$4) -> 0 | CJ7: =IF(CH7="","",CH7-CI7) -> 226933000 | CK7: =IF(OR(CH7="",CH7=0),"",CI7/CH7) -> 0 | CL7: =MAX(0,ROUND($B7+$C7*((YEAR(CL$4)-YEAR($B$3))*12+MONTH(CL$4)-MONTH($B$3)+1),-3)) -> 236133000 | CM7: =SUMIFS(TablaEgresos[Valor],TablaEgresos[Categoría],$A7,TablaEgresos[Mes],CL$4) -> 0 | CN7: =IF(CL7="","",CL7-CM7) -> 236133000 | CO7: =IF(OR(CL7="",CL7=0),"",CM7/CL7) -> 0
A8: SOAT/Matrículas | B8: =IFERROR(AVERAGE(INDEX($B56:$W56,MATCH($B$3,$B$51:$W$51,0)-2):INDEX($B56:$W56,MATCH($B$3,$B$51:$W$51,0))),0) -> 5193888.8 | C8: =IFERROR(SLOPE(INDEX($B56:$W56,1):INDEX($B56:$W56,MATCH($B$3,$B$51:$W$51,0)),INDEX($B$50:$W$50,1):INDEX($B$50:$W$50,MATCH($B$3,$B$51:$W$51,0))),0) -> 4674499.9 | D8: =IF($B8=0,"",$C8/$B8) -> 0.9 | E8: =MAX(0,ROUND($B8+$C8*3,-3)) -> 19217000 | G8: =SUMIFS(TablaEgresos[Valor],TablaEgresos[Categoría],$A8,TablaEgresos[Mes],F$4) -> 0 | H8: =IF(F8="","",F8-G8) | I8: =IF(OR(F8="",F8=0),"",G8/F8) | K8: =SUMIFS(TablaEgresos[Valor],TablaEgresos[Categoría],$A8,TablaEgresos[Mes],J$4) -> 0 | L8: =IF(J8="","",J8-K8) | M8: =IF(OR(J8="",J8=0),"",K8/J8) | O8: =SUMIFS(TablaEgresos[Valor],TablaEgresos[Categoría],$A8,TablaEgresos[Mes],N$4) -> 0 | P8: =IF(N8="","",N8-O8) | Q8: =IF(OR(N8="",N8=0),"",O8/N8) | S8: =SUMIFS(TablaEgresos[Valor],TablaEgresos[Categoría],$A8,TablaEgresos[Mes],R$4) -> 15581666 | T8: =IF(R8="","",R8-S8) | U8: =IF(OR(R8="",R8=0),"",S8/R8) | V8: 0 | W8: =SUMIFS(TablaEgresos[Valor],TablaEgresos[Categoría],$A8,TablaEgresos[Mes],V$4) -> 10465680 | X8: =IF(V8="","",V8-W8) -> -10465680 | Y8: =IF(OR(V8="",V8=0),"",W8/V8) | Z8: 17000000 | AA8: =SUMIFS(TablaEgresos[Valor],TablaEgresos[Categoría],$A8,TablaEgresos[Mes],Z$4) -> 0 | AB8: =IF(Z8="","",Z8-AA8) -> 17000000 | AC8: =IF(OR(Z8="",Z8=0),"",AA8/Z8) -> 0 | AD8: 22000000 | AE8: =SUMIFS(TablaEgresos[Valor],TablaEgresos[Categoría],$A8,TablaEgresos[Mes],AD$4) -> 0 | AF8: =IF(AD8="","",AD8-AE8) -> 22000000 | AG8: =IF(OR(AD8="",AD8=0),"",AE8/AD8) -> 0 | AH8: 17000000 | AI8: =SUMIFS(TablaEgresos[Valor],TablaEgresos[Categoría],$A8,TablaEgresos[Mes],AH$4) -> 0 | AJ8: =IF(AH8="","",AH8-AI8) -> 17000000 | AK8: =IF(OR(AH8="",AH8=0),"",AI8/AH8) -> 0 | AL8: 17000000 | AM8: =SUMIFS(TablaEgresos[Valor],TablaEgresos[Categoría],$A8,TablaEgresos[Mes],AL$4) -> 0 | AN8: =IF(AL8="","",AL8-AM8) -> 17000000 | AO8: =IF(OR(AL8="",AL8=0),"",AM8/AL8) -> 0 | AP8: 17000000 | AQ8: =SUMIFS(TablaEgresos[Valor],TablaEgresos[Categoría],$A8,TablaEgresos[Mes],AP$4) -> 0 | AR8: =IF(AP8="","",AP8-AQ8) -> 17000000 | AS8: =IF(OR(AP8="",AP8=0),"",AQ8/AP8) -> 0 | AT8: 17000000 | AU8: =SUMIFS(TablaEgresos[Valor],TablaEgresos[Categoría],$A8,TablaEgresos[Mes],AT$4) -> 0 | AV8: =IF(AT8="","",AT8-AU8) -> 17000000 | AW8: =IF(OR(AT8="",AT8=0),"",AU8/AT8) -> 0 | AX8: 17000000 | AY8: =SUMIFS(TablaEgresos[Valor],TablaEgresos[Categoría],$A8,TablaEgresos[Mes],AX$4) -> 0 | AZ8: =IF(AX8="","",AX8-AY8) -> 17000000 | BA8: =IF(OR(AX8="",AX8=0),"",AY8/AX8) -> 0 | BB8: 17000000 | BC8: =SUMIFS(TablaEgresos[Valor],TablaEgresos[Categoría],$A8,TablaEgresos[Mes],BB$4) -> 0 | BD8: =IF(BB8="","",BB8-BC8) -> 17000000 | BE8: =IF(OR(BB8="",BB8=0),"",BC8/BB8) -> 0 | BF8: 17000000 | BG8: =SUMIFS(TablaEgresos[Valor],TablaEgresos[Categoría],$A8,TablaEgresos[Mes],BF$4) -> 0 | BH8: =IF(BF8="","",BF8-BG8) -> 17000000 | BI8: =IF(OR(BF8="",BF8=0),"",BG8/BF8) -> 0 | BJ8: 17000000 | BK8: =SUMIFS(TablaEgresos[Valor],TablaEgresos[Categoría],$A8,TablaEgresos[Mes],BJ$4) -> 0 | BL8: =IF(BJ8="","",BJ8-BK8) -> 17000000 | BM8: =IF(OR(BJ8="",BJ8=0),"",BK8/BJ8) -> 0 | BN8: 17000000 | BO8: =SUMIFS(TablaEgresos[Valor],TablaEgresos[Categoría],$A8,TablaEgresos[Mes],BN$4) -> 0 | BP8: =IF(BN8="","",BN8-BO8) -> 17000000 | BQ8: =IF(OR(BN8="",BN8=0),"",BO8/BN8) -> 0 | BR8: 17000000 | BS8: =SUMIFS(TablaEgresos[Valor],TablaEgresos[Categoría],$A8,TablaEgresos[Mes],BR$4) -> 0 | BT8: =IF(BR8="","",BR8-BS8) -> 17000000 | BU8: =IF(OR(BR8="",BR8=0),"",BS8/BR8) -> 0 | BV8: 17000000 | BW8: =SUMIFS(TablaEgresos[Valor],TablaEgresos[Categoría],$A8,TablaEgresos[Mes],BV$4) -> 0 | BX8: =IF(BV8="","",BV8-BW8) -> 17000000 | BY8: =IF(OR(BV8="",BV8=0),"",BW8/BV8) -> 0 | BZ8: 17000000 | CA8: =SUMIFS(TablaEgresos[Valor],TablaEgresos[Categoría],$A8,TablaEgresos[Mes],BZ$4) -> 0 | CB8: =IF(BZ8="","",BZ8-CA8) -> 17000000 | CC8: =IF(OR(BZ8="",BZ8=0),"",CA8/BZ8) -> 0 | CD8: 17000000 | CE8: =SUMIFS(TablaEgresos[Valor],TablaEgresos[Categoría],$A8,TablaEgresos[Mes],CD$4) -> 0 | CF8: =IF(CD8="","",CD8-CE8) -> 17000000 | CG8: =IF(OR(CD8="",CD8=0),"",CE8/CD8) -> 0 | CH8: 17000000 | CI8: =SUMIFS(TablaEgresos[Valor],TablaEgresos[Categoría],$A8,TablaEgresos[Mes],CH$4) -> 0 | CJ8: =IF(CH8="","",CH8-CI8) -> 17000000 | CK8: =IF(OR(CH8="",CH8=0),"",CI8/CH8) -> 0 | CL8: 17000000 | CM8: =SUMIFS(TablaEgresos[Valor],TablaEgresos[Categoría],$A8,TablaEgresos[Mes],CL$4) -> 0 | CN8: =IF(CL8="","",CL8-CM8) -> 17000000 | CO8: =IF(OR(CL8="",CL8=0),"",CM8/CL8) -> 0
A9: Seguros (Hunter) | B9: =IFERROR(AVERAGE(INDEX($B55:$W55,MATCH($B$3,$B$51:$W$51,0)-2):INDEX($B55:$W55,MATCH($B$3,$B$51:$W$51,0))),0) -> 0 | C9: =IFERROR(SLOPE(INDEX($B55:$W55,1):INDEX($B55:$W55,MATCH($B$3,$B$51:$W$51,0)),INDEX($B$50:$W$50,1):INDEX($B$50:$W$50,MATCH($B$3,$B$51:$W$51,0))),0) -> 0 | D9: =IF($B9=0,"",$C9/$B9) | E9: =MAX(0,ROUND($B9+$C9*3,-3)) -> 0 | G9: =SUMIFS(TablaEgresos[Valor],TablaEgresos[Categoría],$A9,TablaEgresos[Mes],F$4) -> 0 | H9: =IF(F9="","",F9-G9) | I9: =IF(OR(F9="",F9=0),"",G9/F9) | K9: =SUMIFS(TablaEgresos[Valor],TablaEgresos[Categoría],$A9,TablaEgresos[Mes],J$4) -> 0 | L9: =IF(J9="","",J9-K9) | M9: =IF(OR(J9="",J9=0),"",K9/J9) | O9: =SUMIFS(TablaEgresos[Valor],TablaEgresos[Categoría],$A9,TablaEgresos[Mes],N$4) -> 0 | P9: =IF(N9="","",N9-O9) | Q9: =IF(OR(N9="",N9=0),"",O9/N9) | S9: =SUMIFS(TablaEgresos[Valor],TablaEgresos[Categoría],$A9,TablaEgresos[Mes],R$4) -> 0 | T9: =IF(R9="","",R9-S9) | U9: =IF(OR(R9="",R9=0),"",S9/R9) | V9: 2200000 | W9: =SUMIFS(TablaEgresos[Valor],TablaEgresos[Categoría],$A9,TablaEgresos[Mes],V$4) -> 0 | X9: =IF(V9="","",V9-W9) -> 2200000 | Y9: =IF(OR(V9="",V9=0),"",W9/V9) -> 0 | Z9: 4000000 | AA9: =SUMIFS(TablaEgresos[Valor],TablaEgresos[Categoría],$A9,TablaEgresos[Mes],Z$4) -> 0 | AB9: =IF(Z9="","",Z9-AA9) -> 4000000 | AC9: =IF(OR(Z9="",Z9=0),"",AA9/Z9) -> 0 | AD9: 4000000 | AE9: =SUMIFS(TablaEgresos[Valor],TablaEgresos[Categoría],$A9,TablaEgresos[Mes],AD$4) -> 0 | AF9: =IF(AD9="","",AD9-AE9) -> 4000000 | AG9: =IF(OR(AD9="",AD9=0),"",AE9/AD9) -> 0 | AH9: 4000000 | AI9: =SUMIFS(TablaEgresos[Valor],TablaEgresos[Categoría],$A9,TablaEgresos[Mes],AH$4) -> 0 | AJ9: =IF(AH9="","",AH9-AI9) -> 4000000 | AK9: =IF(OR(AH9="",AH9=0),"",AI9/AH9) -> 0 | AL9: 4000000 | AM9: =SUMIFS(TablaEgresos[Valor],TablaEgresos[Categoría],$A9,TablaEgresos[Mes],AL$4) -> 0 | AN9: =IF(AL9="","",AL9-AM9) -> 4000000 | AO9: =IF(OR(AL9="",AL9=0),"",AM9/AL9) -> 0 | AP9: 4000000 | AQ9: =SUMIFS(TablaEgresos[Valor],TablaEgresos[Categoría],$A9,TablaEgresos[Mes],AP$4) -> 0 | AR9: =IF(AP9="","",AP9-AQ9) -> 4000000 | AS9: =IF(OR(AP9="",AP9=0),"",AQ9/AP9) -> 0 | AT9: 4000000 | AU9: =SUMIFS(TablaEgresos[Valor],TablaEgresos[Categoría],$A9,TablaEgresos[Mes],AT$4) -> 0 | AV9: =IF(AT9="","",AT9-AU9) -> 4000000 | AW9: =IF(OR(AT9="",AT9=0),"",AU9/AT9) -> 0 | AX9: 4000000 | AY9: =SUMIFS(TablaEgresos[Valor],TablaEgresos[Categoría],$A9,TablaEgresos[Mes],AX$4) -> 0 | AZ9: =IF(AX9="","",AX9-AY9) -> 4000000 | BA9: =IF(OR(AX9="",AX9=0),"",AY9/AX9) -> 0 | BB9: 4000000 | BC9: =SUMIFS(TablaEgresos[Valor],TablaEgresos[Categoría],$A9,TablaEgresos[Mes],BB$4) -> 0 | BD9: =IF(BB9="","",BB9-BC9) -> 4000000 | BE9: =IF(OR(BB9="",BB9=0),"",BC9/BB9) -> 0 | BF9: 4000000 | BG9: =SUMIFS(TablaEgresos[Valor],TablaEgresos[Categoría],$A9,TablaEgresos[Mes],BF$4) -> 0 | BH9: =IF(BF9="","",BF9-BG9) -> 4000000 | BI9: =IF(OR(BF9="",BF9=0),"",BG9/BF9) -> 0 | BJ9: 4000000 | BK9: =SUMIFS(TablaEgresos[Valor],TablaEgresos[Categoría],$A9,TablaEgresos[Mes],BJ$4) -> 0 | BL9: =IF(BJ9="","",BJ9-BK9) -> 4000000 | BM9: =IF(OR(BJ9="",BJ9=0),"",BK9/BJ9) -> 0 | BN9: 4000000 | BO9: =SUMIFS(TablaEgresos[Valor],TablaEgresos[Categoría],$A9,TablaEgresos[Mes],BN$4) -> 0 | BP9: =IF(BN9="","",BN9-BO9) -> 4000000 | BQ9: =IF(OR(BN9="",BN9=0),"",BO9/BN9) -> 0 | BR9: 4000000 | BS9: =SUMIFS(TablaEgresos[Valor],TablaEgresos[Categoría],$A9,TablaEgresos[Mes],BR$4) -> 0 | BT9: =IF(BR9="","",BR9-BS9) -> 4000000 | BU9: =IF(OR(BR9="",BR9=0),"",BS9/BR9) -> 0 | BV9: 4000000 | BW9: =SUMIFS(TablaEgresos[Valor],TablaEgresos[Categoría],$A9,TablaEgresos[Mes],BV$4) -> 0 | BX9: =IF(BV9="","",BV9-BW9) -> 4000000 | BY9: =IF(OR(BV9="",BV9=0),"",BW9/BV9) -> 0 | BZ9: 4000000 | CA9: =SUMIFS(TablaEgresos[Valor],TablaEgresos[Categoría],$A9,TablaEgresos[Mes],BZ$4) -> 0 | CB9: =IF(BZ9="","",BZ9-CA9) -> 4000000 | CC9: =IF(OR(BZ9="",BZ9=0),"",CA9/BZ9) -> 0 | CD9: 4000000 | CE9: =SUMIFS(TablaEgresos[Valor],TablaEgresos[Categoría],$A9,TablaEgresos[Mes],CD$4) -> 0 | CF9: =IF(CD9="","",CD9-CE9) -> 4000000 | CG9: =IF(OR(CD9="",CD9=0),"",CE9/CD9) -> 0 | CH9: 4000000 | CI9: =SUMIFS(TablaEgresos[Valor],TablaEgresos[Categoría],$A9,TablaEgresos[Mes],CH$4) -> 0 | CJ9: =IF(CH9="","",CH9-CI9) -> 4000000 | CK9: =IF(OR(CH9="",CH9=0),"",CI9/CH9) -> 0 | CL9: 4000000 | CM9: =SUMIFS(TablaEgresos[Valor],TablaEgresos[Categoría],$A9,TablaEgresos[Mes],CL$4) -> 0 | CN9: =IF(CL9="","",CL9-CM9) -> 4000000 | CO9: =IF(OR(CL9="",CL9=0),"",CM9/CL9) -> 0
A10: Subtotal Costo de producto | B10: =SUM(B7:B9) -> 66527222 | C10: =SUM(C7:C9) -> 13874500 | D10: =IF(B10=0,"",C10/B10) -> 0.20855372 | E10: =SUM(E7:E9) -> 108150000 | F10: =SUM(F7:F9) -> 0 | G10: =SUM(G7:G9) -> 0 | H10: =SUM(H7:H9) -> 0 | I10: =IF(F10=0,"",G10/F10) | J10: =SUM(J7:J9) -> 0 | K10: =SUM(K7:K9) -> 1.15e+08 | L10: =SUM(L7:L9) -> 0 | M10: =IF(J10=0,"",K10/J10) | N10: =SUM(N7:N9) -> 0 | O10: =SUM(O7:O9) -> 0 | P10: =SUM(P7:P9) -> 0 | Q10: =IF(N10=0,"",O10/N10) | R10: =SUM(R7:R9) -> 0 | S10: =SUM(S7:S9) -> 84581665 | T10: =SUM(T7:T9) -> 0 | U10: =IF(R10=0,"",S10/R10) | V10: =SUM(V7:V9) -> 2200000 | W10: =SUM(W7:W9) -> 10465680 | X10: =SUM(X7:X9) -> -8265680 | Y10: =IF(V10=0,"",W10/V10) -> 4.7571273 | Z10: =SUM(Z7:Z9) -> 21000000 | AA10: =SUM(AA7:AA9) -> 0 | AB10: =SUM(AB7:AB9) -> 21000000 | AC10: =IF(Z10=0,"",AA10/Z10) -> 0 | AD10: =SUM(AD7:AD9) -> 171471312 | AE10: =SUM(AE7:AE9) -> 0 | AF10: =SUM(AF7:AF9) -> 171471312 | AG10: =IF(AD10=0,"",AE10/AD10) -> 0 | AH10: =SUM(AH7:AH9) -> 170030808 | AI10: =SUM(AI7:AI9) -> 0 | AJ10: =SUM(AJ7:AJ9) -> 170030808 | AK10: =IF(AH10=0,"",AI10/AH10) -> 0 | AL10: =SUM(AL7:AL9) -> 276668507 | AM10: =SUM(AM7:AM9) -> 0 | AN10: =SUM(AN7:AN9) -> 276668507 | AO10: =IF(AL10=0,"",AM10/AL10) -> 0 | AP10: =SUM(AP7:AP9) -> 401000000 | AQ10: =SUM(AQ7:AQ9) -> 0 | AR10: =SUM(AR7:AR9) -> 401000000 | AS10: =IF(AP10=0,"",AQ10/AP10) -> 0 | AT10: =SUM(AT7:AT9) -> 155933000 | AU10: =SUM(AU7:AU9) -> 0 | AV10: =SUM(AV7:AV9) -> 155933000 | AW10: =IF(AT10=0,"",AU10/AT10) -> 0 | AX10: =SUM(AX7:AX9) -> 165133000 | AY10: =SUM(AY7:AY9) -> 0 | AZ10: =SUM(AZ7:AZ9) -> 165133000 | BA10: =IF(AX10=0,"",AY10/AX10) -> 0 | BB10: =SUM(BB7:BB9) -> 174333000 | BC10: =SUM(BC7:BC9) -> 0 | BD10: =SUM(BD7:BD9) -> 174333000 | BE10: =IF(BB10=0,"",BC10/BB10) -> 0 | BF10: =SUM(BF7:BF9) -> 183533000 | BG10: =SUM(BG7:BG9) -> 0 | BH10: =SUM(BH7:BH9) -> 183533000 | BI10: =IF(BF10=0,"",BG10/BF10) -> 0 | BJ10: =SUM(BJ7:BJ9) -> 192733000 | BK10: =SUM(BK7:BK9) -> 0 | BL10: =SUM(BL7:BL9) -> 192733000 | BM10: =IF(BJ10=0,"",BK10/BJ10) -> 0 | BN10: =SUM(BN7:BN9) -> 201933000 | BO10: =SUM(BO7:BO9) -> 0 | BP10: =SUM(BP7:BP9) -> 201933000 | BQ10: =IF(BN10=0,"",BO10/BN10) -> 0 | BR10: =SUM(BR7:BR9) -> 211133000 | BS10: =SUM(BS7:BS9) -> 0 | BT10: =SUM(BT7:BT9) -> 211133000 | BU10: =IF(BR10=0,"",BS10/BR10) -> 0 | BV10: =SUM(BV7:BV9) -> 220333000 | BW10: =SUM(BW7:BW9) -> 0 | BX10: =SUM(BX7:BX9) -> 220333000 | BY10: =IF(BV10=0,"",BW10/BV10) -> 0 | BZ10: =SUM(BZ7:BZ9) -> 229533000 | CA10: =SUM(CA7:CA9) -> 0 | CB10: =SUM(CB7:CB9) -> 229533000 | CC10: =IF(BZ10=0,"",CA10/BZ10) -> 0 | CD10: =SUM(CD7:CD9) -> 238733000 | CE10: =SUM(CE7:CE9) -> 0 | CF10: =SUM(CF7:CF9) -> 238733000 | CG10: =IF(CD10=0,"",CE10/CD10) -> 0 | CH10: =SUM(CH7:CH9) -> 247933000 | CI10: =SUM(CI7:CI9) -> 0 | CJ10: =SUM(CJ7:CJ9) -> 247933000 | CK10: =IF(CH10=0,"",CI10/CH10) -> 0 | CL10: =SUM(CL7:CL9) -> 257133000 | CM10: =SUM(CM7:CM9) -> 0 | CN10: =SUM(CN7:CN9) -> 257133000 | CO10: =IF(CL10=0,"",CM10/CL10) -> 0
A11: OPERACIÓN
A12: Arriendos | B12: =IFERROR(AVERAGE(INDEX($B53:$W53,MATCH($B$3,$B$51:$W$51,0)-2):INDEX($B53:$W53,MATCH($B$3,$B$51:$W$51,0))),0) -> 0 | C12: =IFERROR(SLOPE(INDEX($B53:$W53,1):INDEX($B53:$W53,MATCH($B$3,$B$51:$W$51,0)),INDEX($B$50:$W$50,1):INDEX($B$50:$W$50,MATCH($B$3,$B$51:$W$51,0))),0) -> 0 | D12: =IF($B12=0,"",$C12/$B12) | E12: =MAX(0,ROUND($B12+$C12*3,-3)) -> 0 | G12: =SUMIFS(TablaEgresos[Valor],TablaEgresos[Categoría],$A12,TablaEgresos[Mes],F$4) -> 0 | H12: =IF(F12="","",F12-G12) | I12: =IF(OR(F12="",F12=0),"",G12/F12) | K12: =SUMIFS(TablaEgresos[Valor],TablaEgresos[Categoría],$A12,TablaEgresos[Mes],J$4) -> 0 | L12: =IF(J12="","",J12-K12) | M12: =IF(OR(J12="",J12=0),"",K12/J12) | O12: =SUMIFS(TablaEgresos[Valor],TablaEgresos[Categoría],$A12,TablaEgresos[Mes],N$4) -> 0 | P12: =IF(N12="","",N12-O12) | Q12: =IF(OR(N12="",N12=0),"",O12/N12) | S12: =SUMIFS(TablaEgresos[Valor],TablaEgresos[Categoría],$A12,TablaEgresos[Mes],R$4) -> 0 | T12: =IF(R12="","",R12-S12) | U12: =IF(OR(R12="",R12=0),"",S12/R12) | V12: 8000000 | W12: =SUMIFS(TablaEgresos[Valor],TablaEgresos[Categoría],$A12,TablaEgresos[Mes],V$4) -> 0 | X12: =IF(V12="","",V12-W12) -> 8000000 | Y12: =IF(OR(V12="",V12=0),"",W12/V12) -> 0 | Z12: 8350000 | AA12: =SUMIFS(TablaEgresos[Valor],TablaEgresos[Categoría],$A12,TablaEgresos[Mes],Z$4) -> 0 | AB12: =IF(Z12="","",Z12-AA12) -> 8350000 | AC12: =IF(OR(Z12="",Z12=0),"",AA12/Z12) -> 0 | AD12: 8350000 | AE12: =SUMIFS(TablaEgresos[Valor],TablaEgresos[Categoría],$A12,TablaEgresos[Mes],AD$4) -> 0 | AF12: =IF(AD12="","",AD12-AE12) -> 8350000 | AG12: =IF(OR(AD12="",AD12=0),"",AE12/AD12) -> 0 | AH12: 8350000 | AI12: =SUMIFS(TablaEgresos[Valor],TablaEgresos[Categoría],$A12,TablaEgresos[Mes],AH$4) -> 0 | AJ12: =IF(AH12="","",AH12-AI12) -> 8350000 | AK12: =IF(OR(AH12="",AH12=0),"",AI12/AH12) -> 0 | AL12: 8350000 | AM12: =SUMIFS(TablaEgresos[Valor],TablaEgresos[Categoría],$A12,TablaEgresos[Mes],AL$4) -> 0 | AN12: =IF(AL12="","",AL12-AM12) -> 8350000 | AO12: =IF(OR(AL12="",AL12=0),"",AM12/AL12) -> 0 | AP12: 8350000 | AQ12: =SUMIFS(TablaEgresos[Valor],TablaEgresos[Categoría],$A12,TablaEgresos[Mes],AP$4) -> 0 | AR12: =IF(AP12="","",AP12-AQ12) -> 8350000 | AS12: =IF(OR(AP12="",AP12=0),"",AQ12/AP12) -> 0 | AT12: 8350000 | AU12: =SUMIFS(TablaEgresos[Valor],TablaEgresos[Categoría],$A12,TablaEgresos[Mes],AT$4) -> 0 | AV12: =IF(AT12="","",AT12-AU12) -> 8350000 | AW12: =IF(OR(AT12="",AT12=0),"",AU12/AT12) -> 0 | AX12: 8350000 | AY12: =SUMIFS(TablaEgresos[Valor],TablaEgresos[Categoría],$A12,TablaEgresos[Mes],AX$4) -> 0 | AZ12: =IF(AX12="","",AX12-AY12) -> 8350000 | BA12: =IF(OR(AX12="",AX12=0),"",AY12/AX12) -> 0 | BB12: 8350000 | BC12: =SUMIFS(TablaEgresos[Valor],TablaEgresos[Categoría],$A12,TablaEgresos[Mes],BB$4) -> 0 | BD12: =IF(BB12="","",BB12-BC12) -> 8350000 | BE12: =IF(OR(BB12="",BB12=0),"",BC12/BB12) -> 0 | BF12: 8350000 | BG12: =SUMIFS(TablaEgresos[Valor],TablaEgresos[Categoría],$A12,TablaEgresos[Mes],BF$4) -> 0 | BH12: =IF(BF12="","",BF12-BG12) -> 8350000 | BI12: =IF(OR(BF12="",BF12=0),"",BG12/BF12) -> 0 | BJ12: 8350000 | BK12: =SUMIFS(TablaEgresos[Valor],TablaEgresos[Categoría],$A12,TablaEgresos[Mes],BJ$4) -> 0 | BL12: =IF(BJ12="","",BJ12-BK12) -> 8350000 | BM12: =IF(OR(BJ12="",BJ12=0),"",BK12/BJ12) -> 0 | BN12: 8350000 | BO12: =SUMIFS(TablaEgresos[Valor],TablaEgresos[Categoría],$A12,TablaEgresos[Mes],BN$4) -> 0 | BP12: =IF(BN12="","",BN12-BO12) -> 8350000 | BQ12: =IF(OR(BN12="",BN12=0),"",BO12/BN12) -> 0 | BR12: 8350000 | BS12: =SUMIFS(TablaEgresos[Valor],TablaEgresos[Categoría],$A12,TablaEgresos[Mes],BR$4) -> 0 | BT12: =IF(BR12="","",BR12-BS12) -> 8350000 | BU12: =IF(OR(BR12="",BR12=0),"",BS12/BR12) -> 0 | BV12: 8350000 | BW12: =SUMIFS(TablaEgresos[Valor],TablaEgresos[Categoría],$A12,TablaEgresos[Mes],BV$4) -> 0 | BX12: =IF(BV12="","",BV12-BW12) -> 8350000 | BY12: =IF(OR(BV12="",BV12=0),"",BW12/BV12) -> 0 | BZ12: 8350000 | CA12: =SUMIFS(TablaEgresos[Valor],TablaEgresos[Categoría],$A12,TablaEgresos[Mes],BZ$4) -> 0 | CB12: =IF(BZ12="","",BZ12-CA12) -> 8350000 | CC12: =IF(OR(BZ12="",BZ12=0),"",CA12/BZ12) -> 0 | CD12: 8350000 | CE12: =SUMIFS(TablaEgresos[Valor],TablaEgresos[Categoría],$A12,TablaEgresos[Mes],CD$4) -> 0 | CF12: =IF(CD12="","",CD12-CE12) -> 8350000 | CG12: =IF(OR(CD12="",CD12=0),"",CE12/CD12) -> 0 | CH12: 8350000 | CI12: =SUMIFS(TablaEgresos[Valor],TablaEgresos[Categoría],$A12,TablaEgresos[Mes],CH$4) -> 0 | CJ12: =IF(CH12="","",CH12-CI12) -> 8350000 | CK12: =IF(OR(CH12="",CH12=0),"",CI12/CH12) -> 0 | CL12: 8350000 | CM12: =SUMIFS(TablaEgresos[Valor],TablaEgresos[Categoría],$A12,TablaEgresos[Mes],CL$4) -> 0 | CN12: =IF(CL12="","",CL12-CM12) -> 8350000 | CO12: =IF(OR(CL12="",CL12=0),"",CM12/CL12) -> 0
A13: Tecnología y software | B13: =IFERROR(AVERAGE(INDEX($B54:$W54,MATCH($B$3,$B$51:$W$51,0)-2):INDEX($B54:$W54,MATCH($B$3,$B$51:$W$51,0))),0) -> 3970644.5 | C13: =IFERROR(SLOPE(INDEX($B54:$W54,1):INDEX($B54:$W54,MATCH($B$3,$B$51:$W$51,0)),INDEX($B$50:$W$50,1):INDEX($B$50:$W$50,MATCH($B$3,$B$51:$W$51,0))),0) -> 1126204.4 | D13: =IF($B13=0,"",$C13/$B13) -> 0.28363265 | E13: =MAX(0,ROUND($B13+$C13*3,-3)) -> 7349000 | G13: =SUMIFS(TablaEgresos[Valor],TablaEgresos[Categoría],$A13,TablaEgresos[Mes],F$4) -> 468019.13 | H13: =IF(F13="","",F13-G13) | I13: =IF(OR(F13="",F13=0),"",G13/F13) | K13: =SUMIFS(TablaEgresos[Valor],TablaEgresos[Categoría],$A13,TablaEgresos[Mes],J$4) -> 3648770.1 | L13: =IF(J13="","",J13-K13) | M13: =IF(OR(J13="",J13=0),"",K13/J13) | O13: =SUMIFS(TablaEgresos[Valor],TablaEgresos[Categoría],$A13,TablaEgresos[Mes],N$4) -> 4237309.4 | P13: =IF(N13="","",N13-O13) | Q13: =IF(OR(N13="",N13=0),"",O13/N13) | S13: =SUMIFS(TablaEgresos[Valor],TablaEgresos[Categoría],$A13,TablaEgresos[Mes],R$4) -> 4025854.1 | T13: =IF(R13="","",R13-S13) | U13: =IF(OR(R13="",R13=0),"",S13/R13) | V13: 4000000 | W13: =SUMIFS(TablaEgresos[Valor],TablaEgresos[Categoría],$A13,TablaEgresos[Mes],V$4) -> 4808607.4 | X13: =IF(V13="","",V13-W13) -> -808607.42 | Y13: =IF(OR(V13="",V13=0),"",W13/V13) -> 1.2021519 | Z13: 4000000 | AA13: =SUMIFS(TablaEgresos[Valor],TablaEgresos[Categoría],$A13,TablaEgresos[Mes],Z$4) -> 0 | AB13: =IF(Z13="","",Z13-AA13) -> 4000000 | AC13: =IF(OR(Z13="",Z13=0),"",AA13/Z13) -> 0 | AD13: 4000000 | AE13: =SUMIFS(TablaEgresos[Valor],TablaEgresos[Categoría],$A13,TablaEgresos[Mes],AD$4) -> 0 | AF13: =IF(AD13="","",AD13-AE13) -> 4000000 | AG13: =IF(OR(AD13="",AD13=0),"",AE13/AD13) -> 0 | AH13: 4000000 | AI13: =SUMIFS(TablaEgresos[Valor],TablaEgresos[Categoría],$A13,TablaEgresos[Mes],AH$4) -> 0 | AJ13: =IF(AH13="","",AH13-AI13) -> 4000000 | AK13: =IF(OR(AH13="",AH13=0),"",AI13/AH13) -> 0 | AL13: 4000000 | AM13: =SUMIFS(TablaEgresos[Valor],TablaEgresos[Categoría],$A13,TablaEgresos[Mes],AL$4) -> 0 | AN13: =IF(AL13="","",AL13-AM13) -> 4000000 | AO13: =IF(OR(AL13="",AL13=0),"",AM13/AL13) -> 0 | AP13: 4000000 | AQ13: =SUMIFS(TablaEgresos[Valor],TablaEgresos[Categoría],$A13,TablaEgresos[Mes],AP$4) -> 0 | AR13: =IF(AP13="","",AP13-AQ13) -> 4000000 | AS13: =IF(OR(AP13="",AP13=0),"",AQ13/AP13) -> 0 | AT13: 4000000 | AU13: =SUMIFS(TablaEgresos[Valor],TablaEgresos[Categoría],$A13,TablaEgresos[Mes],AT$4) -> 0 | AV13: =IF(AT13="","",AT13-AU13) -> 4000000 | AW13: =IF(OR(AT13="",AT13=0),"",AU13/AT13) -> 0 | AX13: 4000000 | AY13: =SUMIFS(TablaEgresos[Valor],TablaEgresos[Categoría],$A13,TablaEgresos[Mes],AX$4) -> 0 | AZ13: =IF(AX13="","",AX13-AY13) -> 4000000 | BA13: =IF(OR(AX13="",AX13=0),"",AY13/AX13) -> 0 | BB13: 4000000 | BC13: =SUMIFS(TablaEgresos[Valor],TablaEgresos[Categoría],$A13,TablaEgresos[Mes],BB$4) -> 0 | BD13: =IF(BB13="","",BB13-BC13) -> 4000000 | BE13: =IF(OR(BB13="",BB13=0),"",BC13/BB13) -> 0 | BF13: 4000000 | BG13: =SUMIFS(TablaEgresos[Valor],TablaEgresos[Categoría],$A13,TablaEgresos[Mes],BF$4) -> 0 | BH13: =IF(BF13="","",BF13-BG13) -> 4000000 | BI13: =IF(OR(BF13="",BF13=0),"",BG13/BF13) -> 0 | BJ13: 4000000 | BK13: =SUMIFS(TablaEgresos[Valor],TablaEgresos[Categoría],$A13,TablaEgresos[Mes],BJ$4) -> 0 | BL13: =IF(BJ13="","",BJ13-BK13) -> 4000000 | BM13: =IF(OR(BJ13="",BJ13=0),"",BK13/BJ13) -> 0 | BN13: 4000000 | BO13: =SUMIFS(TablaEgresos[Valor],TablaEgresos[Categoría],$A13,TablaEgresos[Mes],BN$4) -> 0 | BP13: =IF(BN13="","",BN13-BO13) -> 4000000 | BQ13: =IF(OR(BN13="",BN13=0),"",BO13/BN13) -> 0 | BR13: 4000000 | BS13: =SUMIFS(TablaEgresos[Valor],TablaEgresos[Categoría],$A13,TablaEgresos[Mes],BR$4) -> 0 | BT13: =IF(BR13="","",BR13-BS13) -> 4000000 | BU13: =IF(OR(BR13="",BR13=0),"",BS13/BR13) -> 0 | BV13: 4000000 | BW13: =SUMIFS(TablaEgresos[Valor],TablaEgresos[Categoría],$A13,TablaEgresos[Mes],BV$4) -> 0 | BX13: =IF(BV13="","",BV13-BW13) -> 4000000 | BY13: =IF(OR(BV13="",BV13=0),"",BW13/BV13) -> 0 | BZ13: 4000000 | CA13: =SUMIFS(TablaEgresos[Valor],TablaEgresos[Categoría],$A13,TablaEgresos[Mes],BZ$4) -> 0 | CB13: =IF(BZ13="","",BZ13-CA13) -> 4000000 | CC13: =IF(OR(BZ13="",BZ13=0),"",CA13/BZ13) -> 0 | CD13: 4000000 | CE13: =SUMIFS(TablaEgresos[Valor],TablaEgresos[Categoría],$A13,TablaEgresos[Mes],CD$4) -> 0 | CF13: =IF(CD13="","",CD13-CE13) -> 4000000 | CG13: =IF(OR(CD13="",CD13=0),"",CE13/CD13) -> 0 | CH13: 4000000 | CI13: =SUMIFS(TablaEgresos[Valor],TablaEgresos[Categoría],$A13,TablaEgresos[Mes],CH$4) -> 0 | CJ13: =IF(CH13="","",CH13-CI13) -> 4000000 | CK13: =IF(OR(CH13="",CH13=0),"",CI13/CH13) -> 0 | CL13: 4000000 | CM13: =SUMIFS(TablaEgresos[Valor],TablaEgresos[Categoría],$A13,TablaEgresos[Mes],CL$4) -> 0 | CN13: =IF(CL13="","",CL13-CM13) -> 4000000 | CO13: =IF(OR(CL13="",CL13=0),"",CM13/CL13) -> 0
A14: Mobiliario/planta/equipo | B14: =IFERROR(AVERAGE(INDEX($B57:$W57,MATCH($B$3,$B$51:$W$51,0)-2):INDEX($B57:$W57,MATCH($B$3,$B$51:$W$51,0))),0) -> 0 | C14: =IFERROR(SLOPE(INDEX($B57:$W57,1):INDEX($B57:$W57,MATCH($B$3,$B$51:$W$51,0)),INDEX($B$50:$W$50,1):INDEX($B$50:$W$50,MATCH($B$3,$B$51:$W$51,0))),0) -> 0 | D14: =IF($B14=0,"",$C14/$B14) | E14: =MAX(0,ROUND($B14+$C14*3,-3)) -> 0 | G14: =SUMIFS(TablaEgresos[Valor],TablaEgresos[Categoría],$A14,TablaEgresos[Mes],F$4) -> 0 | H14: =IF(F14="","",F14-G14) | I14: =IF(OR(F14="",F14=0),"",G14/F14) | K14: =SUMIFS(TablaEgresos[Valor],TablaEgresos[Categoría],$A14,TablaEgresos[Mes],J$4) -> 0 | L14: =IF(J14="","",J14-K14) | M14: =IF(OR(J14="",J14=0),"",K14/J14) | O14: =SUMIFS(TablaEgresos[Valor],TablaEgresos[Categoría],$A14,TablaEgresos[Mes],N$4) -> 0 | P14: =IF(N14="","",N14-O14) | Q14: =IF(OR(N14="",N14=0),"",O14/N14) | S14: =SUMIFS(TablaEgresos[Valor],TablaEgresos[Categoría],$A14,TablaEgresos[Mes],R$4) -> 0 | T14: =IF(R14="","",R14-S14) | U14: =IF(OR(R14="",R14=0),"",S14/R14) | V14: 0 | W14: =SUMIFS(TablaEgresos[Valor],TablaEgresos[Categoría],$A14,TablaEgresos[Mes],V$4) -> 71100 | X14: =IF(V14="","",V14-W14) -> -71100 | Y14: =IF(OR(V14="",V14=0),"",W14/V14) | Z14: 500000 | AA14: =SUMIFS(TablaEgresos[Valor],TablaEgresos[Categoría],$A14,TablaEgresos[Mes],Z$4) -> 0 | AB14: =IF(Z14="","",Z14-AA14) -> 500000 | AC14: =IF(OR(Z14="",Z14=0),"",AA14/Z14) -> 0 | AD14: 500000 | AE14: =SUMIFS(TablaEgresos[Valor],TablaEgresos[Categoría],$A14,TablaEgresos[Mes],AD$4) -> 0 | AF14: =IF(AD14="","",AD14-AE14) -> 500000 | AG14: =IF(OR(AD14="",AD14=0),"",AE14/AD14) -> 0 | AH14: 500000 | AI14: =SUMIFS(TablaEgresos[Valor],TablaEgresos[Categoría],$A14,TablaEgresos[Mes],AH$4) -> 0 | AJ14: =IF(AH14="","",AH14-AI14) -> 500000 | AK14: =IF(OR(AH14="",AH14=0),"",AI14/AH14) -> 0 | AL14: 500000 | AM14: =SUMIFS(TablaEgresos[Valor],TablaEgresos[Categoría],$A14,TablaEgresos[Mes],AL$4) -> 0 | AN14: =IF(AL14="","",AL14-AM14) -> 500000 | AO14: =IF(OR(AL14="",AL14=0),"",AM14/AL14) -> 0 | AP14: 500000 | AQ14: =SUMIFS(TablaEgresos[Valor],TablaEgresos[Categoría],$A14,TablaEgresos[Mes],AP$4) -> 0 | AR14: =IF(AP14="","",AP14-AQ14) -> 500000 | AS14: =IF(OR(AP14="",AP14=0),"",AQ14/AP14) -> 0 | AT14: 500000 | AU14: =SUMIFS(TablaEgresos[Valor],TablaEgresos[Categoría],$A14,TablaEgresos[Mes],AT$4) -> 0 | AV14: =IF(AT14="","",AT14-AU14) -> 500000 | AW14: =IF(OR(AT14="",AT14=0),"",AU14/AT14) -> 0 | AX14: 500000 | AY14: =SUMIFS(TablaEgresos[Valor],TablaEgresos[Categoría],$A14,TablaEgresos[Mes],AX$4) -> 0 | AZ14: =IF(AX14="","",AX14-AY14) -> 500000 | BA14: =IF(OR(AX14="",AX14=0),"",AY14/AX14) -> 0 | BB14: 500000 | BC14: =SUMIFS(TablaEgresos[Valor],TablaEgresos[Categoría],$A14,TablaEgresos[Mes],BB$4) -> 0 | BD14: =IF(BB14="","",BB14-BC14) -> 500000 | BE14: =IF(OR(BB14="",BB14=0),"",BC14/BB14) -> 0 | BF14: 500000 | BG14: =SUMIFS(TablaEgresos[Valor],TablaEgresos[Categoría],$A14,TablaEgresos[Mes],BF$4) -> 0 | BH14: =IF(BF14="","",BF14-BG14) -> 500000 | BI14: =IF(OR(BF14="",BF14=0),"",BG14/BF14) -> 0 | BJ14: 500000 | BK14: =SUMIFS(TablaEgresos[Valor],TablaEgresos[Categoría],$A14,TablaEgresos[Mes],BJ$4) -> 0 | BL14: =IF(BJ14="","",BJ14-BK14) -> 500000 | BM14: =IF(OR(BJ14="",BJ14=0),"",BK14/BJ14) -> 0 | BN14: 500000 | BO14: =SUMIFS(TablaEgresos[Valor],TablaEgresos[Categoría],$A14,TablaEgresos[Mes],BN$4) -> 0 | BP14: =IF(BN14="","",BN14-BO14) -> 500000 | BQ14: =IF(OR(BN14="",BN14=0),"",BO14/BN14) -> 0 | BR14: 500000 | BS14: =SUMIFS(TablaEgresos[Valor],TablaEgresos[Categoría],$A14,TablaEgresos[Mes],BR$4) -> 0 | BT14: =IF(BR14="","",BR14-BS14) -> 500000 | BU14: =IF(OR(BR14="",BR14=0),"",BS14/BR14) -> 0 | BV14: 500000 | BW14: =SUMIFS(TablaEgresos[Valor],TablaEgresos[Categoría],$A14,TablaEgresos[Mes],BV$4) -> 0 | BX14: =IF(BV14="","",BV14-BW14) -> 500000 | BY14: =IF(OR(BV14="",BV14=0),"",BW14/BV14) -> 0 | BZ14: 500000 | CA14: =SUMIFS(TablaEgresos[Valor],TablaEgresos[Categoría],$A14,TablaEgresos[Mes],BZ$4) -> 0 | CB14: =IF(BZ14="","",BZ14-CA14) -> 500000 | CC14: =IF(OR(BZ14="",BZ14=0),"",CA14/BZ14) -> 0 | CD14: 500000 | CE14: =SUMIFS(TablaEgresos[Valor],TablaEgresos[Categoría],$A14,TablaEgresos[Mes],CD$4) -> 0 | CF14: =IF(CD14="","",CD14-CE14) -> 500000 | CG14: =IF(OR(CD14="",CD14=0),"",CE14/CD14) -> 0 | CH14: 500000 | CI14: =SUMIFS(TablaEgresos[Valor],TablaEgresos[Categoría],$A14,TablaEgresos[Mes],CH$4) -> 0 | CJ14: =IF(CH14="","",CH14-CI14) -> 500000 | CK14: =IF(OR(CH14="",CH14=0),"",CI14/CH14) -> 0 | CL14: 500000 | CM14: =SUMIFS(TablaEgresos[Valor],TablaEgresos[Categoría],$A14,TablaEgresos[Mes],CL$4) -> 0 | CN14: =IF(CL14="","",CL14-CM14) -> 500000 | CO14: =IF(OR(CL14="",CL14=0),"",CM14/CL14) -> 0
A15: Servicios públicos y telecom | B15: =IFERROR(AVERAGE(INDEX($B58:$W58,MATCH($B$3,$B$51:$W$51,0)-2):INDEX($B58:$W58,MATCH($B$3,$B$51:$W$51,0))),0) -> 0 | C15: =IFERROR(SLOPE(INDEX($B58:$W58,1):INDEX($B58:$W58,MATCH($B$3,$B$51:$W$51,0)),INDEX($B$50:$W$50,1):INDEX($B$50:$W$50,MATCH($B$3,$B$51:$W$51,0))),0) -> 0 | D15: =IF($B15=0,"",$C15/$B15) | E15: =MAX(0,ROUND($B15+$C15*3,-3)) -> 0 | G15: =SUMIFS(TablaEgresos[Valor],TablaEgresos[Categoría],$A15,TablaEgresos[Mes],F$4) -> 0 | H15: =IF(F15="","",F15-G15) | I15: =IF(OR(F15="",F15=0),"",G15/F15) | K15: =SUMIFS(TablaEgresos[Valor],TablaEgresos[Categoría],$A15,TablaEgresos[Mes],J$4) -> 0 | L15: =IF(J15="","",J15-K15) | M15: =IF(OR(J15="",J15=0),"",K15/J15) | O15: =SUMIFS(TablaEgresos[Valor],TablaEgresos[Categoría],$A15,TablaEgresos[Mes],N$4) -> 0 | P15: =IF(N15="","",N15-O15) | Q15: =IF(OR(N15="",N15=0),"",O15/N15) | S15: =SUMIFS(TablaEgresos[Valor],TablaEgresos[Categoría],$A15,TablaEgresos[Mes],R$4) -> 0 | T15: =IF(R15="","",R15-S15) | U15: =IF(OR(R15="",R15=0),"",S15/R15) | V15: 900000 | W15: =SUMIFS(TablaEgresos[Valor],TablaEgresos[Categoría],$A15,TablaEgresos[Mes],V$4) -> 0 | X15: =IF(V15="","",V15-W15) -> 900000 | Y15: =IF(OR(V15="",V15=0),"",W15/V15) -> 0 | Z15: 900000 | AA15: =SUMIFS(TablaEgresos[Valor],TablaEgresos[Categoría],$A15,TablaEgresos[Mes],Z$4) -> 0 | AB15: =IF(Z15="","",Z15-AA15) -> 900000 | AC15: =IF(OR(Z15="",Z15=0),"",AA15/Z15) -> 0 | AD15: 900000 | AE15: =SUMIFS(TablaEgresos[Valor],TablaEgresos[Categoría],$A15,TablaEgresos[Mes],AD$4) -> 0 | AF15: =IF(AD15="","",AD15-AE15) -> 900000 | AG15: =IF(OR(AD15="",AD15=0),"",AE15/AD15) -> 0 | AH15: 900000 | AI15: =SUMIFS(TablaEgresos[Valor],TablaEgresos[Categoría],$A15,TablaEgresos[Mes],AH$4) -> 0 | AJ15: =IF(AH15="","",AH15-AI15) -> 900000 | AK15: =IF(OR(AH15="",AH15=0),"",AI15/AH15) -> 0 | AL15: 900000 | AM15: =SUMIFS(TablaEgresos[Valor],TablaEgresos[Categoría],$A15,TablaEgresos[Mes],AL$4) -> 0 | AN15: =IF(AL15="","",AL15-AM15) -> 900000 | AO15: =IF(OR(AL15="",AL15=0),"",AM15/AL15) -> 0 | AP15: 900000 | AQ15: =SUMIFS(TablaEgresos[Valor],TablaEgresos[Categoría],$A15,TablaEgresos[Mes],AP$4) -> 0 | AR15: =IF(AP15="","",AP15-AQ15) -> 900000 | AS15: =IF(OR(AP15="",AP15=0),"",AQ15/AP15) -> 0 | AT15: 900000 | AU15: =SUMIFS(TablaEgresos[Valor],TablaEgresos[Categoría],$A15,TablaEgresos[Mes],AT$4) -> 0 | AV15: =IF(AT15="","",AT15-AU15) -> 900000 | AW15: =IF(OR(AT15="",AT15=0),"",AU15/AT15) -> 0 | AX15: 900000 | AY15: =SUMIFS(TablaEgresos[Valor],TablaEgresos[Categoría],$A15,TablaEgresos[Mes],AX$4) -> 0 | AZ15: =IF(AX15="","",AX15-AY15) -> 900000 | BA15: =IF(OR(AX15="",AX15=0),"",AY15/AX15) -> 0 | BB15: 900000 | BC15: =SUMIFS(TablaEgresos[Valor],TablaEgresos[Categoría],$A15,TablaEgresos[Mes],BB$4) -> 0 | BD15: =IF(BB15="","",BB15-BC15) -> 900000 | BE15: =IF(OR(BB15="",BB15=0),"",BC15/BB15) -> 0 | BF15: 900000 | BG15: =SUMIFS(TablaEgresos[Valor],TablaEgresos[Categoría],$A15,TablaEgresos[Mes],BF$4) -> 0 | BH15: =IF(BF15="","",BF15-BG15) -> 900000 | BI15: =IF(OR(BF15="",BF15=0),"",BG15/BF15) -> 0 | BJ15: 900000 | BK15: =SUMIFS(TablaEgresos[Valor],TablaEgresos[Categoría],$A15,TablaEgresos[Mes],BJ$4) -> 0 | BL15: =IF(BJ15="","",BJ15-BK15) -> 900000 | BM15: =IF(OR(BJ15="",BJ15=0),"",BK15/BJ15) -> 0 | BN15: 900000 | BO15: =SUMIFS(TablaEgresos[Valor],TablaEgresos[Categoría],$A15,TablaEgresos[Mes],BN$4) -> 0 | BP15: =IF(BN15="","",BN15-BO15) -> 900000 | BQ15: =IF(OR(BN15="",BN15=0),"",BO15/BN15) -> 0 | BR15: 900000 | BS15: =SUMIFS(TablaEgresos[Valor],TablaEgresos[Categoría],$A15,TablaEgresos[Mes],BR$4) -> 0 | BT15: =IF(BR15="","",BR15-BS15) -> 900000 | BU15: =IF(OR(BR15="",BR15=0),"",BS15/BR15) -> 0 | BV15: 900000 | BW15: =SUMIFS(TablaEgresos[Valor],TablaEgresos[Categoría],$A15,TablaEgresos[Mes],BV$4) -> 0 | BX15: =IF(BV15="","",BV15-BW15) -> 900000 | BY15: =IF(OR(BV15="",BV15=0),"",BW15/BV15) -> 0 | BZ15: 900000 | CA15: =SUMIFS(TablaEgresos[Valor],TablaEgresos[Categoría],$A15,TablaEgresos[Mes],BZ$4) -> 0 | CB15: =IF(BZ15="","",BZ15-CA15) -> 900000 | CC15: =IF(OR(BZ15="",BZ15=0),"",CA15/BZ15) -> 0 | CD15: 900000 | CE15: =SUMIFS(TablaEgresos[Valor],TablaEgresos[Categoría],$A15,TablaEgresos[Mes],CD$4) -> 0 | CF15: =IF(CD15="","",CD15-CE15) -> 900000 | CG15: =IF(OR(CD15="",CD15=0),"",CE15/CD15) -> 0 | CH15: 900000 | CI15: =SUMIFS(TablaEgresos[Valor],TablaEgresos[Categoría],$A15,TablaEgresos[Mes],CH$4) -> 0 | CJ15: =IF(CH15="","",CH15-CI15) -> 900000 | CK15: =IF(OR(CH15="",CH15=0),"",CI15/CH15) -> 0 | CL15: 900000 | CM15: =SUMIFS(TablaEgresos[Valor],TablaEgresos[Categoría],$A15,TablaEgresos[Mes],CL$4) -> 0 | CN15: =IF(CL15="","",CL15-CM15) -> 900000 | CO15: =IF(OR(CL15="",CL15=0),"",CM15/CL15) -> 0
A16: Mercado y aseo | B16: =IFERROR(AVERAGE(INDEX($B59:$W59,MATCH($B$3,$B$51:$W$51,0)-2):INDEX($B59:$W59,MATCH($B$3,$B$51:$W$51,0))),0) -> 361336 | C16: =IFERROR(SLOPE(INDEX($B59:$W59,1):INDEX($B59:$W59,MATCH($B$3,$B$51:$W$51,0)),INDEX($B$50:$W$50,1):INDEX($B$50:$W$50,MATCH($B$3,$B$51:$W$51,0))),0) -> 157818.4 | D16: =IF($B16=0,"",$C16/$B16) -> 0.43676357 | E16: =MAX(0,ROUND($B16+$C16*3,-3)) -> 835000 | G16: =SUMIFS(TablaEgresos[Valor],TablaEgresos[Categoría],$A16,TablaEgresos[Mes],F$4) -> 0 | H16: =IF(F16="","",F16-G16) | I16: =IF(OR(F16="",F16=0),"",G16/F16) | K16: =SUMIFS(TablaEgresos[Valor],TablaEgresos[Categoría],$A16,TablaEgresos[Mes],J$4) -> 312270 | L16: =IF(J16="","",J16-K16) | M16: =IF(OR(J16="",J16=0),"",K16/J16) | O16: =SUMIFS(TablaEgresos[Valor],TablaEgresos[Categoría],$A16,TablaEgresos[Mes],N$4) -> 212380 | P16: =IF(N16="","",N16-O16) | Q16: =IF(OR(N16="",N16=0),"",O16/N16) | S16: =SUMIFS(TablaEgresos[Valor],TablaEgresos[Categoría],$A16,TablaEgresos[Mes],R$4) -> 559358 | T16: =IF(R16="","",R16-S16) | U16: =IF(OR(R16="",R16=0),"",S16/R16) | V16: 600000 | W16: =SUMIFS(TablaEgresos[Valor],TablaEgresos[Categoría],$A16,TablaEgresos[Mes],V$4) -> 106278 | X16: =IF(V16="","",V16-W16) -> 493722 | Y16: =IF(OR(V16="",V16=0),"",W16/V16) -> 0.17713 | Z16: 600000 | AA16: =SUMIFS(TablaEgresos[Valor],TablaEgresos[Categoría],$A16,TablaEgresos[Mes],Z$4) -> 0 | AB16: =IF(Z16="","",Z16-AA16) -> 600000 | AC16: =IF(OR(Z16="",Z16=0),"",AA16/Z16) -> 0 | AD16: 600000 | AE16: =SUMIFS(TablaEgresos[Valor],TablaEgresos[Categoría],$A16,TablaEgresos[Mes],AD$4) -> 0 | AF16: =IF(AD16="","",AD16-AE16) -> 600000 | AG16: =IF(OR(AD16="",AD16=0),"",AE16/AD16) -> 0 | AH16: 600000 | AI16: =SUMIFS(TablaEgresos[Valor],TablaEgresos[Categoría],$A16,TablaEgresos[Mes],AH$4) -> 0 | AJ16: =IF(AH16="","",AH16-AI16) -> 600000 | AK16: =IF(OR(AH16="",AH16=0),"",AI16/AH16) -> 0 | AL16: 600000 | AM16: =SUMIFS(TablaEgresos[Valor],TablaEgresos[Categoría],$A16,TablaEgresos[Mes],AL$4) -> 0 | AN16: =IF(AL16="","",AL16-AM16) -> 600000 | AO16: =IF(OR(AL16="",AL16=0),"",AM16/AL16) -> 0 | AP16: 600000 | AQ16: =SUMIFS(TablaEgresos[Valor],TablaEgresos[Categoría],$A16,TablaEgresos[Mes],AP$4) -> 0 | AR16: =IF(AP16="","",AP16-AQ16) -> 600000 | AS16: =IF(OR(AP16="",AP16=0),"",AQ16/AP16) -> 0 | AT16: 600000 | AU16: =SUMIFS(TablaEgresos[Valor],TablaEgresos[Categoría],$A16,TablaEgresos[Mes],AT$4) -> 0 | AV16: =IF(AT16="","",AT16-AU16) -> 600000 | AW16: =IF(OR(AT16="",AT16=0),"",AU16/AT16) -> 0 | AX16: 600000 | AY16: =SUMIFS(TablaEgresos[Valor],TablaEgresos[Categoría],$A16,TablaEgresos[Mes],AX$4) -> 0 | AZ16: =IF(AX16="","",AX16-AY16) -> 600000 | BA16: =IF(OR(AX16="",AX16=0),"",AY16/AX16) -> 0 | BB16: 600000 | BC16: =SUMIFS(TablaEgresos[Valor],TablaEgresos[Categoría],$A16,TablaEgresos[Mes],BB$4) -> 0 | BD16: =IF(BB16="","",BB16-BC16) -> 600000 | BE16: =IF(OR(BB16="",BB16=0),"",BC16/BB16) -> 0 | BF16: 600000 | BG16: =SUMIFS(TablaEgresos[Valor],TablaEgresos[Categoría],$A16,TablaEgresos[Mes],BF$4) -> 0 | BH16: =IF(BF16="","",BF16-BG16) -> 600000 | BI16: =IF(OR(BF16="",BF16=0),"",BG16/BF16) -> 0 | BJ16: 600000 | BK16: =SUMIFS(TablaEgresos[Valor],TablaEgresos[Categoría],$A16,TablaEgresos[Mes],BJ$4) -> 0 | BL16: =IF(BJ16="","",BJ16-BK16) -> 600000 | BM16: =IF(OR(BJ16="",BJ16=0),"",BK16/BJ16) -> 0 | BN16: 600000 | BO16: =SUMIFS(TablaEgresos[Valor],TablaEgresos[Categoría],$A16,TablaEgresos[Mes],BN$4) -> 0 | BP16: =IF(BN16="","",BN16-BO16) -> 600000 | BQ16: =IF(OR(BN16="",BN16=0),"",BO16/BN16) -> 0 | BR16: 600000 | BS16: =SUMIFS(TablaEgresos[Valor],TablaEgresos[Categoría],$A16,TablaEgresos[Mes],BR$4) -> 0 | BT16: =IF(BR16="","",BR16-BS16) -> 600000 | BU16: =IF(OR(BR16="",BR16=0),"",BS16/BR16) -> 0 | BV16: 600000 | BW16: =SUMIFS(TablaEgresos[Valor],TablaEgresos[Categoría],$A16,TablaEgresos[Mes],BV$4) -> 0 | BX16: =IF(BV16="","",BV16-BW16) -> 600000 | BY16: =IF(OR(BV16="",BV16=0),"",BW16/BV16) -> 0 | BZ16: 600000 | CA16: =SUMIFS(TablaEgresos[Valor],TablaEgresos[Categoría],$A16,TablaEgresos[Mes],BZ$4) -> 0 | CB16: =IF(BZ16="","",BZ16-CA16) -> 600000 | CC16: =IF(OR(BZ16="",BZ16=0),"",CA16/BZ16) -> 0 | CD16: 600000 | CE16: =SUMIFS(TablaEgresos[Valor],TablaEgresos[Categoría],$A16,TablaEgresos[Mes],CD$4) -> 0 | CF16: =IF(CD16="","",CD16-CE16) -> 600000 | CG16: =IF(OR(CD16="",CD16=0),"",CE16/CD16) -> 0 | CH16: 600000 | CI16: =SUMIFS(TablaEgresos[Valor],TablaEgresos[Categoría],$A16,TablaEgresos[Mes],CH$4) -> 0 | CJ16: =IF(CH16="","",CH16-CI16) -> 600000 | CK16: =IF(OR(CH16="",CH16=0),"",CI16/CH16) -> 0 | CL16: 600000 | CM16: =SUMIFS(TablaEgresos[Valor],TablaEgresos[Categoría],$A16,TablaEgresos[Mes],CL$4) -> 0 | CN16: =IF(CL16="","",CL16-CM16) -> 600000 | CO16: =IF(OR(CL16="",CL16=0),"",CM16/CL16) -> 0
A17: Cafetería | B17: =IFERROR(AVERAGE(INDEX($B60:$W60,MATCH($B$3,$B$51:$W$51,0)-2):INDEX($B60:$W60,MATCH($B$3,$B$51:$W$51,0))),0) -> 1108843.4 | C17: =IFERROR(SLOPE(INDEX($B60:$W60,1):INDEX($B60:$W60,MATCH($B$3,$B$51:$W$51,0)),INDEX($B$50:$W$50,1):INDEX($B$50:$W$50,MATCH($B$3,$B$51:$W$51,0))),0) -> 667731.53 | D17: =IF($B17=0,"",$C17/$B17) -> 0.6021874 | E17: =MAX(0,ROUND($B17+$C17*3,-3)) -> 3112000 | G17: =SUMIFS(TablaEgresos[Valor],TablaEgresos[Categoría],$A17,TablaEgresos[Mes],F$4) -> 0 | H17: =IF(F17="","",F17-G17) | I17: =IF(OR(F17="",F17=0),"",G17/F17) | K17: =SUMIFS(TablaEgresos[Valor],TablaEgresos[Categoría],$A17,TablaEgresos[Mes],J$4) -> 67308.47 | L17: =IF(J17="","",J17-K17) | M17: =IF(OR(J17="",J17=0),"",K17/J17) | O17: =SUMIFS(TablaEgresos[Valor],TablaEgresos[Categoría],$A17,TablaEgresos[Mes],N$4) -> 1516520.8 | P17: =IF(N17="","",N17-O17) | Q17: =IF(OR(N17="",N17=0),"",O17/N17) | S17: =SUMIFS(TablaEgresos[Valor],TablaEgresos[Categoría],$A17,TablaEgresos[Mes],R$4) -> 1742701 | T17: =IF(R17="","",R17-S17) | U17: =IF(OR(R17="",R17=0),"",S17/R17) | V17: 500000 | W17: =SUMIFS(TablaEgresos[Valor],TablaEgresos[Categoría],$A17,TablaEgresos[Mes],V$4) -> 176200 | X17: =IF(V17="","",V17-W17) -> 323800 | Y17: =IF(OR(V17="",V17=0),"",W17/V17) -> 0.3524 | Z17: 650000 | AA17: =SUMIFS(TablaEgresos[Valor],TablaEgresos[Categoría],$A17,TablaEgresos[Mes],Z$4) -> 0 | AB17: =IF(Z17="","",Z17-AA17) -> 650000 | AC17: =IF(OR(Z17="",Z17=0),"",AA17/Z17) -> 0 | AD17: 650000 | AE17: =SUMIFS(TablaEgresos[Valor],TablaEgresos[Categoría],$A17,TablaEgresos[Mes],AD$4) -> 0 | AF17: =IF(AD17="","",AD17-AE17) -> 650000 | AG17: =IF(OR(AD17="",AD17=0),"",AE17/AD17) -> 0 | AH17: 650000 | AI17: =SUMIFS(TablaEgresos[Valor],TablaEgresos[Categoría],$A17,TablaEgresos[Mes],AH$4) -> 0 | AJ17: =IF(AH17="","",AH17-AI17) -> 650000 | AK17: =IF(OR(AH17="",AH17=0),"",AI17/AH17) -> 0 | AL17: 650000 | AM17: =SUMIFS(TablaEgresos[Valor],TablaEgresos[Categoría],$A17,TablaEgresos[Mes],AL$4) -> 0 | AN17: =IF(AL17="","",AL17-AM17) -> 650000 | AO17: =IF(OR(AL17="",AL17=0),"",AM17/AL17) -> 0 | AP17: 650000 | AQ17: =SUMIFS(TablaEgresos[Valor],TablaEgresos[Categoría],$A17,TablaEgresos[Mes],AP$4) -> 0 | AR17: =IF(AP17="","",AP17-AQ17) -> 650000 | AS17: =IF(OR(AP17="",AP17=0),"",AQ17/AP17) -> 0 | AT17: 650000 | AU17: =SUMIFS(TablaEgresos[Valor],TablaEgresos[Categoría],$A17,TablaEgresos[Mes],AT$4) -> 0 | AV17: =IF(AT17="","",AT17-AU17) -> 650000 | AW17: =IF(OR(AT17="",AT17=0),"",AU17/AT17) -> 0 | AX17: 650000 | AY17: =SUMIFS(TablaEgresos[Valor],TablaEgresos[Categoría],$A17,TablaEgresos[Mes],AX$4) -> 0 | AZ17: =IF(AX17="","",AX17-AY17) -> 650000 | BA17: =IF(OR(AX17="",AX17=0),"",AY17/AX17) -> 0 | BB17: 650000 | BC17: =SUMIFS(TablaEgresos[Valor],TablaEgresos[Categoría],$A17,TablaEgresos[Mes],BB$4) -> 0 | BD17: =IF(BB17="","",BB17-BC17) -> 650000 | BE17: =IF(OR(BB17="",BB17=0),"",BC17/BB17) -> 0 | BF17: 650000 | BG17: =SUMIFS(TablaEgresos[Valor],TablaEgresos[Categoría],$A17,TablaEgresos[Mes],BF$4) -> 0 | BH17: =IF(BF17="","",BF17-BG17) -> 650000 | BI17: =IF(OR(BF17="",BF17=0),"",BG17/BF17) -> 0 | BJ17: 650000 | BK17: =SUMIFS(TablaEgresos[Valor],TablaEgresos[Categoría],$A17,TablaEgresos[Mes],BJ$4) -> 0 | BL17: =IF(BJ17="","",BJ17-BK17) -> 650000 | BM17: =IF(OR(BJ17="",BJ17=0),"",BK17/BJ17) -> 0 | BN17: 650000 | BO17: =SUMIFS(TablaEgresos[Valor],TablaEgresos[Categoría],$A17,TablaEgresos[Mes],BN$4) -> 0 | BP17: =IF(BN17="","",BN17-BO17) -> 650000 | BQ17: =IF(OR(BN17="",BN17=0),"",BO17/BN17) -> 0 | BR17: 650000 | BS17: =SUMIFS(TablaEgresos[Valor],TablaEgresos[Categoría],$A17,TablaEgresos[Mes],BR$4) -> 0 | BT17: =IF(BR17="","",BR17-BS17) -> 650000 | BU17: =IF(OR(BR17="",BR17=0),"",BS17/BR17) -> 0 | BV17: 650000 | BW17: =SUMIFS(TablaEgresos[Valor],TablaEgresos[Categoría],$A17,TablaEgresos[Mes],BV$4) -> 0 | BX17: =IF(BV17="","",BV17-BW17) -> 650000 | BY17: =IF(OR(BV17="",BV17=0),"",BW17/BV17) -> 0 | BZ17: 650000 | CA17: =SUMIFS(TablaEgresos[Valor],TablaEgresos[Categoría],$A17,TablaEgresos[Mes],BZ$4) -> 0 | CB17: =IF(BZ17="","",BZ17-CA17) -> 650000 | CC17: =IF(OR(BZ17="",BZ17=0),"",CA17/BZ17) -> 0 | CD17: 650000 | CE17: =SUMIFS(TablaEgresos[Valor],TablaEgresos[Categoría],$A17,TablaEgresos[Mes],CD$4) -> 0 | CF17: =IF(CD17="","",CD17-CE17) -> 650000 | CG17: =IF(OR(CD17="",CD17=0),"",CE17/CD17) -> 0 | CH17: 650000 | CI17: =SUMIFS(TablaEgresos[Valor],TablaEgresos[Categoría],$A17,TablaEgresos[Mes],CH$4) -> 0 | CJ17: =IF(CH17="","",CH17-CI17) -> 650000 | CK17: =IF(OR(CH17="",CH17=0),"",CI17/CH17) -> 0 | CL17: 650000 | CM17: =SUMIFS(TablaEgresos[Valor],TablaEgresos[Categoría],$A17,TablaEgresos[Mes],CL$4) -> 0 | CN17: =IF(CL17="","",CL17-CM17) -> 650000 | CO17: =IF(OR(CL17="",CL17=0),"",CM17/CL17) -> 0
A18: Transporte/peajes/combustible/parqueo | B18: =IFERROR(AVERAGE(INDEX($B61:$W61,MATCH($B$3,$B$51:$W$51,0)-2):INDEX($B61:$W61,MATCH($B$3,$B$51:$W$51,0))),0) -> 1351198 | C18: =IFERROR(SLOPE(INDEX($B61:$W61,1):INDEX($B61:$W61,MATCH($B$3,$B$51:$W$51,0)),INDEX($B$50:$W$50,1):INDEX($B$50:$W$50,MATCH($B$3,$B$51:$W$51,0))),0) -> 693125.4 | D18: =IF($B18=0,"",$C18/$B18) -> 0.51297101 | E18: =MAX(0,ROUND($B18+$C18*3,-3)) -> 3431000 | G18: =SUMIFS(TablaEgresos[Valor],TablaEgresos[Categoría],$A18,TablaEgresos[Mes],F$4) -> 0 | H18: =IF(F18="","",F18-G18) | I18: =IF(OR(F18="",F18=0),"",G18/F18) | K18: =SUMIFS(TablaEgresos[Valor],TablaEgresos[Categoría],$A18,TablaEgresos[Mes],J$4) -> 460761 | L18: =IF(J18="","",J18-K18) | M18: =IF(OR(J18="",J18=0),"",K18/J18) | O18: =SUMIFS(TablaEgresos[Valor],TablaEgresos[Categoría],$A18,TablaEgresos[Mes],N$4) -> 1693242 | P18: =IF(N18="","",N18-O18) | Q18: =IF(OR(N18="",N18=0),"",O18/N18) | S18: =SUMIFS(TablaEgresos[Valor],TablaEgresos[Categoría],$A18,TablaEgresos[Mes],R$4) -> 1899591 | T18: =IF(R18="","",R18-S18) | U18: =IF(OR(R18="",R18=0),"",S18/R18) | V18: 1500000 | W18: =SUMIFS(TablaEgresos[Valor],TablaEgresos[Categoría],$A18,TablaEgresos[Mes],V$4) -> 1203598 | X18: =IF(V18="","",V18-W18) -> 296402.04 | Y18: =IF(OR(V18="",V18=0),"",W18/V18) -> 0.80239864 | Z18: 1500000 | AA18: =SUMIFS(TablaEgresos[Valor],TablaEgresos[Categoría],$A18,TablaEgresos[Mes],Z$4) -> 0 | AB18: =IF(Z18="","",Z18-AA18) -> 1500000 | AC18: =IF(OR(Z18="",Z18=0),"",AA18/Z18) -> 0 | AD18: 1500000 | AE18: =SUMIFS(TablaEgresos[Valor],TablaEgresos[Categoría],$A18,TablaEgresos[Mes],AD$4) -> 0 | AF18: =IF(AD18="","",AD18-AE18) -> 1500000 | AG18: =IF(OR(AD18="",AD18=0),"",AE18/AD18) -> 0 | AH18: 1500000 | AI18: =SUMIFS(TablaEgresos[Valor],TablaEgresos[Categoría],$A18,TablaEgresos[Mes],AH$4) -> 0 | AJ18: =IF(AH18="","",AH18-AI18) -> 1500000 | AK18: =IF(OR(AH18="",AH18=0),"",AI18/AH18) -> 0 | AL18: 1500000 | AM18: =SUMIFS(TablaEgresos[Valor],TablaEgresos[Categoría],$A18,TablaEgresos[Mes],AL$4) -> 0 | AN18: =IF(AL18="","",AL18-AM18) -> 1500000 | AO18: =IF(OR(AL18="",AL18=0),"",AM18/AL18) -> 0 | AP18: 1500000 | AQ18: =SUMIFS(TablaEgresos[Valor],TablaEgresos[Categoría],$A18,TablaEgresos[Mes],AP$4) -> 0 | AR18: =IF(AP18="","",AP18-AQ18) -> 1500000 | AS18: =IF(OR(AP18="",AP18=0),"",AQ18/AP18) -> 0 | AT18: 1500000 | AU18: =SUMIFS(TablaEgresos[Valor],TablaEgresos[Categoría],$A18,TablaEgresos[Mes],AT$4) -> 0 | AV18: =IF(AT18="","",AT18-AU18) -> 1500000 | AW18: =IF(OR(AT18="",AT18=0),"",AU18/AT18) -> 0 | AX18: 1500000 | AY18: =SUMIFS(TablaEgresos[Valor],TablaEgresos[Categoría],$A18,TablaEgresos[Mes],AX$4) -> 0 | AZ18: =IF(AX18="","",AX18-AY18) -> 1500000 | BA18: =IF(OR(AX18="",AX18=0),"",AY18/AX18) -> 0 | BB18: 1500000 | BC18: =SUMIFS(TablaEgresos[Valor],TablaEgresos[Categoría],$A18,TablaEgresos[Mes],BB$4) -> 0 | BD18: =IF(BB18="","",BB18-BC18) -> 1500000 | BE18: =IF(OR(BB18="",BB18=0),"",BC18/BB18) -> 0 | BF18: 1500000 | BG18: =SUMIFS(TablaEgresos[Valor],TablaEgresos[Categoría],$A18,TablaEgresos[Mes],BF$4) -> 0 | BH18: =IF(BF18="","",BF18-BG18) -> 1500000 | BI18: =IF(OR(BF18="",BF18=0),"",BG18/BF18) -> 0 | BJ18: 1500000 | BK18: =SUMIFS(TablaEgresos[Valor],TablaEgresos[Categoría],$A18,TablaEgresos[Mes],BJ$4) -> 0 | BL18: =IF(BJ18="","",BJ18-BK18) -> 1500000 | BM18: =IF(OR(BJ18="",BJ18=0),"",BK18/BJ18) -> 0 | BN18: 1500000 | BO18: =SUMIFS(TablaEgresos[Valor],TablaEgresos[Categoría],$A18,TablaEgresos[Mes],BN$4) -> 0 | BP18: =IF(BN18="","",BN18-BO18) -> 1500000 | BQ18: =IF(OR(BN18="",BN18=0),"",BO18/BN18) -> 0 | BR18: 1500000 | BS18: =SUMIFS(TablaEgresos[Valor],TablaEgresos[Categoría],$A18,TablaEgresos[Mes],BR$4) -> 0 | BT18: =IF(BR18="","",BR18-BS18) -> 1500000 | BU18: =IF(OR(BR18="",BR18=0),"",BS18/BR18) -> 0 | BV18: 1500000 | BW18: =SUMIFS(TablaEgresos[Valor],TablaEgresos[Categoría],$A18,TablaEgresos[Mes],BV$4) -> 0 | BX18: =IF(BV18="","",BV18-BW18) -> 1500000 | BY18: =IF(OR(BV18="",BV18=0),"",BW18/BV18) -> 0 | BZ18: 1500000 | CA18: =SUMIFS(TablaEgresos[Valor],TablaEgresos[Categoría],$A18,TablaEgresos[Mes],BZ$4) -> 0 | CB18: =IF(BZ18="","",BZ18-CA18) -> 1500000 | CC18: =IF(OR(BZ18="",BZ18=0),"",CA18/BZ18) -> 0 | CD18: 1500000 | CE18: =SUMIFS(TablaEgresos[Valor],TablaEgresos[Categoría],$A18,TablaEgresos[Mes],CD$4) -> 0 | CF18: =IF(CD18="","",CD18-CE18) -> 1500000 | CG18: =IF(OR(CD18="",CD18=0),"",CE18/CD18) -> 0 | CH18: 1500000 | CI18: =SUMIFS(TablaEgresos[Valor],TablaEgresos[Categoría],$A18,TablaEgresos[Mes],CH$4) -> 0 | CJ18: =IF(CH18="","",CH18-CI18) -> 1500000 | CK18: =IF(OR(CH18="",CH18=0),"",CI18/CH18) -> 0 | CL18: 1500000 | CM18: =SUMIFS(TablaEgresos[Valor],TablaEgresos[Categoría],$A18,TablaEgresos[Mes],CL$4) -> 0 | CN18: =IF(CL18="","",CL18-CM18) -> 1500000 | CO18: =IF(OR(CL18="",CL18=0),"",CM18/CL18) -> 0
A19: Papelería | B19: =IFERROR(AVERAGE(INDEX($B64:$W64,MATCH($B$3,$B$51:$W$51,0)-2):INDEX($B64:$W64,MATCH($B$3,$B$51:$W$51,0))),0) -> 258600 | C19: =IFERROR(SLOPE(INDEX($B64:$W64,1):INDEX($B64:$W64,MATCH($B$3,$B$51:$W$51,0)),INDEX($B$50:$W$50,1):INDEX($B$50:$W$50,MATCH($B$3,$B$51:$W$51,0))),0) -> 107200 | D19: =IF($B19=0,"",$C19/$B19) -> 0.41453983 | E19: =MAX(0,ROUND($B19+$C19*3,-3)) -> 580000 | G19: =SUMIFS(TablaEgresos[Valor],TablaEgresos[Categoría],$A19,TablaEgresos[Mes],F$4) -> 0 | H19: =IF(F19="","",F19-G19) | I19: =IF(OR(F19="",F19=0),"",G19/F19) | K19: =SUMIFS(TablaEgresos[Valor],TablaEgresos[Categoría],$A19,TablaEgresos[Mes],J$4) -> 203700 | L19: =IF(J19="","",J19-K19) | M19: =IF(OR(J19="",J19=0),"",K19/J19) | O19: =SUMIFS(TablaEgresos[Valor],TablaEgresos[Categoría],$A19,TablaEgresos[Mes],N$4) -> 220300 | P19: =IF(N19="","",N19-O19) | Q19: =IF(OR(N19="",N19=0),"",O19/N19) | S19: =SUMIFS(TablaEgresos[Valor],TablaEgresos[Categoría],$A19,TablaEgresos[Mes],R$4) -> 351800 | T19: =IF(R19="","",R19-S19) | U19: =IF(OR(R19="",R19=0),"",S19/R19) | V19: 0 | W19: =SUMIFS(TablaEgresos[Valor],TablaEgresos[Categoría],$A19,TablaEgresos[Mes],V$4) -> 0 | X19: =IF(V19="","",V19-W19) -> 0 | Y19: =IF(OR(V19="",V19=0),"",W19/V19) | Z19: 300000 | AA19: =SUMIFS(TablaEgresos[Valor],TablaEgresos[Categoría],$A19,TablaEgresos[Mes],Z$4) -> 0 | AB19: =IF(Z19="","",Z19-AA19) -> 300000 | AC19: =IF(OR(Z19="",Z19=0),"",AA19/Z19) -> 0 | AD19: 300000 | AE19: =SUMIFS(TablaEgresos[Valor],TablaEgresos[Categoría],$A19,TablaEgresos[Mes],AD$4) -> 0 | AF19: =IF(AD19="","",AD19-AE19) -> 300000 | AG19: =IF(OR(AD19="",AD19=0),"",AE19/AD19) -> 0 | AH19: 300000 | AI19: =SUMIFS(TablaEgresos[Valor],TablaEgresos[Categoría],$A19,TablaEgresos[Mes],AH$4) -> 0 | AJ19: =IF(AH19="","",AH19-AI19) -> 300000 | AK19: =IF(OR(AH19="",AH19=0),"",AI19/AH19) -> 0 | AL19: 300000 | AM19: =SUMIFS(TablaEgresos[Valor],TablaEgresos[Categoría],$A19,TablaEgresos[Mes],AL$4) -> 0 | AN19: =IF(AL19="","",AL19-AM19) -> 300000 | AO19: =IF(OR(AL19="",AL19=0),"",AM19/AL19) -> 0 | AP19: 300000 | AQ19: =SUMIFS(TablaEgresos[Valor],TablaEgresos[Categoría],$A19,TablaEgresos[Mes],AP$4) -> 0 | AR19: =IF(AP19="","",AP19-AQ19) -> 300000 | AS19: =IF(OR(AP19="",AP19=0),"",AQ19/AP19) -> 0 | AT19: 300000 | AU19: =SUMIFS(TablaEgresos[Valor],TablaEgresos[Categoría],$A19,TablaEgresos[Mes],AT$4) -> 0 | AV19: =IF(AT19="","",AT19-AU19) -> 300000 | AW19: =IF(OR(AT19="",AT19=0),"",AU19/AT19) -> 0 | AX19: 300000 | AY19: =SUMIFS(TablaEgresos[Valor],TablaEgresos[Categoría],$A19,TablaEgresos[Mes],AX$4) -> 0 | AZ19: =IF(AX19="","",AX19-AY19) -> 300000 | BA19: =IF(OR(AX19="",AX19=0),"",AY19/AX19) -> 0 | BB19: 300000 | BC19: =SUMIFS(TablaEgresos[Valor],TablaEgresos[Categoría],$A19,TablaEgresos[Mes],BB$4) -> 0 | BD19: =IF(BB19="","",BB19-BC19) -> 300000 | BE19: =IF(OR(BB19="",BB19=0),"",BC19/BB19) -> 0 | BF19: 300000 | BG19: =SUMIFS(TablaEgresos[Valor],TablaEgresos[Categoría],$A19,TablaEgresos[Mes],BF$4) -> 0 | BH19: =IF(BF19="","",BF19-BG19) -> 300000 | BI19: =IF(OR(BF19="",BF19=0),"",BG19/BF19) -> 0 | BJ19: 300000 | BK19: =SUMIFS(TablaEgresos[Valor],TablaEgresos[Categoría],$A19,TablaEgresos[Mes],BJ$4) -> 0 | BL19: =IF(BJ19="","",BJ19-BK19) -> 300000 | BM19: =IF(OR(BJ19="",BJ19=0),"",BK19/BJ19) -> 0 | BN19: 300000 | BO19: =SUMIFS(TablaEgresos[Valor],TablaEgresos[Categoría],$A19,TablaEgresos[Mes],BN$4) -> 0 | BP19: =IF(BN19="","",BN19-BO19) -> 300000 | BQ19: =IF(OR(BN19="",BN19=0),"",BO19/BN19) -> 0 | BR19: 300000 | BS19: =SUMIFS(TablaEgresos[Valor],TablaEgresos[Categoría],$A19,TablaEgresos[Mes],BR$4) -> 0 | BT19: =IF(BR19="","",BR19-BS19) -> 300000 | BU19: =IF(OR(BR19="",BR19=0),"",BS19/BR19) -> 0 | BV19: 300000 | BW19: =SUMIFS(TablaEgresos[Valor],TablaEgresos[Categoría],$A19,TablaEgresos[Mes],BV$4) -> 0 | BX19: =IF(BV19="","",BV19-BW19) -> 300000 | BY19: =IF(OR(BV19="",BV19=0),"",BW19/BV19) -> 0 | BZ19: 300000 | CA19: =SUMIFS(TablaEgresos[Valor],TablaEgresos[Categoría],$A19,TablaEgresos[Mes],BZ$4) -> 0 | CB19: =IF(BZ19="","",BZ19-CA19) -> 300000 | CC19: =IF(OR(BZ19="",BZ19=0),"",CA19/BZ19) -> 0 | CD19: 300000 | CE19: =SUMIFS(TablaEgresos[Valor],TablaEgresos[Categoría],$A19,TablaEgresos[Mes],CD$4) -> 0 | CF19: =IF(CD19="","",CD19-CE19) -> 300000 | CG19: =IF(OR(CD19="",CD19=0),"",CE19/CD19) -> 0 | CH19: 300000 | CI19: =SUMIFS(TablaEgresos[Valor],TablaEgresos[Categoría],$A19,TablaEgresos[Mes],CH$4) -> 0 | CJ19: =IF(CH19="","",CH19-CI19) -> 300000 | CK19: =IF(OR(CH19="",CH19=0),"",CI19/CH19) -> 0 | CL19: 300000 | CM19: =SUMIFS(TablaEgresos[Valor],TablaEgresos[Categoría],$A19,TablaEgresos[Mes],CL$4) -> 0 | CN19: =IF(CL19="","",CL19-CM19) -> 300000 | CO19: =IF(OR(CL19="",CL19=0),"",CM19/CL19) -> 0
A20: Marketing y publicidad | B20: =IFERROR(AVERAGE(INDEX($B63:$W63,MATCH($B$3,$B$51:$W$51,0)-2):INDEX($B63:$W63,MATCH($B$3,$B$51:$W$51,0))),0) -> 182471.33 | C20: =IFERROR(SLOPE(INDEX($B63:$W63,1):INDEX($B63:$W63,MATCH($B$3,$B$51:$W$51,0)),INDEX($B$50:$W$50,1):INDEX($B$50:$W$50,MATCH($B$3,$B$51:$W$51,0))),0) -> 60002.8 | D20: =IF($B20=0,"",$C20/$B20) -> 0.32883412 | E20: =MAX(0,ROUND($B20+$C20*3,-3)) -> 362000 | G20: =SUMIFS(TablaEgresos[Valor],TablaEgresos[Categoría],$A20,TablaEgresos[Mes],F$4) -> 0 | H20: =IF(F20="","",F20-G20) | I20: =IF(OR(F20="",F20=0),"",G20/F20) | K20: =SUMIFS(TablaEgresos[Valor],TablaEgresos[Categoría],$A20,TablaEgresos[Mes],J$4) -> 153693 | L20: =IF(J20="","",J20-K20) | M20: =IF(OR(J20="",J20=0),"",K20/J20) | O20: =SUMIFS(TablaEgresos[Valor],TablaEgresos[Categoría],$A20,TablaEgresos[Mes],N$4) -> 213721 | P20: =IF(N20="","",N20-O20) | Q20: =IF(OR(N20="",N20=0),"",O20/N20) | S20: =SUMIFS(TablaEgresos[Valor],TablaEgresos[Categoría],$A20,TablaEgresos[Mes],R$4) -> 180000 | T20: =IF(R20="","",R20-S20) | U20: =IF(OR(R20="",R20=0),"",S20/R20) | V20: 0 | W20: =SUMIFS(TablaEgresos[Valor],TablaEgresos[Categoría],$A20,TablaEgresos[Mes],V$4) -> 0 | X20: =IF(V20="","",V20-W20) -> 0 | Y20: =IF(OR(V20="",V20=0),"",W20/V20) | Z20: 3000000 | AA20: =SUMIFS(TablaEgresos[Valor],TablaEgresos[Categoría],$A20,TablaEgresos[Mes],Z$4) -> 0 | AB20: =IF(Z20="","",Z20-AA20) -> 3000000 | AC20: =IF(OR(Z20="",Z20=0),"",AA20/Z20) -> 0 | AD20: 3000000 | AE20: =SUMIFS(TablaEgresos[Valor],TablaEgresos[Categoría],$A20,TablaEgresos[Mes],AD$4) -> 0 | AF20: =IF(AD20="","",AD20-AE20) -> 3000000 | AG20: =IF(OR(AD20="",AD20=0),"",AE20/AD20) -> 0 | AH20: 3000000 | AI20: =SUMIFS(TablaEgresos[Valor],TablaEgresos[Categoría],$A20,TablaEgresos[Mes],AH$4) -> 0 | AJ20: =IF(AH20="","",AH20-AI20) -> 3000000 | AK20: =IF(OR(AH20="",AH20=0),"",AI20/AH20) -> 0 | AL20: 3000000 | AM20: =SUMIFS(TablaEgresos[Valor],TablaEgresos[Categoría],$A20,TablaEgresos[Mes],AL$4) -> 0 | AN20: =IF(AL20="","",AL20-AM20) -> 3000000 | AO20: =IF(OR(AL20="",AL20=0),"",AM20/AL20) -> 0 | AP20: 3000000 | AQ20: =SUMIFS(TablaEgresos[Valor],TablaEgresos[Categoría],$A20,TablaEgresos[Mes],AP$4) -> 0 | AR20: =IF(AP20="","",AP20-AQ20) -> 3000000 | AS20: =IF(OR(AP20="",AP20=0),"",AQ20/AP20) -> 0 | AT20: 3000000 | AU20: =SUMIFS(TablaEgresos[Valor],TablaEgresos[Categoría],$A20,TablaEgresos[Mes],AT$4) -> 0 | AV20: =IF(AT20="","",AT20-AU20) -> 3000000 | AW20: =IF(OR(AT20="",AT20=0),"",AU20/AT20) -> 0 | AX20: 3000000 | AY20: =SUMIFS(TablaEgresos[Valor],TablaEgresos[Categoría],$A20,TablaEgresos[Mes],AX$4) -> 0 | AZ20: =IF(AX20="","",AX20-AY20) -> 3000000 | BA20: =IF(OR(AX20="",AX20=0),"",AY20/AX20) -> 0 | BB20: 3000000 | BC20: =SUMIFS(TablaEgresos[Valor],TablaEgresos[Categoría],$A20,TablaEgresos[Mes],BB$4) -> 0 | BD20: =IF(BB20="","",BB20-BC20) -> 3000000 | BE20: =IF(OR(BB20="",BB20=0),"",BC20/BB20) -> 0 | BF20: 3000000 | BG20: =SUMIFS(TablaEgresos[Valor],TablaEgresos[Categoría],$A20,TablaEgresos[Mes],BF$4) -> 0 | BH20: =IF(BF20="","",BF20-BG20) -> 3000000 | BI20: =IF(OR(BF20="",BF20=0),"",BG20/BF20) -> 0 | BJ20: 3000000 | BK20: =SUMIFS(TablaEgresos[Valor],TablaEgresos[Categoría],$A20,TablaEgresos[Mes],BJ$4) -> 0 | BL20: =IF(BJ20="","",BJ20-BK20) -> 3000000 | BM20: =IF(OR(BJ20="",BJ20=0),"",BK20/BJ20) -> 0 | BN20: 3000000 | BO20: =SUMIFS(TablaEgresos[Valor],TablaEgresos[Categoría],$A20,TablaEgresos[Mes],BN$4) -> 0 | BP20: =IF(BN20="","",BN20-BO20) -> 3000000 | BQ20: =IF(OR(BN20="",BN20=0),"",BO20/BN20) -> 0 | BR20: 3000000 | BS20: =SUMIFS(TablaEgresos[Valor],TablaEgresos[Categoría],$A20,TablaEgresos[Mes],BR$4) -> 0 | BT20: =IF(BR20="","",BR20-BS20) -> 3000000 | BU20: =IF(OR(BR20="",BR20=0),"",BS20/BR20) -> 0 | BV20: 3000000 | BW20: =SUMIFS(TablaEgresos[Valor],TablaEgresos[Categoría],$A20,TablaEgresos[Mes],BV$4) -> 0 | BX20: =IF(BV20="","",BV20-BW20) -> 3000000 | BY20: =IF(OR(BV20="",BV20=0),"",BW20/BV20) -> 0 | BZ20: 3000000 | CA20: =SUMIFS(TablaEgresos[Valor],TablaEgresos[Categoría],$A20,TablaEgresos[Mes],BZ$4) -> 0 | CB20: =IF(BZ20="","",BZ20-CA20) -> 3000000 | CC20: =IF(OR(BZ20="",BZ20=0),"",CA20/BZ20) -> 0 | CD20: 3000000 | CE20: =SUMIFS(TablaEgresos[Valor],TablaEgresos[Categoría],$A20,TablaEgresos[Mes],CD$4) -> 0 | CF20: =IF(CD20="","",CD20-CE20) -> 3000000 | CG20: =IF(OR(CD20="",CD20=0),"",CE20/CD20) -> 0 | CH20: 3000000 | CI20: =SUMIFS(TablaEgresos[Valor],TablaEgresos[Categoría],$A20,TablaEgresos[Mes],CH$4) -> 0 | CJ20: =IF(CH20="","",CH20-CI20) -> 3000000 | CK20: =IF(OR(CH20="",CH20=0),"",CI20/CH20) -> 0 | CL20: 3000000 | CM20: =SUMIFS(TablaEgresos[Valor],TablaEgresos[Categoría],$A20,TablaEgresos[Mes],CL$4) -> 0 | CN20: =IF(CL20="","",CL20-CM20) -> 3000000 | CO20: =IF(OR(CL20="",CL20=0),"",CM20/CL20) -> 0
A21: Gastos de representación | B21: =IFERROR(AVERAGE(INDEX($B62:$W62,MATCH($B$3,$B$51:$W$51,0)-2):INDEX($B62:$W62,MATCH($B$3,$B$51:$W$51,0))),0) -> 572143.67 | C21: =IFERROR(SLOPE(INDEX($B62:$W62,1):INDEX($B62:$W62,MATCH($B$3,$B$51:$W$51,0)),INDEX($B$50:$W$50,1):INDEX($B$50:$W$50,MATCH($B$3,$B$51:$W$51,0))),0) -> 137239.1 | D21: =IF($B21=0,"",$C21/$B21) -> 0.23986825 | E21: =MAX(0,ROUND($B21+$C21*3,-3)) -> 984000 | G21: =SUMIFS(TablaEgresos[Valor],TablaEgresos[Categoría],$A21,TablaEgresos[Mes],F$4) -> 0 | H21: =IF(F21="","",F21-G21) | I21: =IF(OR(F21="",F21=0),"",G21/F21) | K21: =SUMIFS(TablaEgresos[Valor],TablaEgresos[Categoría],$A21,TablaEgresos[Mes],J$4) -> 557076 | L21: =IF(J21="","",J21-K21) | M21: =IF(OR(J21="",J21=0),"",K21/J21) | O21: =SUMIFS(TablaEgresos[Valor],TablaEgresos[Categoría],$A21,TablaEgresos[Mes],N$4) -> 774299 | P21: =IF(N21="","",N21-O21) | Q21: =IF(OR(N21="",N21=0),"",O21/N21) | S21: =SUMIFS(TablaEgresos[Valor],TablaEgresos[Categoría],$A21,TablaEgresos[Mes],R$4) -> 385056 | T21: =IF(R21="","",R21-S21) | U21: =IF(OR(R21="",R21=0),"",S21/R21) | V21: 0 | W21: =SUMIFS(TablaEgresos[Valor],TablaEgresos[Categoría],$A21,TablaEgresos[Mes],V$4) -> 0 | X21: =IF(V21="","",V21-W21) -> 0 | Y21: =IF(OR(V21="",V21=0),"",W21/V21) | Z21: 1000000 | AA21: =SUMIFS(TablaEgresos[Valor],TablaEgresos[Categoría],$A21,TablaEgresos[Mes],Z$4) -> 0 | AB21: =IF(Z21="","",Z21-AA21) -> 1000000 | AC21: =IF(OR(Z21="",Z21=0),"",AA21/Z21) -> 0 | AD21: 1000000 | AE21: =SUMIFS(TablaEgresos[Valor],TablaEgresos[Categoría],$A21,TablaEgresos[Mes],AD$4) -> 0 | AF21: =IF(AD21="","",AD21-AE21) -> 1000000 | AG21: =IF(OR(AD21="",AD21=0),"",AE21/AD21) -> 0 | AH21: 1000000 | AI21: =SUMIFS(TablaEgresos[Valor],TablaEgresos[Categoría],$A21,TablaEgresos[Mes],AH$4) -> 0 | AJ21: =IF(AH21="","",AH21-AI21) -> 1000000 | AK21: =IF(OR(AH21="",AH21=0),"",AI21/AH21) -> 0 | AL21: 1000000 | AM21: =SUMIFS(TablaEgresos[Valor],TablaEgresos[Categoría],$A21,TablaEgresos[Mes],AL$4) -> 0 | AN21: =IF(AL21="","",AL21-AM21) -> 1000000 | AO21: =IF(OR(AL21="",AL21=0),"",AM21/AL21) -> 0 | AP21: 1000000 | AQ21: =SUMIFS(TablaEgresos[Valor],TablaEgresos[Categoría],$A21,TablaEgresos[Mes],AP$4) -> 0 | AR21: =IF(AP21="","",AP21-AQ21) -> 1000000 | AS21: =IF(OR(AP21="",AP21=0),"",AQ21/AP21) -> 0 | AT21: 1000000 | AU21: =SUMIFS(TablaEgresos[Valor],TablaEgresos[Categoría],$A21,TablaEgresos[Mes],AT$4) -> 0 | AV21: =IF(AT21="","",AT21-AU21) -> 1000000 | AW21: =IF(OR(AT21="",AT21=0),"",AU21/AT21) -> 0 | AX21: 1000000 | AY21: =SUMIFS(TablaEgresos[Valor],TablaEgresos[Categoría],$A21,TablaEgresos[Mes],AX$4) -> 0 | AZ21: =IF(AX21="","",AX21-AY21) -> 1000000 | BA21: =IF(OR(AX21="",AX21=0),"",AY21/AX21) -> 0 | BB21: 1000000 | BC21: =SUMIFS(TablaEgresos[Valor],TablaEgresos[Categoría],$A21,TablaEgresos[Mes],BB$4) -> 0 | BD21: =IF(BB21="","",BB21-BC21) -> 1000000 | BE21: =IF(OR(BB21="",BB21=0),"",BC21/BB21) -> 0 | BF21: 1000000 | BG21: =SUMIFS(TablaEgresos[Valor],TablaEgresos[Categoría],$A21,TablaEgresos[Mes],BF$4) -> 0 | BH21: =IF(BF21="","",BF21-BG21) -> 1000000 | BI21: =IF(OR(BF21="",BF21=0),"",BG21/BF21) -> 0 | BJ21: 1000000 | BK21: =SUMIFS(TablaEgresos[Valor],TablaEgresos[Categoría],$A21,TablaEgresos[Mes],BJ$4) -> 0 | BL21: =IF(BJ21="","",BJ21-BK21) -> 1000000 | BM21: =IF(OR(BJ21="",BJ21=0),"",BK21/BJ21) -> 0 | BN21: 1000000 | BO21: =SUMIFS(TablaEgresos[Valor],TablaEgresos[Categoría],$A21,TablaEgresos[Mes],BN$4) -> 0 | BP21: =IF(BN21="","",BN21-BO21) -> 1000000 | BQ21: =IF(OR(BN21="",BN21=0),"",BO21/BN21) -> 0 | BR21: 1000000 | BS21: =SUMIFS(TablaEgresos[Valor],TablaEgresos[Categoría],$A21,TablaEgresos[Mes],BR$4) -> 0 | BT21: =IF(BR21="","",BR21-BS21) -> 1000000 | BU21: =IF(OR(BR21="",BR21=0),"",BS21/BR21) -> 0 | BV21: 1000000 | BW21: =SUMIFS(TablaEgresos[Valor],TablaEgresos[Categoría],$A21,TablaEgresos[Mes],BV$4) -> 0 | BX21: =IF(BV21="","",BV21-BW21) -> 1000000 | BY21: =IF(OR(BV21="",BV21=0),"",BW21/BV21) -> 0 | BZ21: 1000000 | CA21: =SUMIFS(TablaEgresos[Valor],TablaEgresos[Categoría],$A21,TablaEgresos[Mes],BZ$4) -> 0 | CB21: =IF(BZ21="","",BZ21-CA21) -> 1000000 | CC21: =IF(OR(BZ21="",BZ21=0),"",CA21/BZ21) -> 0 | CD21: 1000000 | CE21: =SUMIFS(TablaEgresos[Valor],TablaEgresos[Categoría],$A21,TablaEgresos[Mes],CD$4) -> 0 | CF21: =IF(CD21="","",CD21-CE21) -> 1000000 | CG21: =IF(OR(CD21="",CD21=0),"",CE21/CD21) -> 0 | CH21: 1000000 | CI21: =SUMIFS(TablaEgresos[Valor],TablaEgresos[Categoría],$A21,TablaEgresos[Mes],CH$4) -> 0 | CJ21: =IF(CH21="","",CH21-CI21) -> 1000000 | CK21: =IF(OR(CH21="",CH21=0),"",CI21/CH21) -> 0 | CL21: 1000000 | CM21: =SUMIFS(TablaEgresos[Valor],TablaEgresos[Categoría],$A21,TablaEgresos[Mes],CL$4) -> 0 | CN21: =IF(CL21="","",CL21-CM21) -> 1000000 | CO21: =IF(OR(CL21="",CL21=0),"",CM21/CL21) -> 0
A22: Renting | B22: =IFERROR(AVERAGE(INDEX($B66:$W66,MATCH($B$3,$B$51:$W$51,0)-2):INDEX($B66:$W66,MATCH($B$3,$B$51:$W$51,0))),0) -> 0 | C22: =IFERROR(SLOPE(INDEX($B66:$W66,1):INDEX($B66:$W66,MATCH($B$3,$B$51:$W$51,0)),INDEX($B$50:$W$50,1):INDEX($B$50:$W$50,MATCH($B$3,$B$51:$W$51,0))),0) -> 0 | D22: =IF($B22=0,"",$C22/$B22) | E22: =MAX(0,ROUND($B22+$C22*3,-3)) -> 0 | G22: =SUMIFS(TablaEgresos[Valor],TablaEgresos[Categoría],$A22,TablaEgresos[Mes],F$4) -> 0 | H22: =IF(F22="","",F22-G22) | I22: =IF(OR(F22="",F22=0),"",G22/F22) | K22: =SUMIFS(TablaEgresos[Valor],TablaEgresos[Categoría],$A22,TablaEgresos[Mes],J$4) -> 0 | L22: =IF(J22="","",J22-K22) | M22: =IF(OR(J22="",J22=0),"",K22/J22) | O22: =SUMIFS(TablaEgresos[Valor],TablaEgresos[Categoría],$A22,TablaEgresos[Mes],N$4) -> 0 | P22: =IF(N22="","",N22-O22) | Q22: =IF(OR(N22="",N22=0),"",O22/N22) | S22: =SUMIFS(TablaEgresos[Valor],TablaEgresos[Categoría],$A22,TablaEgresos[Mes],R$4) -> 0 | T22: =IF(R22="","",R22-S22) | U22: =IF(OR(R22="",R22=0),"",S22/R22) | V22: 12000000 | W22: =SUMIFS(TablaEgresos[Valor],TablaEgresos[Categoría],$A22,TablaEgresos[Mes],V$4) -> 0 | X22: =IF(V22="","",V22-W22) -> 12000000 | Y22: =IF(OR(V22="",V22=0),"",W22/V22) -> 0 | Z22: 12000000 | AA22: =SUMIFS(TablaEgresos[Valor],TablaEgresos[Categoría],$A22,TablaEgresos[Mes],Z$4) -> 0 | AB22: =IF(Z22="","",Z22-AA22) -> 12000000 | AC22: =IF(OR(Z22="",Z22=0),"",AA22/Z22) -> 0 | AD22: 12000000 | AE22: =SUMIFS(TablaEgresos[Valor],TablaEgresos[Categoría],$A22,TablaEgresos[Mes],AD$4) -> 0 | AF22: =IF(AD22="","",AD22-AE22) -> 12000000 | AG22: =IF(OR(AD22="",AD22=0),"",AE22/AD22) -> 0 | AH22: 12000000 | AI22: =SUMIFS(TablaEgresos[Valor],TablaEgresos[Categoría],$A22,TablaEgresos[Mes],AH$4) -> 0 | AJ22: =IF(AH22="","",AH22-AI22) -> 12000000 | AK22: =IF(OR(AH22="",AH22=0),"",AI22/AH22) -> 0 | AL22: 12000000 | AM22: =SUMIFS(TablaEgresos[Valor],TablaEgresos[Categoría],$A22,TablaEgresos[Mes],AL$4) -> 0 | AN22: =IF(AL22="","",AL22-AM22) -> 12000000 | AO22: =IF(OR(AL22="",AL22=0),"",AM22/AL22) -> 0 | AP22: 12000000 | AQ22: =SUMIFS(TablaEgresos[Valor],TablaEgresos[Categoría],$A22,TablaEgresos[Mes],AP$4) -> 0 | AR22: =IF(AP22="","",AP22-AQ22) -> 12000000 | AS22: =IF(OR(AP22="",AP22=0),"",AQ22/AP22) -> 0 | AT22: 12000000 | AU22: =SUMIFS(TablaEgresos[Valor],TablaEgresos[Categoría],$A22,TablaEgresos[Mes],AT$4) -> 0 | AV22: =IF(AT22="","",AT22-AU22) -> 12000000 | AW22: =IF(OR(AT22="",AT22=0),"",AU22/AT22) -> 0 | AX22: 12000000 | AY22: =SUMIFS(TablaEgresos[Valor],TablaEgresos[Categoría],$A22,TablaEgresos[Mes],AX$4) -> 0 | AZ22: =IF(AX22="","",AX22-AY22) -> 12000000 | BA22: =IF(OR(AX22="",AX22=0),"",AY22/AX22) -> 0 | BB22: 12000000 | BC22: =SUMIFS(TablaEgresos[Valor],TablaEgresos[Categoría],$A22,TablaEgresos[Mes],BB$4) -> 0 | BD22: =IF(BB22="","",BB22-BC22) -> 12000000 | BE22: =IF(OR(BB22="",BB22=0),"",BC22/BB22) -> 0 | BF22: 12000000 | BG22: =SUMIFS(TablaEgresos[Valor],TablaEgresos[Categoría],$A22,TablaEgresos[Mes],BF$4) -> 0 | BH22: =IF(BF22="","",BF22-BG22) -> 12000000 | BI22: =IF(OR(BF22="",BF22=0),"",BG22/BF22) -> 0 | BJ22: 12000000 | BK22: =SUMIFS(TablaEgresos[Valor],TablaEgresos[Categoría],$A22,TablaEgresos[Mes],BJ$4) -> 0 | BL22: =IF(BJ22="","",BJ22-BK22) -> 12000000 | BM22: =IF(OR(BJ22="",BJ22=0),"",BK22/BJ22) -> 0 | BN22: 12000000 | BO22: =SUMIFS(TablaEgresos[Valor],TablaEgresos[Categoría],$A22,TablaEgresos[Mes],BN$4) -> 0 | BP22: =IF(BN22="","",BN22-BO22) -> 12000000 | BQ22: =IF(OR(BN22="",BN22=0),"",BO22/BN22) -> 0 | BR22: 12000000 | BS22: =SUMIFS(TablaEgresos[Valor],TablaEgresos[Categoría],$A22,TablaEgresos[Mes],BR$4) -> 0 | BT22: =IF(BR22="","",BR22-BS22) -> 12000000 | BU22: =IF(OR(BR22="",BR22=0),"",BS22/BR22) -> 0 | BV22: 12000000 | BW22: =SUMIFS(TablaEgresos[Valor],TablaEgresos[Categoría],$A22,TablaEgresos[Mes],BV$4) -> 0 | BX22: =IF(BV22="","",BV22-BW22) -> 12000000 | BY22: =IF(OR(BV22="",BV22=0),"",BW22/BV22) -> 0 | BZ22: 12000000 | CA22: =SUMIFS(TablaEgresos[Valor],TablaEgresos[Categoría],$A22,TablaEgresos[Mes],BZ$4) -> 0 | CB22: =IF(BZ22="","",BZ22-CA22) -> 12000000 | CC22: =IF(OR(BZ22="",BZ22=0),"",CA22/BZ22) -> 0 | CD22: 12000000 | CE22: =SUMIFS(TablaEgresos[Valor],TablaEgresos[Categoría],$A22,TablaEgresos[Mes],CD$4) -> 0 | CF22: =IF(CD22="","",CD22-CE22) -> 12000000 | CG22: =IF(OR(CD22="",CD22=0),"",CE22/CD22) -> 0 | CH22: 12000000 | CI22: =SUMIFS(TablaEgresos[Valor],TablaEgresos[Categoría],$A22,TablaEgresos[Mes],CH$4) -> 0 | CJ22: =IF(CH22="","",CH22-CI22) -> 12000000 | CK22: =IF(OR(CH22="",CH22=0),"",CI22/CH22) -> 0 | CL22: 12000000 | CM22: =SUMIFS(TablaEgresos[Valor],TablaEgresos[Categoría],$A22,TablaEgresos[Mes],CL$4) -> 0 | CN22: =IF(CL22="","",CL22-CM22) -> 12000000 | CO22: =IF(OR(CL22="",CL22=0),"",CM22/CL22) -> 0
A23: Subtotal Operación | B23: =SUM(B12:B22) -> 7805236.9 | C23: =SUM(C12:C22) -> 2949321.7 | D23: =IF(B23=0,"",C23/B23) -> 0.37786446 | E23: =SUM(E12:E22) -> 16653000 | F23: =SUM(F12:F22) -> 0 | G23: =SUM(G12:G22) -> 468019.13 | H23: =SUM(H12:H22) -> 0 | I23: =IF(F23=0,"",G23/F23) | J23: =SUM(J12:J22) -> 0 | K23: =SUM(K12:K22) -> 5403578.5 | L23: =SUM(L12:L22) -> 0 | M23: =IF(J23=0,"",K23/J23) | N23: =SUM(N12:N22) -> 0 | O23: =SUM(O12:O22) -> 8867772.2 | P23: =SUM(P12:P22) -> 0 | Q23: =IF(N23=0,"",O23/N23) | R23: =SUM(R12:R22) -> 0 | S23: =SUM(S12:S22) -> 9144360.1 | T23: =SUM(T12:T22) -> 0 | U23: =IF(R23=0,"",S23/R23) | V23: =SUM(V12:V22) -> 27500000 | W23: =SUM(W12:W22) -> 6365783.4 | X23: =SUM(X12:X22) -> 21134217 | Y23: =IF(V23=0,"",W23/V23) -> 0.23148303 | Z23: =SUM(Z12:Z22) -> 32800000 | AA23: =SUM(AA12:AA22) -> 0 | AB23: =SUM(AB12:AB22) -> 32800000 | AC23: =IF(Z23=0,"",AA23/Z23) -> 0 | AD23: =SUM(AD12:AD22) -> 32800000 | AE23: =SUM(AE12:AE22) -> 0 | AF23: =SUM(AF12:AF22) -> 32800000 | AG23: =IF(AD23=0,"",AE23/AD23) -> 0 | AH23: =SUM(AH12:AH22) -> 32800000 | AI23: =SUM(AI12:AI22) -> 0 | AJ23: =SUM(AJ12:AJ22) -> 32800000 | AK23: =IF(AH23=0,"",AI23/AH23) -> 0 | AL23: =SUM(AL12:AL22) -> 32800000 | AM23: =SUM(AM12:AM22) -> 0 | AN23: =SUM(AN12:AN22) -> 32800000 | AO23: =IF(AL23=0,"",AM23/AL23) -> 0 | AP23: =SUM(AP12:AP22) -> 32800000 | AQ23: =SUM(AQ12:AQ22) -> 0 | AR23: =SUM(AR12:AR22) -> 32800000 | AS23: =IF(AP23=0,"",AQ23/AP23) -> 0 | AT23: =SUM(AT12:AT22) -> 32800000 | AU23: =SUM(AU12:AU22) -> 0 | AV23: =SUM(AV12:AV22) -> 32800000 | AW23: =IF(AT23=0,"",AU23/AT23) -> 0 | AX23: =SUM(AX12:AX22) -> 32800000 | AY23: =SUM(AY12:AY22) -> 0 | AZ23: =SUM(AZ12:AZ22) -> 32800000 | BA23: =IF(AX23=0,"",AY23/AX23) -> 0 | BB23: =SUM(BB12:BB22) -> 32800000 | BC23: =SUM(BC12:BC22) -> 0 | BD23: =SUM(BD12:BD22) -> 32800000 | BE23: =IF(BB23=0,"",BC23/BB23) -> 0 | BF23: =SUM(BF12:BF22) -> 32800000 | BG23: =SUM(BG12:BG22) -> 0 | BH23: =SUM(BH12:BH22) -> 32800000 | BI23: =IF(BF23=0,"",BG23/BF23) -> 0 | BJ23: =SUM(BJ12:BJ22) -> 32800000 | BK23: =SUM(BK12:BK22) -> 0 | BL23: =SUM(BL12:BL22) -> 32800000 | BM23: =IF(BJ23=0,"",BK23/BJ23) -> 0 | BN23: =SUM(BN12:BN22) -> 32800000 | BO23: =SUM(BO12:BO22) -> 0 | BP23: =SUM(BP12:BP22) -> 32800000 | BQ23: =IF(BN23=0,"",BO23/BN23) -> 0 | BR23: =SUM(BR12:BR22) -> 32800000 | BS23: =SUM(BS12:BS22) -> 0 | BT23: =SUM(BT12:BT22) -> 32800000 | BU23: =IF(BR23=0,"",BS23/BR23) -> 0 | BV23: =SUM(BV12:BV22) -> 32800000 | BW23: =SUM(BW12:BW22) -> 0 | BX23: =SUM(BX12:BX22) -> 32800000 | BY23: =IF(BV23=0,"",BW23/BV23) -> 0 | BZ23: =SUM(BZ12:BZ22) -> 32800000 | CA23: =SUM(CA12:CA22) -> 0 | CB23: =SUM(CB12:CB22) -> 32800000 | CC23: =IF(BZ23=0,"",CA23/BZ23) -> 0 | CD23: =SUM(CD12:CD22) -> 32800000 | CE23: =SUM(CE12:CE22) -> 0 | CF23: =SUM(CF12:CF22) -> 32800000 | CG23: =IF(CD23=0,"",CE23/CD23) -> 0 | CH23: =SUM(CH12:CH22) -> 32800000 | CI23: =SUM(CI12:CI22) -> 0 | CJ23: =SUM(CJ12:CJ22) -> 32800000 | CK23: =IF(CH23=0,"",CI23/CH23) -> 0 | CL23: =SUM(CL12:CL22) -> 32800000 | CM23: =SUM(CM12:CM22) -> 0 | CN23: =SUM(CN12:CN22) -> 32800000 | CO23: =IF(CL23=0,"",CM23/CL23) -> 0
A24: NÓMINA
A25: Sueldos empleados | B25: =IFERROR(AVERAGE(INDEX($B69:$W69,MATCH($B$3,$B$51:$W$51,0)-2):INDEX($B69:$W69,MATCH($B$3,$B$51:$W$51,0))),0) -> 3384593.6 | C25: =IFERROR(SLOPE(INDEX($B69:$W69,1):INDEX($B69:$W69,MATCH($B$3,$B$51:$W$51,0)),INDEX($B$50:$W$50,1):INDEX($B$50:$W$50,MATCH($B$3,$B$51:$W$51,0))),0) -> 1930977.9 | D25: =IF($B25=0,"",$C25/$B25) -> 0.57051986 | E25: =MAX(0,ROUND($B25+$C25*3,-3)) -> 9178000 | G25: =SUMIFS(TablaEgresos[Valor],TablaEgresos[Categoría],$A25,TablaEgresos[Mes],F$4) -> 0 | H25: =IF(F25="","",F25-G25) | I25: =IF(OR(F25="",F25=0),"",G25/F25) | K25: =SUMIFS(TablaEgresos[Valor],TablaEgresos[Categoría],$A25,TablaEgresos[Mes],J$4) -> 1765927.4 | L25: =IF(J25="","",J25-K25) | M25: =IF(OR(J25="",J25=0),"",K25/J25) | O25: =SUMIFS(TablaEgresos[Valor],TablaEgresos[Categoría],$A25,TablaEgresos[Mes],N$4) -> 2043927 | P25: =IF(N25="","",N25-O25) | Q25: =IF(OR(N25="",N25=0),"",O25/N25) | S25: =SUMIFS(TablaEgresos[Valor],TablaEgresos[Categoría],$A25,TablaEgresos[Mes],R$4) -> 6343926.3 | T25: =IF(R25="","",R25-S25) | U25: =IF(OR(R25="",R25=0),"",S25/R25) | V25: 10000000 | W25: =SUMIFS(TablaEgresos[Valor],TablaEgresos[Categoría],$A25,TablaEgresos[Mes],V$4) -> 9656272.8 | X25: =IF(V25="","",V25-W25) -> 343727.24 | Y25: =IF(OR(V25="",V25=0),"",W25/V25) -> 0.96562728 | Z25: 11000000 | AA25: =SUMIFS(TablaEgresos[Valor],TablaEgresos[Categoría],$A25,TablaEgresos[Mes],Z$4) -> 0 | AB25: =IF(Z25="","",Z25-AA25) -> 11000000 | AC25: =IF(OR(Z25="",Z25=0),"",AA25/Z25) -> 0 | AD25: 11000000 | AE25: =SUMIFS(TablaEgresos[Valor],TablaEgresos[Categoría],$A25,TablaEgresos[Mes],AD$4) -> 0 | AF25: =IF(AD25="","",AD25-AE25) -> 11000000 | AG25: =IF(OR(AD25="",AD25=0),"",AE25/AD25) -> 0 | AH25: 11000000 | AI25: =SUMIFS(TablaEgresos[Valor],TablaEgresos[Categoría],$A25,TablaEgresos[Mes],AH$4) -> 0 | AJ25: =IF(AH25="","",AH25-AI25) -> 11000000 | AK25: =IF(OR(AH25="",AH25=0),"",AI25/AH25) -> 0 | AL25: 11000000 | AM25: =SUMIFS(TablaEgresos[Valor],TablaEgresos[Categoría],$A25,TablaEgresos[Mes],AL$4) -> 0 | AN25: =IF(AL25="","",AL25-AM25) -> 11000000 | AO25: =IF(OR(AL25="",AL25=0),"",AM25/AL25) -> 0 | AP25: 11000000 | AQ25: =SUMIFS(TablaEgresos[Valor],TablaEgresos[Categoría],$A25,TablaEgresos[Mes],AP$4) -> 0 | AR25: =IF(AP25="","",AP25-AQ25) -> 11000000 | AS25: =IF(OR(AP25="",AP25=0),"",AQ25/AP25) -> 0 | AT25: 11000000 | AU25: =SUMIFS(TablaEgresos[Valor],TablaEgresos[Categoría],$A25,TablaEgresos[Mes],AT$4) -> 0 | AV25: =IF(AT25="","",AT25-AU25) -> 11000000 | AW25: =IF(OR(AT25="",AT25=0),"",AU25/AT25) -> 0 | AX25: 11000000 | AY25: =SUMIFS(TablaEgresos[Valor],TablaEgresos[Categoría],$A25,TablaEgresos[Mes],AX$4) -> 0 | AZ25: =IF(AX25="","",AX25-AY25) -> 11000000 | BA25: =IF(OR(AX25="",AX25=0),"",AY25/AX25) -> 0 | BB25: 11000000 | BC25: =SUMIFS(TablaEgresos[Valor],TablaEgresos[Categoría],$A25,TablaEgresos[Mes],BB$4) -> 0 | BD25: =IF(BB25="","",BB25-BC25) -> 11000000 | BE25: =IF(OR(BB25="",BB25=0),"",BC25/BB25) -> 0 | BF25: 11000000 | BG25: =SUMIFS(TablaEgresos[Valor],TablaEgresos[Categoría],$A25,TablaEgresos[Mes],BF$4) -> 0 | BH25: =IF(BF25="","",BF25-BG25) -> 11000000 | BI25: =IF(OR(BF25="",BF25=0),"",BG25/BF25) -> 0 | BJ25: 11000000 | BK25: =SUMIFS(TablaEgresos[Valor],TablaEgresos[Categoría],$A25,TablaEgresos[Mes],BJ$4) -> 0 | BL25: =IF(BJ25="","",BJ25-BK25) -> 11000000 | BM25: =IF(OR(BJ25="",BJ25=0),"",BK25/BJ25) -> 0 | BN25: 11000000 | BO25: =SUMIFS(TablaEgresos[Valor],TablaEgresos[Categoría],$A25,TablaEgresos[Mes],BN$4) -> 0 | BP25: =IF(BN25="","",BN25-BO25) -> 11000000 | BQ25: =IF(OR(BN25="",BN25=0),"",BO25/BN25) -> 0 | BR25: 11000000 | BS25: =SUMIFS(TablaEgresos[Valor],TablaEgresos[Categoría],$A25,TablaEgresos[Mes],BR$4) -> 0 | BT25: =IF(BR25="","",BR25-BS25) -> 11000000 | BU25: =IF(OR(BR25="",BR25=0),"",BS25/BR25) -> 0 | BV25: 11000000 | BW25: =SUMIFS(TablaEgresos[Valor],TablaEgresos[Categoría],$A25,TablaEgresos[Mes],BV$4) -> 0 | BX25: =IF(BV25="","",BV25-BW25) -> 11000000 | BY25: =IF(OR(BV25="",BV25=0),"",BW25/BV25) -> 0 | BZ25: 11000000 | CA25: =SUMIFS(TablaEgresos[Valor],TablaEgresos[Categoría],$A25,TablaEgresos[Mes],BZ$4) -> 0 | CB25: =IF(BZ25="","",BZ25-CA25) -> 11000000 | CC25: =IF(OR(BZ25="",BZ25=0),"",CA25/BZ25) -> 0 | CD25: 11000000 | CE25: =SUMIFS(TablaEgresos[Valor],TablaEgresos[Categoría],$A25,TablaEgresos[Mes],CD$4) -> 0 | CF25: =IF(CD25="","",CD25-CE25) -> 11000000 | CG25: =IF(OR(CD25="",CD25=0),"",CE25/CD25) -> 0 | CH25: 11000000 | CI25: =SUMIFS(TablaEgresos[Valor],TablaEgresos[Categoría],$A25,TablaEgresos[Mes],CH$4) -> 0 | CJ25: =IF(CH25="","",CH25-CI25) -> 11000000 | CK25: =IF(OR(CH25="",CH25=0),"",CI25/CH25) -> 0 | CL25: 11000000 | CM25: =SUMIFS(TablaEgresos[Valor],TablaEgresos[Categoría],$A25,TablaEgresos[Mes],CL$4) -> 0 | CN25: =IF(CL25="","",CL25-CM25) -> 11000000 | CO25: =IF(OR(CL25="",CL25=0),"",CM25/CL25) -> 0
A26: Sueldos directivos | B26: =IFERROR(AVERAGE(INDEX($B70:$W70,MATCH($B$3,$B$51:$W$51,0)-2):INDEX($B70:$W70,MATCH($B$3,$B$51:$W$51,0))),0) -> 0 | C26: =IFERROR(SLOPE(INDEX($B70:$W70,1):INDEX($B70:$W70,MATCH($B$3,$B$51:$W$51,0)),INDEX($B$50:$W$50,1):INDEX($B$50:$W$50,MATCH($B$3,$B$51:$W$51,0))),0) -> 0 | D26: =IF($B26=0,"",$C26/$B26) | E26: =MAX(0,ROUND($B26+$C26*3,-3)) -> 0 | G26: =SUMIFS(TablaEgresos[Valor],TablaEgresos[Categoría],$A26,TablaEgresos[Mes],F$4) -> 0 | H26: =IF(F26="","",F26-G26) | I26: =IF(OR(F26="",F26=0),"",G26/F26) | K26: =SUMIFS(TablaEgresos[Valor],TablaEgresos[Categoría],$A26,TablaEgresos[Mes],J$4) -> 0 | L26: =IF(J26="","",J26-K26) | M26: =IF(OR(J26="",J26=0),"",K26/J26) | O26: =SUMIFS(TablaEgresos[Valor],TablaEgresos[Categoría],$A26,TablaEgresos[Mes],N$4) -> 0 | P26: =IF(N26="","",N26-O26) | Q26: =IF(OR(N26="",N26=0),"",O26/N26) | S26: =SUMIFS(TablaEgresos[Valor],TablaEgresos[Categoría],$A26,TablaEgresos[Mes],R$4) -> 0 | T26: =IF(R26="","",R26-S26) | U26: =IF(OR(R26="",R26=0),"",S26/R26) | V26: 36791951 | W26: =SUMIFS(TablaEgresos[Valor],TablaEgresos[Categoría],$A26,TablaEgresos[Mes],V$4) -> 20291951 | X26: =IF(V26="","",V26-W26) -> 16500000 | Y26: =IF(OR(V26="",V26=0),"",W26/V26) -> 0.55153235 | Z26: 31723000 | AA26: =SUMIFS(TablaEgresos[Valor],TablaEgresos[Categoría],$A26,TablaEgresos[Mes],Z$4) -> 0 | AB26: =IF(Z26="","",Z26-AA26) -> 31723000 | AC26: =IF(OR(Z26="",Z26=0),"",AA26/Z26) -> 0 | AD26: 31723000 | AE26: =SUMIFS(TablaEgresos[Valor],TablaEgresos[Categoría],$A26,TablaEgresos[Mes],AD$4) -> 0 | AF26: =IF(AD26="","",AD26-AE26) -> 31723000 | AG26: =IF(OR(AD26="",AD26=0),"",AE26/AD26) -> 0 | AH26: 31723000 | AI26: =SUMIFS(TablaEgresos[Valor],TablaEgresos[Categoría],$A26,TablaEgresos[Mes],AH$4) -> 0 | AJ26: =IF(AH26="","",AH26-AI26) -> 31723000 | AK26: =IF(OR(AH26="",AH26=0),"",AI26/AH26) -> 0 | AL26: 31723000 | AM26: =SUMIFS(TablaEgresos[Valor],TablaEgresos[Categoría],$A26,TablaEgresos[Mes],AL$4) -> 0 | AN26: =IF(AL26="","",AL26-AM26) -> 31723000 | AO26: =IF(OR(AL26="",AL26=0),"",AM26/AL26) -> 0 | AP26: 31723000 | AQ26: =SUMIFS(TablaEgresos[Valor],TablaEgresos[Categoría],$A26,TablaEgresos[Mes],AP$4) -> 0 | AR26: =IF(AP26="","",AP26-AQ26) -> 31723000 | AS26: =IF(OR(AP26="",AP26=0),"",AQ26/AP26) -> 0 | AT26: 31723000 | AU26: =SUMIFS(TablaEgresos[Valor],TablaEgresos[Categoría],$A26,TablaEgresos[Mes],AT$4) -> 0 | AV26: =IF(AT26="","",AT26-AU26) -> 31723000 | AW26: =IF(OR(AT26="",AT26=0),"",AU26/AT26) -> 0 | AX26: 31723000 | AY26: =SUMIFS(TablaEgresos[Valor],TablaEgresos[Categoría],$A26,TablaEgresos[Mes],AX$4) -> 0 | AZ26: =IF(AX26="","",AX26-AY26) -> 31723000 | BA26: =IF(OR(AX26="",AX26=0),"",AY26/AX26) -> 0 | BB26: 31723000 | BC26: =SUMIFS(TablaEgresos[Valor],TablaEgresos[Categoría],$A26,TablaEgresos[Mes],BB$4) -> 0 | BD26: =IF(BB26="","",BB26-BC26) -> 31723000 | BE26: =IF(OR(BB26="",BB26=0),"",BC26/BB26) -> 0 | BF26: 31723000 | BG26: =SUMIFS(TablaEgresos[Valor],TablaEgresos[Categoría],$A26,TablaEgresos[Mes],BF$4) -> 0 | BH26: =IF(BF26="","",BF26-BG26) -> 31723000 | BI26: =IF(OR(BF26="",BF26=0),"",BG26/BF26) -> 0 | BJ26: 31723000 | BK26: =SUMIFS(TablaEgresos[Valor],TablaEgresos[Categoría],$A26,TablaEgresos[Mes],BJ$4) -> 0 | BL26: =IF(BJ26="","",BJ26-BK26) -> 31723000 | BM26: =IF(OR(BJ26="",BJ26=0),"",BK26/BJ26) -> 0 | BN26: 31723000 | BO26: =SUMIFS(TablaEgresos[Valor],TablaEgresos[Categoría],$A26,TablaEgresos[Mes],BN$4) -> 0 | BP26: =IF(BN26="","",BN26-BO26) -> 31723000 | BQ26: =IF(OR(BN26="",BN26=0),"",BO26/BN26) -> 0 | BR26: 31723000 | BS26: =SUMIFS(TablaEgresos[Valor],TablaEgresos[Categoría],$A26,TablaEgresos[Mes],BR$4) -> 0 | BT26: =IF(BR26="","",BR26-BS26) -> 31723000 | BU26: =IF(OR(BR26="",BR26=0),"",BS26/BR26) -> 0 | BV26: 31723000 | BW26: =SUMIFS(TablaEgresos[Valor],TablaEgresos[Categoría],$A26,TablaEgresos[Mes],BV$4) -> 0 | BX26: =IF(BV26="","",BV26-BW26) -> 31723000 | BY26: =IF(OR(BV26="",BV26=0),"",BW26/BV26) -> 0 | BZ26: 31723000 | CA26: =SUMIFS(TablaEgresos[Valor],TablaEgresos[Categoría],$A26,TablaEgresos[Mes],BZ$4) -> 0 | CB26: =IF(BZ26="","",BZ26-CA26) -> 31723000 | CC26: =IF(OR(BZ26="",BZ26=0),"",CA26/BZ26) -> 0 | CD26: 31723000 | CE26: =SUMIFS(TablaEgresos[Valor],TablaEgresos[Categoría],$A26,TablaEgresos[Mes],CD$4) -> 0 | CF26: =IF(CD26="","",CD26-CE26) -> 31723000 | CG26: =IF(OR(CD26="",CD26=0),"",CE26/CD26) -> 0 | CH26: 31723000 | CI26: =SUMIFS(TablaEgresos[Valor],TablaEgresos[Categoría],$A26,TablaEgresos[Mes],CH$4) -> 0 | CJ26: =IF(CH26="","",CH26-CI26) -> 31723000 | CK26: =IF(OR(CH26="",CH26=0),"",CI26/CH26) -> 0 | CL26: 31723000 | CM26: =SUMIFS(TablaEgresos[Valor],TablaEgresos[Categoría],$A26,TablaEgresos[Mes],CL$4) -> 0 | CN26: =IF(CL26="","",CL26-CM26) -> 31723000 | CO26: =IF(OR(CL26="",CL26=0),"",CM26/CL26) -> 0
A27: Bonificaciones | B27: =IFERROR(AVERAGE(INDEX($B71:$W71,MATCH($B$3,$B$51:$W$51,0)-2):INDEX($B71:$W71,MATCH($B$3,$B$51:$W$51,0))),0) -> 5338206.5 | C27: =IFERROR(SLOPE(INDEX($B71:$W71,1):INDEX($B71:$W71,MATCH($B$3,$B$51:$W$51,0)),INDEX($B$50:$W$50,1):INDEX($B$50:$W$50,MATCH($B$3,$B$51:$W$51,0))),0) -> 2053944.3 | D27: =IF($B27=0,"",$C27/$B27) -> 0.38476298 | E27: =MAX(0,ROUND($B27+$C27*3,-3)) -> 11500000 | G27: =SUMIFS(TablaEgresos[Valor],TablaEgresos[Categoría],$A27,TablaEgresos[Mes],F$4) -> 0 | H27: =IF(F27="","",F27-G27) | I27: =IF(OR(F27="",F27=0),"",G27/F27) | K27: =SUMIFS(TablaEgresos[Valor],TablaEgresos[Categoría],$A27,TablaEgresos[Mes],J$4) -> 4017588 | L27: =IF(J27="","",J27-K27) | M27: =IF(OR(J27="",J27=0),"",K27/J27) | O27: =SUMIFS(TablaEgresos[Valor],TablaEgresos[Categoría],$A27,TablaEgresos[Mes],N$4) -> 5717031.8 | P27: =IF(N27="","",N27-O27) | Q27: =IF(OR(N27="",N27=0),"",O27/N27) | S27: =SUMIFS(TablaEgresos[Valor],TablaEgresos[Categoría],$A27,TablaEgresos[Mes],R$4) -> 6279999.6 | T27: =IF(R27="","",R27-S27) | U27: =IF(OR(R27="",R27=0),"",S27/R27) | V27: 82000000 | W27: =SUMIFS(TablaEgresos[Valor],TablaEgresos[Categoría],$A27,TablaEgresos[Mes],V$4) -> 80314004 | X27: =IF(V27="","",V27-W27) -> 1685995.6 | Y27: =IF(OR(V27="",V27=0),"",W27/V27) -> 0.97943908 | Z27: 0 | AA27: =SUMIFS(TablaEgresos[Valor],TablaEgresos[Categoría],$A27,TablaEgresos[Mes],Z$4) -> 0 | AB27: =IF(Z27="","",Z27-AA27) -> 0 | AC27: =IF(OR(Z27="",Z27=0),"",AA27/Z27) | AD27: 0 | AE27: =SUMIFS(TablaEgresos[Valor],TablaEgresos[Categoría],$A27,TablaEgresos[Mes],AD$4) -> 0 | AF27: =IF(AD27="","",AD27-AE27) -> 0 | AG27: =IF(OR(AD27="",AD27=0),"",AE27/AD27) | AH27: 0 | AI27: =SUMIFS(TablaEgresos[Valor],TablaEgresos[Categoría],$A27,TablaEgresos[Mes],AH$4) -> 0 | AJ27: =IF(AH27="","",AH27-AI27) -> 0 | AK27: =IF(OR(AH27="",AH27=0),"",AI27/AH27) | AL27: 0 | AM27: =SUMIFS(TablaEgresos[Valor],TablaEgresos[Categoría],$A27,TablaEgresos[Mes],AL$4) -> 0 | AN27: =IF(AL27="","",AL27-AM27) -> 0 | AO27: =IF(OR(AL27="",AL27=0),"",AM27/AL27) | AP27: 0 | AQ27: =SUMIFS(TablaEgresos[Valor],TablaEgresos[Categoría],$A27,TablaEgresos[Mes],AP$4) -> 0 | AR27: =IF(AP27="","",AP27-AQ27) -> 0 | AS27: =IF(OR(AP27="",AP27=0),"",AQ27/AP27) | AT27: 0 | AU27: =SUMIFS(TablaEgresos[Valor],TablaEgresos[Categoría],$A27,TablaEgresos[Mes],AT$4) -> 0 | AV27: =IF(AT27="","",AT27-AU27) -> 0 | AW27: =IF(OR(AT27="",AT27=0),"",AU27/AT27) | AX27: 0 | AY27: =SUMIFS(TablaEgresos[Valor],TablaEgresos[Categoría],$A27,TablaEgresos[Mes],AX$4) -> 0 | AZ27: =IF(AX27="","",AX27-AY27) -> 0 | BA27: =IF(OR(AX27="",AX27=0),"",AY27/AX27) | BB27: 0 | BC27: =SUMIFS(TablaEgresos[Valor],TablaEgresos[Categoría],$A27,TablaEgresos[Mes],BB$4) -> 0 | BD27: =IF(BB27="","",BB27-BC27) -> 0 | BE27: =IF(OR(BB27="",BB27=0),"",BC27/BB27) | BF27: 0 | BG27: =SUMIFS(TablaEgresos[Valor],TablaEgresos[Categoría],$A27,TablaEgresos[Mes],BF$4) -> 0 | BH27: =IF(BF27="","",BF27-BG27) -> 0 | BI27: =IF(OR(BF27="",BF27=0),"",BG27/BF27) | BJ27: 0 | BK27: =SUMIFS(TablaEgresos[Valor],TablaEgresos[Categoría],$A27,TablaEgresos[Mes],BJ$4) -> 0 | BL27: =IF(BJ27="","",BJ27-BK27) -> 0 | BM27: =IF(OR(BJ27="",BJ27=0),"",BK27/BJ27) | BN27: 0 | BO27: =SUMIFS(TablaEgresos[Valor],TablaEgresos[Categoría],$A27,TablaEgresos[Mes],BN$4) -> 0 | BP27: =IF(BN27="","",BN27-BO27) -> 0 | BQ27: =IF(OR(BN27="",BN27=0),"",BO27/BN27) | BR27: 0 | BS27: =SUMIFS(TablaEgresos[Valor],TablaEgresos[Categoría],$A27,TablaEgresos[Mes],BR$4) -> 0 | BT27: =IF(BR27="","",BR27-BS27) -> 0 | BU27: =IF(OR(BR27="",BR27=0),"",BS27/BR27) | BV27: 0 | BW27: =SUMIFS(TablaEgresos[Valor],TablaEgresos[Categoría],$A27,TablaEgresos[Mes],BV$4) -> 0 | BX27: =IF(BV27="","",BV27-BW27) -> 0 | BY27: =IF(OR(BV27="",BV27=0),"",BW27/BV27) | BZ27: 0 | CA27: =SUMIFS(TablaEgresos[Valor],TablaEgresos[Categoría],$A27,TablaEgresos[Mes],BZ$4) -> 0 | CB27: =IF(BZ27="","",BZ27-CA27) -> 0 | CC27: =IF(OR(BZ27="",BZ27=0),"",CA27/BZ27) | CD27: 0 | CE27: =SUMIFS(TablaEgresos[Valor],TablaEgresos[Categoría],$A27,TablaEgresos[Mes],CD$4) -> 0 | CF27: =IF(CD27="","",CD27-CE27) -> 0 | CG27: =IF(OR(CD27="",CD27=0),"",CE27/CD27) | CH27: 0 | CI27: =SUMIFS(TablaEgresos[Valor],TablaEgresos[Categoría],$A27,TablaEgresos[Mes],CH$4) -> 0 | CJ27: =IF(CH27="","",CH27-CI27) -> 0 | CK27: =IF(OR(CH27="",CH27=0),"",CI27/CH27) | CL27: 0 | CM27: =SUMIFS(TablaEgresos[Valor],TablaEgresos[Categoría],$A27,TablaEgresos[Mes],CL$4) -> 0 | CN27: =IF(CL27="","",CL27-CM27) -> 0 | CO27: =IF(OR(CL27="",CL27=0),"",CM27/CL27)
A28: Beneficios Heads | B28: =IFERROR(AVERAGE(INDEX($B72:$W72,MATCH($B$3,$B$51:$W$51,0)-2):INDEX($B72:$W72,MATCH($B$3,$B$51:$W$51,0))),0) -> 109264.33 | C28: =IFERROR(SLOPE(INDEX($B72:$W72,1):INDEX($B72:$W72,MATCH($B$3,$B$51:$W$51,0)),INDEX($B$50:$W$50,1):INDEX($B$50:$W$50,MATCH($B$3,$B$51:$W$51,0))),0) -> -32779.3 | D28: =IF($B28=0,"",$C28/$B28) -> -0.3 | E28: =MAX(0,ROUND($B28+$C28*3,-3)) -> 11000 | G28: =SUMIFS(TablaEgresos[Valor],TablaEgresos[Categoría],$A28,TablaEgresos[Mes],F$4) -> 0 | H28: =IF(F28="","",F28-G28) | I28: =IF(OR(F28="",F28=0),"",G28/F28) | K28: =SUMIFS(TablaEgresos[Valor],TablaEgresos[Categoría],$A28,TablaEgresos[Mes],J$4) -> 327793 | L28: =IF(J28="","",J28-K28) | M28: =IF(OR(J28="",J28=0),"",K28/J28) | O28: =SUMIFS(TablaEgresos[Valor],TablaEgresos[Categoría],$A28,TablaEgresos[Mes],N$4) -> 0 | P28: =IF(N28="","",N28-O28) | Q28: =IF(OR(N28="",N28=0),"",O28/N28) | S28: =SUMIFS(TablaEgresos[Valor],TablaEgresos[Categoría],$A28,TablaEgresos[Mes],R$4) -> 0 | T28: =IF(R28="","",R28-S28) | U28: =IF(OR(R28="",R28=0),"",S28/R28) | V28: 0 | W28: =SUMIFS(TablaEgresos[Valor],TablaEgresos[Categoría],$A28,TablaEgresos[Mes],V$4) -> 0 | X28: =IF(V28="","",V28-W28) -> 0 | Y28: =IF(OR(V28="",V28=0),"",W28/V28) | Z28: 350000 | AA28: =SUMIFS(TablaEgresos[Valor],TablaEgresos[Categoría],$A28,TablaEgresos[Mes],Z$4) -> 0 | AB28: =IF(Z28="","",Z28-AA28) -> 350000 | AC28: =IF(OR(Z28="",Z28=0),"",AA28/Z28) -> 0 | AD28: 350000 | AE28: =SUMIFS(TablaEgresos[Valor],TablaEgresos[Categoría],$A28,TablaEgresos[Mes],AD$4) -> 0 | AF28: =IF(AD28="","",AD28-AE28) -> 350000 | AG28: =IF(OR(AD28="",AD28=0),"",AE28/AD28) -> 0 | AH28: 350000 | AI28: =SUMIFS(TablaEgresos[Valor],TablaEgresos[Categoría],$A28,TablaEgresos[Mes],AH$4) -> 0 | AJ28: =IF(AH28="","",AH28-AI28) -> 350000 | AK28: =IF(OR(AH28="",AH28=0),"",AI28/AH28) -> 0 | AL28: 350000 | AM28: =SUMIFS(TablaEgresos[Valor],TablaEgresos[Categoría],$A28,TablaEgresos[Mes],AL$4) -> 0 | AN28: =IF(AL28="","",AL28-AM28) -> 350000 | AO28: =IF(OR(AL28="",AL28=0),"",AM28/AL28) -> 0 | AP28: 350000 | AQ28: =SUMIFS(TablaEgresos[Valor],TablaEgresos[Categoría],$A28,TablaEgresos[Mes],AP$4) -> 0 | AR28: =IF(AP28="","",AP28-AQ28) -> 350000 | AS28: =IF(OR(AP28="",AP28=0),"",AQ28/AP28) -> 0 | AT28: 350000 | AU28: =SUMIFS(TablaEgresos[Valor],TablaEgresos[Categoría],$A28,TablaEgresos[Mes],AT$4) -> 0 | AV28: =IF(AT28="","",AT28-AU28) -> 350000 | AW28: =IF(OR(AT28="",AT28=0),"",AU28/AT28) -> 0 | AX28: 350000 | AY28: =SUMIFS(TablaEgresos[Valor],TablaEgresos[Categoría],$A28,TablaEgresos[Mes],AX$4) -> 0 | AZ28: =IF(AX28="","",AX28-AY28) -> 350000 | BA28: =IF(OR(AX28="",AX28=0),"",AY28/AX28) -> 0 | BB28: 350000 | BC28: =SUMIFS(TablaEgresos[Valor],TablaEgresos[Categoría],$A28,TablaEgresos[Mes],BB$4) -> 0 | BD28: =IF(BB28="","",BB28-BC28) -> 350000 | BE28: =IF(OR(BB28="",BB28=0),"",BC28/BB28) -> 0 | BF28: 350000 | BG28: =SUMIFS(TablaEgresos[Valor],TablaEgresos[Categoría],$A28,TablaEgresos[Mes],BF$4) -> 0 | BH28: =IF(BF28="","",BF28-BG28) -> 350000 | BI28: =IF(OR(BF28="",BF28=0),"",BG28/BF28) -> 0 | BJ28: 350000 | BK28: =SUMIFS(TablaEgresos[Valor],TablaEgresos[Categoría],$A28,TablaEgresos[Mes],BJ$4) -> 0 | BL28: =IF(BJ28="","",BJ28-BK28) -> 350000 | BM28: =IF(OR(BJ28="",BJ28=0),"",BK28/BJ28) -> 0 | BN28: 350000 | BO28: =SUMIFS(TablaEgresos[Valor],TablaEgresos[Categoría],$A28,TablaEgresos[Mes],BN$4) -> 0 | BP28: =IF(BN28="","",BN28-BO28) -> 350000 | BQ28: =IF(OR(BN28="",BN28=0),"",BO28/BN28) -> 0 | BR28: 350000 | BS28: =SUMIFS(TablaEgresos[Valor],TablaEgresos[Categoría],$A28,TablaEgresos[Mes],BR$4) -> 0 | BT28: =IF(BR28="","",BR28-BS28) -> 350000 | BU28: =IF(OR(BR28="",BR28=0),"",BS28/BR28) -> 0 | BV28: 350000 | BW28: =SUMIFS(TablaEgresos[Valor],TablaEgresos[Categoría],$A28,TablaEgresos[Mes],BV$4) -> 0 | BX28: =IF(BV28="","",BV28-BW28) -> 350000 | BY28: =IF(OR(BV28="",BV28=0),"",BW28/BV28) -> 0 | BZ28: 350000 | CA28: =SUMIFS(TablaEgresos[Valor],TablaEgresos[Categoría],$A28,TablaEgresos[Mes],BZ$4) -> 0 | CB28: =IF(BZ28="","",BZ28-CA28) -> 350000 | CC28: =IF(OR(BZ28="",BZ28=0),"",CA28/BZ28) -> 0 | CD28: 350000 | CE28: =SUMIFS(TablaEgresos[Valor],TablaEgresos[Categoría],$A28,TablaEgresos[Mes],CD$4) -> 0 | CF28: =IF(CD28="","",CD28-CE28) -> 350000 | CG28: =IF(OR(CD28="",CD28=0),"",CE28/CD28) -> 0 | CH28: 350000 | CI28: =SUMIFS(TablaEgresos[Valor],TablaEgresos[Categoría],$A28,TablaEgresos[Mes],CH$4) -> 0 | CJ28: =IF(CH28="","",CH28-CI28) -> 350000 | CK28: =IF(OR(CH28="",CH28=0),"",CI28/CH28) -> 0 | CL28: 350000 | CM28: =SUMIFS(TablaEgresos[Valor],TablaEgresos[Categoría],$A28,TablaEgresos[Mes],CL$4) -> 0 | CN28: =IF(CL28="","",CL28-CM28) -> 350000 | CO28: =IF(OR(CL28="",CL28=0),"",CM28/CL28) -> 0
A29: Planillas nuevas | B29: =IFERROR(AVERAGE(INDEX($B73:$W73,MATCH($B$3,$B$51:$W$51,0)-2):INDEX($B73:$W73,MATCH($B$3,$B$51:$W$51,0))),0) -> 0 | C29: =IFERROR(SLOPE(INDEX($B73:$W73,1):INDEX($B73:$W73,MATCH($B$3,$B$51:$W$51,0)),INDEX($B$50:$W$50,1):INDEX($B$50:$W$50,MATCH($B$3,$B$51:$W$51,0))),0) -> 0 | D29: =IF($B29=0,"",$C29/$B29) | E29: =MAX(0,ROUND($B29+$C29*3,-3)) -> 0 | G29: =SUMIFS(TablaEgresos[Valor],TablaEgresos[Categoría],$A29,TablaEgresos[Mes],F$4) -> 0 | H29: =IF(F29="","",F29-G29) | I29: =IF(OR(F29="",F29=0),"",G29/F29) | K29: =SUMIFS(TablaEgresos[Valor],TablaEgresos[Categoría],$A29,TablaEgresos[Mes],J$4) -> 0 | L29: =IF(J29="","",J29-K29) | M29: =IF(OR(J29="",J29=0),"",K29/J29) | O29: =SUMIFS(TablaEgresos[Valor],TablaEgresos[Categoría],$A29,TablaEgresos[Mes],N$4) -> 0 | P29: =IF(N29="","",N29-O29) | Q29: =IF(OR(N29="",N29=0),"",O29/N29) | S29: =SUMIFS(TablaEgresos[Valor],TablaEgresos[Categoría],$A29,TablaEgresos[Mes],R$4) -> 0 | T29: =IF(R29="","",R29-S29) | U29: =IF(OR(R29="",R29=0),"",S29/R29) | V29: 0 | W29: =SUMIFS(TablaEgresos[Valor],TablaEgresos[Categoría],$A29,TablaEgresos[Mes],V$4) -> 0 | X29: =IF(V29="","",V29-W29) -> 0 | Y29: =IF(OR(V29="",V29=0),"",W29/V29) | Z29: 6000000 | AA29: =SUMIFS(TablaEgresos[Valor],TablaEgresos[Categoría],$A29,TablaEgresos[Mes],Z$4) -> 0 | AB29: =IF(Z29="","",Z29-AA29) -> 6000000 | AC29: =IF(OR(Z29="",Z29=0),"",AA29/Z29) -> 0 | AD29: 6000000 | AE29: =SUMIFS(TablaEgresos[Valor],TablaEgresos[Categoría],$A29,TablaEgresos[Mes],AD$4) -> 0 | AF29: =IF(AD29="","",AD29-AE29) -> 6000000 | AG29: =IF(OR(AD29="",AD29=0),"",AE29/AD29) -> 0 | AH29: 6000000 | AI29: =SUMIFS(TablaEgresos[Valor],TablaEgresos[Categoría],$A29,TablaEgresos[Mes],AH$4) -> 0 | AJ29: =IF(AH29="","",AH29-AI29) -> 6000000 | AK29: =IF(OR(AH29="",AH29=0),"",AI29/AH29) -> 0 | AL29: 6000000 | AM29: =SUMIFS(TablaEgresos[Valor],TablaEgresos[Categoría],$A29,TablaEgresos[Mes],AL$4) -> 0 | AN29: =IF(AL29="","",AL29-AM29) -> 6000000 | AO29: =IF(OR(AL29="",AL29=0),"",AM29/AL29) -> 0 | AP29: 6000000 | AQ29: =SUMIFS(TablaEgresos[Valor],TablaEgresos[Categoría],$A29,TablaEgresos[Mes],AP$4) -> 0 | AR29: =IF(AP29="","",AP29-AQ29) -> 6000000 | AS29: =IF(OR(AP29="",AP29=0),"",AQ29/AP29) -> 0 | AT29: 6000000 | AU29: =SUMIFS(TablaEgresos[Valor],TablaEgresos[Categoría],$A29,TablaEgresos[Mes],AT$4) -> 0 | AV29: =IF(AT29="","",AT29-AU29) -> 6000000 | AW29: =IF(OR(AT29="",AT29=0),"",AU29/AT29) -> 0 | AX29: 6000000 | AY29: =SUMIFS(TablaEgresos[Valor],TablaEgresos[Categoría],$A29,TablaEgresos[Mes],AX$4) -> 0 | AZ29: =IF(AX29="","",AX29-AY29) -> 6000000 | BA29: =IF(OR(AX29="",AX29=0),"",AY29/AX29) -> 0 | BB29: 6000000 | BC29: =SUMIFS(TablaEgresos[Valor],TablaEgresos[Categoría],$A29,TablaEgresos[Mes],BB$4) -> 0 | BD29: =IF(BB29="","",BB29-BC29) -> 6000000 | BE29: =IF(OR(BB29="",BB29=0),"",BC29/BB29) -> 0 | BF29: 6000000 | BG29: =SUMIFS(TablaEgresos[Valor],TablaEgresos[Categoría],$A29,TablaEgresos[Mes],BF$4) -> 0 | BH29: =IF(BF29="","",BF29-BG29) -> 6000000 | BI29: =IF(OR(BF29="",BF29=0),"",BG29/BF29) -> 0 | BJ29: 6000000 | BK29: =SUMIFS(TablaEgresos[Valor],TablaEgresos[Categoría],$A29,TablaEgresos[Mes],BJ$4) -> 0 | BL29: =IF(BJ29="","",BJ29-BK29) -> 6000000 | BM29: =IF(OR(BJ29="",BJ29=0),"",BK29/BJ29) -> 0 | BN29: 6000000 | BO29: =SUMIFS(TablaEgresos[Valor],TablaEgresos[Categoría],$A29,TablaEgresos[Mes],BN$4) -> 0 | BP29: =IF(BN29="","",BN29-BO29) -> 6000000 | BQ29: =IF(OR(BN29="",BN29=0),"",BO29/BN29) -> 0 | BR29: 6000000 | BS29: =SUMIFS(TablaEgresos[Valor],TablaEgresos[Categoría],$A29,TablaEgresos[Mes],BR$4) -> 0 | BT29: =IF(BR29="","",BR29-BS29) -> 6000000 | BU29: =IF(OR(BR29="",BR29=0),"",BS29/BR29) -> 0 | BV29: 6000000 | BW29: =SUMIFS(TablaEgresos[Valor],TablaEgresos[Categoría],$A29,TablaEgresos[Mes],BV$4) -> 0 | BX29: =IF(BV29="","",BV29-BW29) -> 6000000 | BY29: =IF(OR(BV29="",BV29=0),"",BW29/BV29) -> 0 | BZ29: 6000000 | CA29: =SUMIFS(TablaEgresos[Valor],TablaEgresos[Categoría],$A29,TablaEgresos[Mes],BZ$4) -> 0 | CB29: =IF(BZ29="","",BZ29-CA29) -> 6000000 | CC29: =IF(OR(BZ29="",BZ29=0),"",CA29/BZ29) -> 0 | CD29: 6000000 | CE29: =SUMIFS(TablaEgresos[Valor],TablaEgresos[Categoría],$A29,TablaEgresos[Mes],CD$4) -> 0 | CF29: =IF(CD29="","",CD29-CE29) -> 6000000 | CG29: =IF(OR(CD29="",CD29=0),"",CE29/CD29) -> 0 | CH29: 6000000 | CI29: =SUMIFS(TablaEgresos[Valor],TablaEgresos[Categoría],$A29,TablaEgresos[Mes],CH$4) -> 0 | CJ29: =IF(CH29="","",CH29-CI29) -> 6000000 | CK29: =IF(OR(CH29="",CH29=0),"",CI29/CH29) -> 0 | CL29: 6000000 | CM29: =SUMIFS(TablaEgresos[Valor],TablaEgresos[Categoría],$A29,TablaEgresos[Mes],CL$4) -> 0 | CN29: =IF(CL29="","",CL29-CM29) -> 6000000 | CO29: =IF(OR(CL29="",CL29=0),"",CM29/CL29) -> 0
A30: Planillas anteriores | B30: =IFERROR(AVERAGE(INDEX($B74:$W74,MATCH($B$3,$B$51:$W$51,0)-2):INDEX($B74:$W74,MATCH($B$3,$B$51:$W$51,0))),0) -> 0 | C30: =IFERROR(SLOPE(INDEX($B74:$W74,1):INDEX($B74:$W74,MATCH($B$3,$B$51:$W$51,0)),INDEX($B$50:$W$50,1):INDEX($B$50:$W$50,MATCH($B$3,$B$51:$W$51,0))),0) -> 0 | D30: =IF($B30=0,"",$C30/$B30) | E30: =MAX(0,ROUND($B30+$C30*3,-3)) -> 0 | G30: =SUMIFS(TablaEgresos[Valor],TablaEgresos[Categoría],$A30,TablaEgresos[Mes],F$4) -> 0 | H30: =IF(F30="","",F30-G30) | I30: =IF(OR(F30="",F30=0),"",G30/F30) | K30: =SUMIFS(TablaEgresos[Valor],TablaEgresos[Categoría],$A30,TablaEgresos[Mes],J$4) -> 0 | L30: =IF(J30="","",J30-K30) | M30: =IF(OR(J30="",J30=0),"",K30/J30) | O30: =SUMIFS(TablaEgresos[Valor],TablaEgresos[Categoría],$A30,TablaEgresos[Mes],N$4) -> 0 | P30: =IF(N30="","",N30-O30) | Q30: =IF(OR(N30="",N30=0),"",O30/N30) | S30: =SUMIFS(TablaEgresos[Valor],TablaEgresos[Categoría],$A30,TablaEgresos[Mes],R$4) -> 0 | T30: =IF(R30="","",R30-S30) | U30: =IF(OR(R30="",R30=0),"",S30/R30) | V30: 38979200 | W30: =SUMIFS(TablaEgresos[Valor],TablaEgresos[Categoría],$A30,TablaEgresos[Mes],V$4) -> 38979200 | X30: =IF(V30="","",V30-W30) -> 0 | Y30: =IF(OR(V30="",V30=0),"",W30/V30) -> 1 | Z30: 0 | AA30: =SUMIFS(TablaEgresos[Valor],TablaEgresos[Categoría],$A30,TablaEgresos[Mes],Z$4) -> 0 | AB30: =IF(Z30="","",Z30-AA30) -> 0 | AC30: =IF(OR(Z30="",Z30=0),"",AA30/Z30) | AD30: 0 | AE30: =SUMIFS(TablaEgresos[Valor],TablaEgresos[Categoría],$A30,TablaEgresos[Mes],AD$4) -> 0 | AF30: =IF(AD30="","",AD30-AE30) -> 0 | AG30: =IF(OR(AD30="",AD30=0),"",AE30/AD30) | AH30: 0 | AI30: =SUMIFS(TablaEgresos[Valor],TablaEgresos[Categoría],$A30,TablaEgresos[Mes],AH$4) -> 0 | AJ30: =IF(AH30="","",AH30-AI30) -> 0 | AK30: =IF(OR(AH30="",AH30=0),"",AI30/AH30) | AL30: 0 | AM30: =SUMIFS(TablaEgresos[Valor],TablaEgresos[Categoría],$A30,TablaEgresos[Mes],AL$4) -> 0 | AN30: =IF(AL30="","",AL30-AM30) -> 0 | AO30: =IF(OR(AL30="",AL30=0),"",AM30/AL30) | AP30: 0 | AQ30: =SUMIFS(TablaEgresos[Valor],TablaEgresos[Categoría],$A30,TablaEgresos[Mes],AP$4) -> 0 | AR30: =IF(AP30="","",AP30-AQ30) -> 0 | AS30: =IF(OR(AP30="",AP30=0),"",AQ30/AP30) | AT30: 0 | AU30: =SUMIFS(TablaEgresos[Valor],TablaEgresos[Categoría],$A30,TablaEgresos[Mes],AT$4) -> 0 | AV30: =IF(AT30="","",AT30-AU30) -> 0 | AW30: =IF(OR(AT30="",AT30=0),"",AU30/AT30) | AX30: 0 | AY30: =SUMIFS(TablaEgresos[Valor],TablaEgresos[Categoría],$A30,TablaEgresos[Mes],AX$4) -> 0 | AZ30: =IF(AX30="","",AX30-AY30) -> 0 | BA30: =IF(OR(AX30="",AX30=0),"",AY30/AX30) | BB30: 0 | BC30: =SUMIFS(TablaEgresos[Valor],TablaEgresos[Categoría],$A30,TablaEgresos[Mes],BB$4) -> 0 | BD30: =IF(BB30="","",BB30-BC30) -> 0 | BE30: =IF(OR(BB30="",BB30=0),"",BC30/BB30) | BF30: 0 | BG30: =SUMIFS(TablaEgresos[Valor],TablaEgresos[Categoría],$A30,TablaEgresos[Mes],BF$4) -> 0 | BH30: =IF(BF30="","",BF30-BG30) -> 0 | BI30: =IF(OR(BF30="",BF30=0),"",BG30/BF30) | BJ30: 0 | BK30: =SUMIFS(TablaEgresos[Valor],TablaEgresos[Categoría],$A30,TablaEgresos[Mes],BJ$4) -> 0 | BL30: =IF(BJ30="","",BJ30-BK30) -> 0 | BM30: =IF(OR(BJ30="",BJ30=0),"",BK30/BJ30) | BN30: 0 | BO30: =SUMIFS(TablaEgresos[Valor],TablaEgresos[Categoría],$A30,TablaEgresos[Mes],BN$4) -> 0 | BP30: =IF(BN30="","",BN30-BO30) -> 0 | BQ30: =IF(OR(BN30="",BN30=0),"",BO30/BN30) | BR30: 0 | BS30: =SUMIFS(TablaEgresos[Valor],TablaEgresos[Categoría],$A30,TablaEgresos[Mes],BR$4) -> 0 | BT30: =IF(BR30="","",BR30-BS30) -> 0 | BU30: =IF(OR(BR30="",BR30=0),"",BS30/BR30) | BV30: 0 | BW30: =SUMIFS(TablaEgresos[Valor],TablaEgresos[Categoría],$A30,TablaEgresos[Mes],BV$4) -> 0 | BX30: =IF(BV30="","",BV30-BW30) -> 0 | BY30: =IF(OR(BV30="",BV30=0),"",BW30/BV30) | BZ30: 0 | CA30: =SUMIFS(TablaEgresos[Valor],TablaEgresos[Categoría],$A30,TablaEgresos[Mes],BZ$4) -> 0 | CB30: =IF(BZ30="","",BZ30-CA30) -> 0 | CC30: =IF(OR(BZ30="",BZ30=0),"",CA30/BZ30) | CD30: 0 | CE30: =SUMIFS(TablaEgresos[Valor],TablaEgresos[Categoría],$A30,TablaEgresos[Mes],CD$4) -> 0 | CF30: =IF(CD30="","",CD30-CE30) -> 0 | CG30: =IF(OR(CD30="",CD30=0),"",CE30/CD30) | CH30: 0 | CI30: =SUMIFS(TablaEgresos[Valor],TablaEgresos[Categoría],$A30,TablaEgresos[Mes],CH$4) -> 0 | CJ30: =IF(CH30="","",CH30-CI30) -> 0 | CK30: =IF(OR(CH30="",CH30=0),"",CI30/CH30) | CL30: 0 | CM30: =SUMIFS(TablaEgresos[Valor],TablaEgresos[Categoría],$A30,TablaEgresos[Mes],CL$4) -> 0 | CN30: =IF(CL30="","",CL30-CM30) -> 0 | CO30: =IF(OR(CL30="",CL30=0),"",CM30/CL30)
A31: Subtotal Nómina | B31: =SUM(B25:B30) -> 8832064.4 | C31: =SUM(C25:C30) -> 3952142.8 | D31: =IF(B31=0,"",C31/B31) -> 0.44747668 | E31: =SUM(E25:E30) -> 20689000 | F31: =SUM(F25:F30) -> 0 | G31: =SUM(G25:G30) -> 0 | H31: =SUM(H25:H30) -> 0 | I31: =IF(F31=0,"",G31/F31) | J31: =SUM(J25:J30) -> 0 | K31: =SUM(K25:K30) -> 6111308.4 | L31: =SUM(L25:L30) -> 0 | M31: =IF(J31=0,"",K31/J31) | N31: =SUM(N25:N30) -> 0 | O31: =SUM(O25:O30) -> 7760958.8 | P31: =SUM(P25:P30) -> 0 | Q31: =IF(N31=0,"",O31/N31) | R31: =SUM(R25:R30) -> 0 | S31: =SUM(S25:S30) -> 12623926 | T31: =SUM(T25:T30) -> 0 | U31: =IF(R31=0,"",S31/R31) | V31: =SUM(V25:V30) -> 1.6777115e+08 | W31: =SUM(W25:W30) -> 1.4924143e+08 | X31: =SUM(X25:X30) -> 18529723 | Y31: =IF(V31=0,"",W31/V31) -> 0.88955358 | Z31: =SUM(Z25:Z30) -> 49073000 | AA31: =SUM(AA25:AA30) -> 0 | AB31: =SUM(AB25:AB30) -> 49073000 | AC31: =IF(Z31=0,"",AA31/Z31) -> 0 | AD31: =SUM(AD25:AD30) -> 49073000 | AE31: =SUM(AE25:AE30) -> 0 | AF31: =SUM(AF25:AF30) -> 49073000 | AG31: =IF(AD31=0,"",AE31/AD31) -> 0 | AH31: =SUM(AH25:AH30) -> 49073000 | AI31: =SUM(AI25:AI30) -> 0 | AJ31: =SUM(AJ25:AJ30) -> 49073000 | AK31: =IF(AH31=0,"",AI31/AH31) -> 0 | AL31: =SUM(AL25:AL30) -> 49073000 | AM31: =SUM(AM25:AM30) -> 0 | AN31: =SUM(AN25:AN30) -> 49073000 | AO31: =IF(AL31=0,"",AM31/AL31) -> 0 | AP31: =SUM(AP25:AP30) -> 49073000 | AQ31: =SUM(AQ25:AQ30) -> 0 | AR31: =SUM(AR25:AR30) -> 49073000 | AS31: =IF(AP31=0,"",AQ31/AP31) -> 0 | AT31: =SUM(AT25:AT30) -> 49073000 | AU31: =SUM(AU25:AU30) -> 0 | AV31: =SUM(AV25:AV30) -> 49073000 | AW31: =IF(AT31=0,"",AU31/AT31) -> 0 | AX31: =SUM(AX25:AX30) -> 49073000 | AY31: =SUM(AY25:AY30) -> 0 | AZ31: =SUM(AZ25:AZ30) -> 49073000 | BA31: =IF(AX31=0,"",AY31/AX31) -> 0 | BB31: =SUM(BB25:BB30) -> 49073000 | BC31: =SUM(BC25:BC30) -> 0 | BD31: =SUM(BD25:BD30) -> 49073000 | BE31: =IF(BB31=0,"",BC31/BB31) -> 0 | BF31: =SUM(BF25:BF30) -> 49073000 | BG31: =SUM(BG25:BG30) -> 0 | BH31: =SUM(BH25:BH30) -> 49073000 | BI31: =IF(BF31=0,"",BG31/BF31) -> 0 | BJ31: =SUM(BJ25:BJ30) -> 49073000 | BK31: =SUM(BK25:BK30) -> 0 | BL31: =SUM(BL25:BL30) -> 49073000 | BM31: =IF(BJ31=0,"",BK31/BJ31) -> 0 | BN31: =SUM(BN25:BN30) -> 49073000 | BO31: =SUM(BO25:BO30) -> 0 | BP31: =SUM(BP25:BP30) -> 49073000 | BQ31: =IF(BN31=0,"",BO31/BN31) -> 0 | BR31: =SUM(BR25:BR30) -> 49073000 | BS31: =SUM(BS25:BS30) -> 0 | BT31: =SUM(BT25:BT30) -> 49073000 | BU31: =IF(BR31=0,"",BS31/BR31) -> 0 | BV31: =SUM(BV25:BV30) -> 49073000 | BW31: =SUM(BW25:BW30) -> 0 | BX31: =SUM(BX25:BX30) -> 49073000 | BY31: =IF(BV31=0,"",BW31/BV31) -> 0 | BZ31: =SUM(BZ25:BZ30) -> 49073000 | CA31: =SUM(CA25:CA30) -> 0 | CB31: =SUM(CB25:CB30) -> 49073000 | CC31: =IF(BZ31=0,"",CA31/BZ31) -> 0 | CD31: =SUM(CD25:CD30) -> 49073000 | CE31: =SUM(CE25:CE30) -> 0 | CF31: =SUM(CF25:CF30) -> 49073000 | CG31: =IF(CD31=0,"",CE31/CD31) -> 0 | CH31: =SUM(CH25:CH30) -> 49073000 | CI31: =SUM(CI25:CI30) -> 0 | CJ31: =SUM(CJ25:CJ30) -> 49073000 | CK31: =IF(CH31=0,"",CI31/CH31) -> 0 | CL31: =SUM(CL25:CL30) -> 49073000 | CM31: =SUM(CM25:CM30) -> 0 | CN31: =SUM(CN25:CN30) -> 49073000 | CO31: =IF(CL31=0,"",CM31/CL31) -> 0
A32: DEUDAS Y OBLIGACIONES
A33: Préstamos | B33: =IFERROR(AVERAGE(INDEX($B77:$W77,MATCH($B$3,$B$51:$W$51,0)-2):INDEX($B77:$W77,MATCH($B$3,$B$51:$W$51,0))),0) -> 8152503.5 | C33: =IFERROR(SLOPE(INDEX($B77:$W77,1):INDEX($B77:$W77,MATCH($B$3,$B$51:$W$51,0)),INDEX($B$50:$W$50,1):INDEX($B$50:$W$50,MATCH($B$3,$B$51:$W$51,0))),0) -> -4894011.2 | D33: =IF($B33=0,"",$C33/$B33) -> -0.60030777 | E33: =MAX(0,ROUND($B33+$C33*3,-3)) -> 0 | G33: =SUMIFS(TablaEgresos[Valor],TablaEgresos[Categoría],$A33,TablaEgresos[Mes],F$4) -> 12734889 | H33: =IF(F33="","",F33-G33) | I33: =IF(OR(F33="",F33=0),"",G33/F33) | K33: =SUMIFS(TablaEgresos[Valor],TablaEgresos[Categoría],$A33,TablaEgresos[Mes],J$4) -> 17596478 | L33: =IF(J33="","",J33-K33) | M33: =IF(OR(J33="",J33=0),"",K33/J33) | O33: =SUMIFS(TablaEgresos[Valor],TablaEgresos[Categoría],$A33,TablaEgresos[Mes],N$4) -> 6861032 | P33: =IF(N33="","",N33-O33) | Q33: =IF(OR(N33="",N33=0),"",O33/N33) | S33: =SUMIFS(TablaEgresos[Valor],TablaEgresos[Categoría],$A33,TablaEgresos[Mes],R$4) -> 0 | T33: =IF(R33="","",R33-S33) | U33: =IF(OR(R33="",R33=0),"",S33/R33) | V33: 21000000 | W33: =SUMIFS(TablaEgresos[Valor],TablaEgresos[Categoría],$A33,TablaEgresos[Mes],V$4) -> 17653261 | X33: =IF(V33="","",V33-W33) -> 3346739 | Y33: =IF(OR(V33="",V33=0),"",W33/V33) -> 0.84063147 | Z33: 21000000 | AA33: =SUMIFS(TablaEgresos[Valor],TablaEgresos[Categoría],$A33,TablaEgresos[Mes],Z$4) -> 0 | AB33: =IF(Z33="","",Z33-AA33) -> 21000000 | AC33: =IF(OR(Z33="",Z33=0),"",AA33/Z33) -> 0 | AD33: 21000000 | AE33: =SUMIFS(TablaEgresos[Valor],TablaEgresos[Categoría],$A33,TablaEgresos[Mes],AD$4) -> 0 | AF33: =IF(AD33="","",AD33-AE33) -> 21000000 | AG33: =IF(OR(AD33="",AD33=0),"",AE33/AD33) -> 0 | AH33: 21000000 | AI33: =SUMIFS(TablaEgresos[Valor],TablaEgresos[Categoría],$A33,TablaEgresos[Mes],AH$4) -> 0 | AJ33: =IF(AH33="","",AH33-AI33) -> 21000000 | AK33: =IF(OR(AH33="",AH33=0),"",AI33/AH33) -> 0 | AL33: 21000000 | AM33: =SUMIFS(TablaEgresos[Valor],TablaEgresos[Categoría],$A33,TablaEgresos[Mes],AL$4) -> 0 | AN33: =IF(AL33="","",AL33-AM33) -> 21000000 | AO33: =IF(OR(AL33="",AL33=0),"",AM33/AL33) -> 0 | AP33: 21000000 | AQ33: =SUMIFS(TablaEgresos[Valor],TablaEgresos[Categoría],$A33,TablaEgresos[Mes],AP$4) -> 0 | AR33: =IF(AP33="","",AP33-AQ33) -> 21000000 | AS33: =IF(OR(AP33="",AP33=0),"",AQ33/AP33) -> 0 | AT33: 21000000 | AU33: =SUMIFS(TablaEgresos[Valor],TablaEgresos[Categoría],$A33,TablaEgresos[Mes],AT$4) -> 0 | AV33: =IF(AT33="","",AT33-AU33) -> 21000000 | AW33: =IF(OR(AT33="",AT33=0),"",AU33/AT33) -> 0 | AX33: 21000000 | AY33: =SUMIFS(TablaEgresos[Valor],TablaEgresos[Categoría],$A33,TablaEgresos[Mes],AX$4) -> 0 | AZ33: =IF(AX33="","",AX33-AY33) -> 21000000 | BA33: =IF(OR(AX33="",AX33=0),"",AY33/AX33) -> 0 | BB33: 21000000 | BC33: =SUMIFS(TablaEgresos[Valor],TablaEgresos[Categoría],$A33,TablaEgresos[Mes],BB$4) -> 0 | BD33: =IF(BB33="","",BB33-BC33) -> 21000000 | BE33: =IF(OR(BB33="",BB33=0),"",BC33/BB33) -> 0 | BF33: 21000000 | BG33: =SUMIFS(TablaEgresos[Valor],TablaEgresos[Categoría],$A33,TablaEgresos[Mes],BF$4) -> 0 | BH33: =IF(BF33="","",BF33-BG33) -> 21000000 | BI33: =IF(OR(BF33="",BF33=0),"",BG33/BF33) -> 0 | BJ33: 21000000 | BK33: =SUMIFS(TablaEgresos[Valor],TablaEgresos[Categoría],$A33,TablaEgresos[Mes],BJ$4) -> 0 | BL33: =IF(BJ33="","",BJ33-BK33) -> 21000000 | BM33: =IF(OR(BJ33="",BJ33=0),"",BK33/BJ33) -> 0 | BN33: 21000000 | BO33: =SUMIFS(TablaEgresos[Valor],TablaEgresos[Categoría],$A33,TablaEgresos[Mes],BN$4) -> 0 | BP33: =IF(BN33="","",BN33-BO33) -> 21000000 | BQ33: =IF(OR(BN33="",BN33=0),"",BO33/BN33) -> 0 | BR33: 21000000 | BS33: =SUMIFS(TablaEgresos[Valor],TablaEgresos[Categoría],$A33,TablaEgresos[Mes],BR$4) -> 0 | BT33: =IF(BR33="","",BR33-BS33) -> 21000000 | BU33: =IF(OR(BR33="",BR33=0),"",BS33/BR33) -> 0 | BV33: 21000000 | BW33: =SUMIFS(TablaEgresos[Valor],TablaEgresos[Categoría],$A33,TablaEgresos[Mes],BV$4) -> 0 | BX33: =IF(BV33="","",BV33-BW33) -> 21000000 | BY33: =IF(OR(BV33="",BV33=0),"",BW33/BV33) -> 0 | BZ33: 21000000 | CA33: =SUMIFS(TablaEgresos[Valor],TablaEgresos[Categoría],$A33,TablaEgresos[Mes],BZ$4) -> 0 | CB33: =IF(BZ33="","",BZ33-CA33) -> 21000000 | CC33: =IF(OR(BZ33="",BZ33=0),"",CA33/BZ33) -> 0 | CD33: 21000000 | CE33: =SUMIFS(TablaEgresos[Valor],TablaEgresos[Categoría],$A33,TablaEgresos[Mes],CD$4) -> 0 | CF33: =IF(CD33="","",CD33-CE33) -> 21000000 | CG33: =IF(OR(CD33="",CD33=0),"",CE33/CD33) -> 0 | CH33: 21000000 | CI33: =SUMIFS(TablaEgresos[Valor],TablaEgresos[Categoría],$A33,TablaEgresos[Mes],CH$4) -> 0 | CJ33: =IF(CH33="","",CH33-CI33) -> 21000000 | CK33: =IF(OR(CH33="",CH33=0),"",CI33/CH33) -> 0 | CL33: 21000000 | CM33: =SUMIFS(TablaEgresos[Valor],TablaEgresos[Categoría],$A33,TablaEgresos[Mes],CL$4) -> 0 | CN33: =IF(CL33="","",CL33-CM33) -> 21000000 | CO33: =IF(OR(CL33="",CL33=0),"",CM33/CL33) -> 0
A34: Deudas tarjetas de crédito | B34: =IFERROR(AVERAGE(INDEX($B78:$W78,MATCH($B$3,$B$51:$W$51,0)-2):INDEX($B78:$W78,MATCH($B$3,$B$51:$W$51,0))),0) -> 0 | C34: =IFERROR(SLOPE(INDEX($B78:$W78,1):INDEX($B78:$W78,MATCH($B$3,$B$51:$W$51,0)),INDEX($B$50:$W$50,1):INDEX($B$50:$W$50,MATCH($B$3,$B$51:$W$51,0))),0) -> 0 | D34: =IF($B34=0,"",$C34/$B34) | E34: =MAX(0,ROUND($B34+$C34*3,-3)) -> 0 | G34: =SUMIFS(TablaEgresos[Valor],TablaEgresos[Categoría],$A34,TablaEgresos[Mes],F$4) -> 0 | H34: =IF(F34="","",F34-G34) | I34: =IF(OR(F34="",F34=0),"",G34/F34) | K34: =SUMIFS(TablaEgresos[Valor],TablaEgresos[Categoría],$A34,TablaEgresos[Mes],J$4) -> 0 | L34: =IF(J34="","",J34-K34) | M34: =IF(OR(J34="",J34=0),"",K34/J34) | O34: =SUMIFS(TablaEgresos[Valor],TablaEgresos[Categoría],$A34,TablaEgresos[Mes],N$4) -> 0 | P34: =IF(N34="","",N34-O34) | Q34: =IF(OR(N34="",N34=0),"",O34/N34) | S34: =SUMIFS(TablaEgresos[Valor],TablaEgresos[Categoría],$A34,TablaEgresos[Mes],R$4) -> 0 | T34: =IF(R34="","",R34-S34) | U34: =IF(OR(R34="",R34=0),"",S34/R34) | V34: 9200000 | W34: =SUMIFS(TablaEgresos[Valor],TablaEgresos[Categoría],$A34,TablaEgresos[Mes],V$4) -> 9200000 | X34: =IF(V34="","",V34-W34) -> 0 | Y34: =IF(OR(V34="",V34=0),"",W34/V34) -> 1 | Z34: 0 | AA34: =SUMIFS(TablaEgresos[Valor],TablaEgresos[Categoría],$A34,TablaEgresos[Mes],Z$4) -> 0 | AB34: =IF(Z34="","",Z34-AA34) -> 0 | AC34: =IF(OR(Z34="",Z34=0),"",AA34/Z34) | AD34: 0 | AE34: =SUMIFS(TablaEgresos[Valor],TablaEgresos[Categoría],$A34,TablaEgresos[Mes],AD$4) -> 0 | AF34: =IF(AD34="","",AD34-AE34) -> 0 | AG34: =IF(OR(AD34="",AD34=0),"",AE34/AD34) | AH34: 0 | AI34: =SUMIFS(TablaEgresos[Valor],TablaEgresos[Categoría],$A34,TablaEgresos[Mes],AH$4) -> 0 | AJ34: =IF(AH34="","",AH34-AI34) -> 0 | AK34: =IF(OR(AH34="",AH34=0),"",AI34/AH34) | AL34: 0 | AM34: =SUMIFS(TablaEgresos[Valor],TablaEgresos[Categoría],$A34,TablaEgresos[Mes],AL$4) -> 0 | AN34: =IF(AL34="","",AL34-AM34) -> 0 | AO34: =IF(OR(AL34="",AL34=0),"",AM34/AL34) | AP34: 0 | AQ34: =SUMIFS(TablaEgresos[Valor],TablaEgresos[Categoría],$A34,TablaEgresos[Mes],AP$4) -> 0 | AR34: =IF(AP34="","",AP34-AQ34) -> 0 | AS34: =IF(OR(AP34="",AP34=0),"",AQ34/AP34) | AT34: 0 | AU34: =SUMIFS(TablaEgresos[Valor],TablaEgresos[Categoría],$A34,TablaEgresos[Mes],AT$4) -> 0 | AV34: =IF(AT34="","",AT34-AU34) -> 0 | AW34: =IF(OR(AT34="",AT34=0),"",AU34/AT34) | AX34: 0 | AY34: =SUMIFS(TablaEgresos[Valor],TablaEgresos[Categoría],$A34,TablaEgresos[Mes],AX$4) -> 0 | AZ34: =IF(AX34="","",AX34-AY34) -> 0 | BA34: =IF(OR(AX34="",AX34=0),"",AY34/AX34) | BB34: 0 | BC34: =SUMIFS(TablaEgresos[Valor],TablaEgresos[Categoría],$A34,TablaEgresos[Mes],BB$4) -> 0 | BD34: =IF(BB34="","",BB34-BC34) -> 0 | BE34: =IF(OR(BB34="",BB34=0),"",BC34/BB34) | BF34: 0 | BG34: =SUMIFS(TablaEgresos[Valor],TablaEgresos[Categoría],$A34,TablaEgresos[Mes],BF$4) -> 0 | BH34: =IF(BF34="","",BF34-BG34) -> 0 | BI34: =IF(OR(BF34="",BF34=0),"",BG34/BF34) | BJ34: 0 | BK34: =SUMIFS(TablaEgresos[Valor],TablaEgresos[Categoría],$A34,TablaEgresos[Mes],BJ$4) -> 0 | BL34: =IF(BJ34="","",BJ34-BK34) -> 0 | BM34: =IF(OR(BJ34="",BJ34=0),"",BK34/BJ34) | BN34: 0 | BO34: =SUMIFS(TablaEgresos[Valor],TablaEgresos[Categoría],$A34,TablaEgresos[Mes],BN$4) -> 0 | BP34: =IF(BN34="","",BN34-BO34) -> 0 | BQ34: =IF(OR(BN34="",BN34=0),"",BO34/BN34) | BR34: 0 | BS34: =SUMIFS(TablaEgresos[Valor],TablaEgresos[Categoría],$A34,TablaEgresos[Mes],BR$4) -> 0 | BT34: =IF(BR34="","",BR34-BS34) -> 0 | BU34: =IF(OR(BR34="",BR34=0),"",BS34/BR34) | BV34: 0 | BW34: =SUMIFS(TablaEgresos[Valor],TablaEgresos[Categoría],$A34,TablaEgresos[Mes],BV$4) -> 0 | BX34: =IF(BV34="","",BV34-BW34) -> 0 | BY34: =IF(OR(BV34="",BV34=0),"",BW34/BV34) | BZ34: 0 | CA34: =SUMIFS(TablaEgresos[Valor],TablaEgresos[Categoría],$A34,TablaEgresos[Mes],BZ$4) -> 0 | CB34: =IF(BZ34="","",BZ34-CA34) -> 0 | CC34: =IF(OR(BZ34="",BZ34=0),"",CA34/BZ34) | CD34: 0 | CE34: =SUMIFS(TablaEgresos[Valor],TablaEgresos[Categoría],$A34,TablaEgresos[Mes],CD$4) -> 0 | CF34: =IF(CD34="","",CD34-CE34) -> 0 | CG34: =IF(OR(CD34="",CD34=0),"",CE34/CD34) | CH34: 0 | CI34: =SUMIFS(TablaEgresos[Valor],TablaEgresos[Categoría],$A34,TablaEgresos[Mes],CH$4) -> 0 | CJ34: =IF(CH34="","",CH34-CI34) -> 0 | CK34: =IF(OR(CH34="",CH34=0),"",CI34/CH34) | CL34: 0 | CM34: =SUMIFS(TablaEgresos[Valor],TablaEgresos[Categoría],$A34,TablaEgresos[Mes],CL$4) -> 0 | CN34: =IF(CL34="","",CL34-CM34) -> 0 | CO34: =IF(OR(CL34="",CL34=0),"",CM34/CL34)
A35: Garantía cupo | B35: =IFERROR(AVERAGE(INDEX($B79:$W79,MATCH($B$3,$B$51:$W$51,0)-2):INDEX($B79:$W79,MATCH($B$3,$B$51:$W$51,0))),0) -> 0 | C35: =IFERROR(SLOPE(INDEX($B79:$W79,1):INDEX($B79:$W79,MATCH($B$3,$B$51:$W$51,0)),INDEX($B$50:$W$50,1):INDEX($B$50:$W$50,MATCH($B$3,$B$51:$W$51,0))),0) -> 0 | D35: =IF($B35=0,"",$C35/$B35) | E35: =MAX(0,ROUND($B35+$C35*3,-3)) -> 0 | G35: =SUMIFS(TablaEgresos[Valor],TablaEgresos[Categoría],$A35,TablaEgresos[Mes],F$4) -> 0 | H35: =IF(F35="","",F35-G35) | I35: =IF(OR(F35="",F35=0),"",G35/F35) | K35: =SUMIFS(TablaEgresos[Valor],TablaEgresos[Categoría],$A35,TablaEgresos[Mes],J$4) -> 0 | L35: =IF(J35="","",J35-K35) | M35: =IF(OR(J35="",J35=0),"",K35/J35) | O35: =SUMIFS(TablaEgresos[Valor],TablaEgresos[Categoría],$A35,TablaEgresos[Mes],N$4) -> 0 | P35: =IF(N35="","",N35-O35) | Q35: =IF(OR(N35="",N35=0),"",O35/N35) | S35: =SUMIFS(TablaEgresos[Valor],TablaEgresos[Categoría],$A35,TablaEgresos[Mes],R$4) -> 0 | T35: =IF(R35="","",R35-S35) | U35: =IF(OR(R35="",R35=0),"",S35/R35) | V35: 14000000 | W35: =SUMIFS(TablaEgresos[Valor],TablaEgresos[Categoría],$A35,TablaEgresos[Mes],V$4) -> 0 | X35: =IF(V35="","",V35-W35) -> 14000000 | Y35: =IF(OR(V35="",V35=0),"",W35/V35) -> 0 | Z35: 14000000 | AA35: =SUMIFS(TablaEgresos[Valor],TablaEgresos[Categoría],$A35,TablaEgresos[Mes],Z$4) -> 0 | AB35: =IF(Z35="","",Z35-AA35) -> 14000000 | AC35: =IF(OR(Z35="",Z35=0),"",AA35/Z35) -> 0 | AD35: 14000000 | AE35: =SUMIFS(TablaEgresos[Valor],TablaEgresos[Categoría],$A35,TablaEgresos[Mes],AD$4) -> 0 | AF35: =IF(AD35="","",AD35-AE35) -> 14000000 | AG35: =IF(OR(AD35="",AD35=0),"",AE35/AD35) -> 0 | AH35: 14000000 | AI35: =SUMIFS(TablaEgresos[Valor],TablaEgresos[Categoría],$A35,TablaEgresos[Mes],AH$4) -> 0 | AJ35: =IF(AH35="","",AH35-AI35) -> 14000000 | AK35: =IF(OR(AH35="",AH35=0),"",AI35/AH35) -> 0 | AL35: 14000000 | AM35: =SUMIFS(TablaEgresos[Valor],TablaEgresos[Categoría],$A35,TablaEgresos[Mes],AL$4) -> 0 | AN35: =IF(AL35="","",AL35-AM35) -> 14000000 | AO35: =IF(OR(AL35="",AL35=0),"",AM35/AL35) -> 0 | AP35: 14000000 | AQ35: =SUMIFS(TablaEgresos[Valor],TablaEgresos[Categoría],$A35,TablaEgresos[Mes],AP$4) -> 0 | AR35: =IF(AP35="","",AP35-AQ35) -> 14000000 | AS35: =IF(OR(AP35="",AP35=0),"",AQ35/AP35) -> 0 | AT35: 14000000 | AU35: =SUMIFS(TablaEgresos[Valor],TablaEgresos[Categoría],$A35,TablaEgresos[Mes],AT$4) -> 0 | AV35: =IF(AT35="","",AT35-AU35) -> 14000000 | AW35: =IF(OR(AT35="",AT35=0),"",AU35/AT35) -> 0 | AX35: 14000000 | AY35: =SUMIFS(TablaEgresos[Valor],TablaEgresos[Categoría],$A35,TablaEgresos[Mes],AX$4) -> 0 | AZ35: =IF(AX35="","",AX35-AY35) -> 14000000 | BA35: =IF(OR(AX35="",AX35=0),"",AY35/AX35) -> 0 | BB35: 14000000 | BC35: =SUMIFS(TablaEgresos[Valor],TablaEgresos[Categoría],$A35,TablaEgresos[Mes],BB$4) -> 0 | BD35: =IF(BB35="","",BB35-BC35) -> 14000000 | BE35: =IF(OR(BB35="",BB35=0),"",BC35/BB35) -> 0 | BF35: 14000000 | BG35: =SUMIFS(TablaEgresos[Valor],TablaEgresos[Categoría],$A35,TablaEgresos[Mes],BF$4) -> 0 | BH35: =IF(BF35="","",BF35-BG35) -> 14000000 | BI35: =IF(OR(BF35="",BF35=0),"",BG35/BF35) -> 0 | BJ35: 14000000 | BK35: =SUMIFS(TablaEgresos[Valor],TablaEgresos[Categoría],$A35,TablaEgresos[Mes],BJ$4) -> 0 | BL35: =IF(BJ35="","",BJ35-BK35) -> 14000000 | BM35: =IF(OR(BJ35="",BJ35=0),"",BK35/BJ35) -> 0 | BN35: 14000000 | BO35: =SUMIFS(TablaEgresos[Valor],TablaEgresos[Categoría],$A35,TablaEgresos[Mes],BN$4) -> 0 | BP35: =IF(BN35="","",BN35-BO35) -> 14000000 | BQ35: =IF(OR(BN35="",BN35=0),"",BO35/BN35) -> 0 | BR35: 14000000 | BS35: =SUMIFS(TablaEgresos[Valor],TablaEgresos[Categoría],$A35,TablaEgresos[Mes],BR$4) -> 0 | BT35: =IF(BR35="","",BR35-BS35) -> 14000000 | BU35: =IF(OR(BR35="",BR35=0),"",BS35/BR35) -> 0 | BV35: 14000000 | BW35: =SUMIFS(TablaEgresos[Valor],TablaEgresos[Categoría],$A35,TablaEgresos[Mes],BV$4) -> 0 | BX35: =IF(BV35="","",BV35-BW35) -> 14000000 | BY35: =IF(OR(BV35="",BV35=0),"",BW35/BV35) -> 0 | BZ35: 14000000 | CA35: =SUMIFS(TablaEgresos[Valor],TablaEgresos[Categoría],$A35,TablaEgresos[Mes],BZ$4) -> 0 | CB35: =IF(BZ35="","",BZ35-CA35) -> 14000000 | CC35: =IF(OR(BZ35="",BZ35=0),"",CA35/BZ35) -> 0 | CD35: 14000000 | CE35: =SUMIFS(TablaEgresos[Valor],TablaEgresos[Categoría],$A35,TablaEgresos[Mes],CD$4) -> 0 | CF35: =IF(CD35="","",CD35-CE35) -> 14000000 | CG35: =IF(OR(CD35="",CD35=0),"",CE35/CD35) -> 0 | CH35: 14000000 | CI35: =SUMIFS(TablaEgresos[Valor],TablaEgresos[Categoría],$A35,TablaEgresos[Mes],CH$4) -> 0 | CJ35: =IF(CH35="","",CH35-CI35) -> 14000000 | CK35: =IF(OR(CH35="",CH35=0),"",CI35/CH35) -> 0 | CL35: 14000000 | CM35: =SUMIFS(TablaEgresos[Valor],TablaEgresos[Categoría],$A35,TablaEgresos[Mes],CL$4) -> 0 | CN35: =IF(CL35="","",CL35-CM35) -> 14000000 | CO35: =IF(OR(CL35="",CL35=0),"",CM35/CL35) -> 0
A36: Deudas impuestos | B36: =IFERROR(AVERAGE(INDEX($B80:$W80,MATCH($B$3,$B$51:$W$51,0)-2):INDEX($B80:$W80,MATCH($B$3,$B$51:$W$51,0))),0) -> 0 | C36: =IFERROR(SLOPE(INDEX($B80:$W80,1):INDEX($B80:$W80,MATCH($B$3,$B$51:$W$51,0)),INDEX($B$50:$W$50,1):INDEX($B$50:$W$50,MATCH($B$3,$B$51:$W$51,0))),0) -> 0 | D36: =IF($B36=0,"",$C36/$B36) | E36: =MAX(0,ROUND($B36+$C36*3,-3)) -> 0 | G36: =SUMIFS(TablaEgresos[Valor],TablaEgresos[Categoría],$A36,TablaEgresos[Mes],F$4) -> 0 | H36: =IF(F36="","",F36-G36) | I36: =IF(OR(F36="",F36=0),"",G36/F36) | K36: =SUMIFS(TablaEgresos[Valor],TablaEgresos[Categoría],$A36,TablaEgresos[Mes],J$4) -> 0 | L36: =IF(J36="","",J36-K36) | M36: =IF(OR(J36="",J36=0),"",K36/J36) | O36: =SUMIFS(TablaEgresos[Valor],TablaEgresos[Categoría],$A36,TablaEgresos[Mes],N$4) -> 0 | P36: =IF(N36="","",N36-O36) | Q36: =IF(OR(N36="",N36=0),"",O36/N36) | S36: =SUMIFS(TablaEgresos[Valor],TablaEgresos[Categoría],$A36,TablaEgresos[Mes],R$4) -> 0 | T36: =IF(R36="","",R36-S36) | U36: =IF(OR(R36="",R36=0),"",S36/R36) | V36: 9000000 | W36: =SUMIFS(TablaEgresos[Valor],TablaEgresos[Categoría],$A36,TablaEgresos[Mes],V$4) -> 0 | X36: =IF(V36="","",V36-W36) -> 9000000 | Y36: =IF(OR(V36="",V36=0),"",W36/V36) -> 0 | Z36: 2500000 | AA36: =SUMIFS(TablaEgresos[Valor],TablaEgresos[Categoría],$A36,TablaEgresos[Mes],Z$4) -> 0 | AB36: =IF(Z36="","",Z36-AA36) -> 2500000 | AC36: =IF(OR(Z36="",Z36=0),"",AA36/Z36) -> 0 | AD36: 2500000 | AE36: =SUMIFS(TablaEgresos[Valor],TablaEgresos[Categoría],$A36,TablaEgresos[Mes],AD$4) -> 0 | AF36: =IF(AD36="","",AD36-AE36) -> 2500000 | AG36: =IF(OR(AD36="",AD36=0),"",AE36/AD36) -> 0 | AH36: 2500000 | AI36: =SUMIFS(TablaEgresos[Valor],TablaEgresos[Categoría],$A36,TablaEgresos[Mes],AH$4) -> 0 | AJ36: =IF(AH36="","",AH36-AI36) -> 2500000 | AK36: =IF(OR(AH36="",AH36=0),"",AI36/AH36) -> 0 | AL36: 2500000 | AM36: =SUMIFS(TablaEgresos[Valor],TablaEgresos[Categoría],$A36,TablaEgresos[Mes],AL$4) -> 0 | AN36: =IF(AL36="","",AL36-AM36) -> 2500000 | AO36: =IF(OR(AL36="",AL36=0),"",AM36/AL36) -> 0 | AP36: 2500000 | AQ36: =SUMIFS(TablaEgresos[Valor],TablaEgresos[Categoría],$A36,TablaEgresos[Mes],AP$4) -> 0 | AR36: =IF(AP36="","",AP36-AQ36) -> 2500000 | AS36: =IF(OR(AP36="",AP36=0),"",AQ36/AP36) -> 0 | AT36: 2500000 | AU36: =SUMIFS(TablaEgresos[Valor],TablaEgresos[Categoría],$A36,TablaEgresos[Mes],AT$4) -> 0 | AV36: =IF(AT36="","",AT36-AU36) -> 2500000 | AW36: =IF(OR(AT36="",AT36=0),"",AU36/AT36) -> 0 | AX36: 2500000 | AY36: =SUMIFS(TablaEgresos[Valor],TablaEgresos[Categoría],$A36,TablaEgresos[Mes],AX$4) -> 0 | AZ36: =IF(AX36="","",AX36-AY36) -> 2500000 | BA36: =IF(OR(AX36="",AX36=0),"",AY36/AX36) -> 0 | BB36: 2500000 | BC36: =SUMIFS(TablaEgresos[Valor],TablaEgresos[Categoría],$A36,TablaEgresos[Mes],BB$4) -> 0 | BD36: =IF(BB36="","",BB36-BC36) -> 2500000 | BE36: =IF(OR(BB36="",BB36=0),"",BC36/BB36) -> 0 | BF36: 2500000 | BG36: =SUMIFS(TablaEgresos[Valor],TablaEgresos[Categoría],$A36,TablaEgresos[Mes],BF$4) -> 0 | BH36: =IF(BF36="","",BF36-BG36) -> 2500000 | BI36: =IF(OR(BF36="",BF36=0),"",BG36/BF36) -> 0 | BJ36: 2500000 | BK36: =SUMIFS(TablaEgresos[Valor],TablaEgresos[Categoría],$A36,TablaEgresos[Mes],BJ$4) -> 0 | BL36: =IF(BJ36="","",BJ36-BK36) -> 2500000 | BM36: =IF(OR(BJ36="",BJ36=0),"",BK36/BJ36) -> 0 | BN36: 2500000 | BO36: =SUMIFS(TablaEgresos[Valor],TablaEgresos[Categoría],$A36,TablaEgresos[Mes],BN$4) -> 0 | BP36: =IF(BN36="","",BN36-BO36) -> 2500000 | BQ36: =IF(OR(BN36="",BN36=0),"",BO36/BN36) -> 0 | BR36: 2500000 | BS36: =SUMIFS(TablaEgresos[Valor],TablaEgresos[Categoría],$A36,TablaEgresos[Mes],BR$4) -> 0 | BT36: =IF(BR36="","",BR36-BS36) -> 2500000 | BU36: =IF(OR(BR36="",BR36=0),"",BS36/BR36) -> 0 | BV36: 2500000 | BW36: =SUMIFS(TablaEgresos[Valor],TablaEgresos[Categoría],$A36,TablaEgresos[Mes],BV$4) -> 0 | BX36: =IF(BV36="","",BV36-BW36) -> 2500000 | BY36: =IF(OR(BV36="",BV36=0),"",BW36/BV36) -> 0 | BZ36: 2500000 | CA36: =SUMIFS(TablaEgresos[Valor],TablaEgresos[Categoría],$A36,TablaEgresos[Mes],BZ$4) -> 0 | CB36: =IF(BZ36="","",BZ36-CA36) -> 2500000 | CC36: =IF(OR(BZ36="",BZ36=0),"",CA36/BZ36) -> 0 | CD36: 2500000 | CE36: =SUMIFS(TablaEgresos[Valor],TablaEgresos[Categoría],$A36,TablaEgresos[Mes],CD$4) -> 0 | CF36: =IF(CD36="","",CD36-CE36) -> 2500000 | CG36: =IF(OR(CD36="",CD36=0),"",CE36/CD36) -> 0 | CH36: 2500000 | CI36: =SUMIFS(TablaEgresos[Valor],TablaEgresos[Categoría],$A36,TablaEgresos[Mes],CH$4) -> 0 | CJ36: =IF(CH36="","",CH36-CI36) -> 2500000 | CK36: =IF(OR(CH36="",CH36=0),"",CI36/CH36) -> 0 | CL36: 2500000 | CM36: =SUMIFS(TablaEgresos[Valor],TablaEgresos[Categoría],$A36,TablaEgresos[Mes],CL$4) -> 0 | CN36: =IF(CL36="","",CL36-CM36) -> 2500000 | CO36: =IF(OR(CL36="",CL36=0),"",CM36/CL36) -> 0
A37: Deudas proveedores anteriores | B37: =IFERROR(AVERAGE(INDEX($B81:$W81,MATCH($B$3,$B$51:$W$51,0)-2):INDEX($B81:$W81,MATCH($B$3,$B$51:$W$51,0))),0) -> 1405599.3 | C37: =IFERROR(SLOPE(INDEX($B81:$W81,1):INDEX($B81:$W81,MATCH($B$3,$B$51:$W$51,0)),INDEX($B$50:$W$50,1):INDEX($B$50:$W$50,MATCH($B$3,$B$51:$W$51,0))),0) -> 85000.086 | D37: =IF($B37=0,"",$C37/$B37) -> 0.060472486 | E37: =MAX(0,ROUND($B37+$C37*3,-3)) -> 1661000 | G37: =SUMIFS(TablaEgresos[Valor],TablaEgresos[Categoría],$A37,TablaEgresos[Mes],F$4) -> 0 | H37: =IF(F37="","",F37-G37) | I37: =IF(OR(F37="",F37=0),"",G37/F37) | K37: =SUMIFS(TablaEgresos[Valor],TablaEgresos[Categoría],$A37,TablaEgresos[Mes],J$4) -> 1683398.6 | L37: =IF(J37="","",J37-K37) | M37: =IF(OR(J37="",J37=0),"",K37/J37) | O37: =SUMIFS(TablaEgresos[Valor],TablaEgresos[Categoría],$A37,TablaEgresos[Mes],N$4) -> 2533399.4 | P37: =IF(N37="","",N37-O37) | Q37: =IF(OR(N37="",N37=0),"",O37/N37) | S37: =SUMIFS(TablaEgresos[Valor],TablaEgresos[Categoría],$A37,TablaEgresos[Mes],R$4) -> 0 | T37: =IF(R37="","",R37-S37) | U37: =IF(OR(R37="",R37=0),"",S37/R37) | V37: 20000000 | W37: =SUMIFS(TablaEgresos[Valor],TablaEgresos[Categoría],$A37,TablaEgresos[Mes],V$4) -> 9999999.8 | X37: =IF(V37="","",V37-W37) -> 10000000 | Y37: =IF(OR(V37="",V37=0),"",W37/V37) -> 0.49999999 | Z37: 30000000 | AA37: =SUMIFS(TablaEgresos[Valor],TablaEgresos[Categoría],$A37,TablaEgresos[Mes],Z$4) -> 0 | AB37: =IF(Z37="","",Z37-AA37) -> 30000000 | AC37: =IF(OR(Z37="",Z37=0),"",AA37/Z37) -> 0 | AD37: 30000000 | AE37: =SUMIFS(TablaEgresos[Valor],TablaEgresos[Categoría],$A37,TablaEgresos[Mes],AD$4) -> 0 | AF37: =IF(AD37="","",AD37-AE37) -> 30000000 | AG37: =IF(OR(AD37="",AD37=0),"",AE37/AD37) -> 0 | AH37: 30000000 | AI37: =SUMIFS(TablaEgresos[Valor],TablaEgresos[Categoría],$A37,TablaEgresos[Mes],AH$4) -> 0 | AJ37: =IF(AH37="","",AH37-AI37) -> 30000000 | AK37: =IF(OR(AH37="",AH37=0),"",AI37/AH37) -> 0 | AL37: 30000000 | AM37: =SUMIFS(TablaEgresos[Valor],TablaEgresos[Categoría],$A37,TablaEgresos[Mes],AL$4) -> 0 | AN37: =IF(AL37="","",AL37-AM37) -> 30000000 | AO37: =IF(OR(AL37="",AL37=0),"",AM37/AL37) -> 0 | AP37: 30000000 | AQ37: =SUMIFS(TablaEgresos[Valor],TablaEgresos[Categoría],$A37,TablaEgresos[Mes],AP$4) -> 0 | AR37: =IF(AP37="","",AP37-AQ37) -> 30000000 | AS37: =IF(OR(AP37="",AP37=0),"",AQ37/AP37) -> 0 | AT37: 30000000 | AU37: =SUMIFS(TablaEgresos[Valor],TablaEgresos[Categoría],$A37,TablaEgresos[Mes],AT$4) -> 0 | AV37: =IF(AT37="","",AT37-AU37) -> 30000000 | AW37: =IF(OR(AT37="",AT37=0),"",AU37/AT37) -> 0 | AX37: 30000000 | AY37: =SUMIFS(TablaEgresos[Valor],TablaEgresos[Categoría],$A37,TablaEgresos[Mes],AX$4) -> 0 | AZ37: =IF(AX37="","",AX37-AY37) -> 30000000 | BA37: =IF(OR(AX37="",AX37=0),"",AY37/AX37) -> 0 | BB37: 30000000 | BC37: =SUMIFS(TablaEgresos[Valor],TablaEgresos[Categoría],$A37,TablaEgresos[Mes],BB$4) -> 0 | BD37: =IF(BB37="","",BB37-BC37) -> 30000000 | BE37: =IF(OR(BB37="",BB37=0),"",BC37/BB37) -> 0 | BF37: 30000000 | BG37: =SUMIFS(TablaEgresos[Valor],TablaEgresos[Categoría],$A37,TablaEgresos[Mes],BF$4) -> 0 | BH37: =IF(BF37="","",BF37-BG37) -> 30000000 | BI37: =IF(OR(BF37="",BF37=0),"",BG37/BF37) -> 0 | BJ37: 30000000 | BK37: =SUMIFS(TablaEgresos[Valor],TablaEgresos[Categoría],$A37,TablaEgresos[Mes],BJ$4) -> 0 | BL37: =IF(BJ37="","",BJ37-BK37) -> 30000000 | BM37: =IF(OR(BJ37="",BJ37=0),"",BK37/BJ37) -> 0 | BN37: 30000000 | BO37: =SUMIFS(TablaEgresos[Valor],TablaEgresos[Categoría],$A37,TablaEgresos[Mes],BN$4) -> 0 | BP37: =IF(BN37="","",BN37-BO37) -> 30000000 | BQ37: =IF(OR(BN37="",BN37=0),"",BO37/BN37) -> 0 | BR37: 30000000 | BS37: =SUMIFS(TablaEgresos[Valor],TablaEgresos[Categoría],$A37,TablaEgresos[Mes],BR$4) -> 0 | BT37: =IF(BR37="","",BR37-BS37) -> 30000000 | BU37: =IF(OR(BR37="",BR37=0),"",BS37/BR37) -> 0 | BV37: 30000000 | BW37: =SUMIFS(TablaEgresos[Valor],TablaEgresos[Categoría],$A37,TablaEgresos[Mes],BV$4) -> 0 | BX37: =IF(BV37="","",BV37-BW37) -> 30000000 | BY37: =IF(OR(BV37="",BV37=0),"",BW37/BV37) -> 0 | BZ37: 30000000 | CA37: =SUMIFS(TablaEgresos[Valor],TablaEgresos[Categoría],$A37,TablaEgresos[Mes],BZ$4) -> 0 | CB37: =IF(BZ37="","",BZ37-CA37) -> 30000000 | CC37: =IF(OR(BZ37="",BZ37=0),"",CA37/BZ37) -> 0 | CD37: 30000000 | CE37: =SUMIFS(TablaEgresos[Valor],TablaEgresos[Categoría],$A37,TablaEgresos[Mes],CD$4) -> 0 | CF37: =IF(CD37="","",CD37-CE37) -> 30000000 | CG37: =IF(OR(CD37="",CD37=0),"",CE37/CD37) -> 0 | CH37: 30000000 | CI37: =SUMIFS(TablaEgresos[Valor],TablaEgresos[Categoría],$A37,TablaEgresos[Mes],CH$4) -> 0 | CJ37: =IF(CH37="","",CH37-CI37) -> 30000000 | CK37: =IF(OR(CH37="",CH37=0),"",CI37/CH37) -> 0 | CL37: 30000000 | CM37: =SUMIFS(TablaEgresos[Valor],TablaEgresos[Categoría],$A37,TablaEgresos[Mes],CL$4) -> 0 | CN37: =IF(CL37="","",CL37-CM37) -> 30000000 | CO37: =IF(OR(CL37="",CL37=0),"",CM37/CL37) -> 0
A38: Subtotal Deudas | B38: =SUM(B33:B37) -> 9558102.8 | C38: =SUM(C33:C37) -> -4809011.1 | D38: =IF(B38=0,"",C38/B38) -> -0.50313448 | E38: =SUM(E33:E37) -> 1661000 | F38: =SUM(F33:F37) -> 0 | G38: =SUM(G33:G37) -> 12734889 | H38: =SUM(H33:H37) -> 0 | I38: =IF(F38=0,"",G38/F38) | J38: =SUM(J33:J37) -> 0 | K38: =SUM(K33:K37) -> 19279877 | L38: =SUM(L33:L37) -> 0 | M38: =IF(J38=0,"",K38/J38) | N38: =SUM(N33:N37) -> 0 | O38: =SUM(O33:O37) -> 9394431.4 | P38: =SUM(P33:P37) -> 0 | Q38: =IF(N38=0,"",O38/N38) | R38: =SUM(R33:R37) -> 0 | S38: =SUM(S33:S37) -> 0 | T38: =SUM(T33:T37) -> 0 | U38: =IF(R38=0,"",S38/R38) | V38: =SUM(V33:V37) -> 73200000 | W38: =SUM(W33:W37) -> 36853261 | X38: =SUM(X33:X37) -> 36346739 | Y38: =IF(V38=0,"",W38/V38) -> 0.50345985 | Z38: =SUM(Z33:Z37) -> 67500000 | AA38: =SUM(AA33:AA37) -> 0 | AB38: =SUM(AB33:AB37) -> 67500000 | AC38: =IF(Z38=0,"",AA38/Z38) -> 0 | AD38: =SUM(AD33:AD37) -> 67500000 | AE38: =SUM(AE33:AE37) -> 0 | AF38: =SUM(AF33:AF37) -> 67500000 | AG38: =IF(AD38=0,"",AE38/AD38) -> 0 | AH38: =SUM(AH33:AH37) -> 67500000 | AI38: =SUM(AI33:AI37) -> 0 | AJ38: =SUM(AJ33:AJ37) -> 67500000 | AK38: =IF(AH38=0,"",AI38/AH38) -> 0 | AL38: =SUM(AL33:AL37) -> 67500000 | AM38: =SUM(AM33:AM37) -> 0 | AN38: =SUM(AN33:AN37) -> 67500000 | AO38: =IF(AL38=0,"",AM38/AL38) -> 0 | AP38: =SUM(AP33:AP37) -> 67500000 | AQ38: =SUM(AQ33:AQ37) -> 0 | AR38: =SUM(AR33:AR37) -> 67500000 | AS38: =IF(AP38=0,"",AQ38/AP38) -> 0 | AT38: =SUM(AT33:AT37) -> 67500000 | AU38: =SUM(AU33:AU37) -> 0 | AV38: =SUM(AV33:AV37) -> 67500000 | AW38: =IF(AT38=0,"",AU38/AT38) -> 0 | AX38: =SUM(AX33:AX37) -> 67500000 | AY38: =SUM(AY33:AY37) -> 0 | AZ38: =SUM(AZ33:AZ37) -> 67500000 | BA38: =IF(AX38=0,"",AY38/AX38) -> 0 | BB38: =SUM(BB33:BB37) -> 67500000 | BC38: =SUM(BC33:BC37) -> 0 | BD38: =SUM(BD33:BD37) -> 67500000 | BE38: =IF(BB38=0,"",BC38/BB38) -> 0 | BF38: =SUM(BF33:BF37) -> 67500000 | BG38: =SUM(BG33:BG37) -> 0 | BH38: =SUM(BH33:BH37) -> 67500000 | BI38: =IF(BF38=0,"",BG38/BF38) -> 0 | BJ38: =SUM(BJ33:BJ37) -> 67500000 | BK38: =SUM(BK33:BK37) -> 0 | BL38: =SUM(BL33:BL37) -> 67500000 | BM38: =IF(BJ38=0,"",BK38/BJ38) -> 0 | BN38: =SUM(BN33:BN37) -> 67500000 | BO38: =SUM(BO33:BO37) -> 0 | BP38: =SUM(BP33:BP37) -> 67500000 | BQ38: =IF(BN38=0,"",BO38/BN38) -> 0 | BR38: =SUM(BR33:BR37) -> 67500000 | BS38: =SUM(BS33:BS37) -> 0 | BT38: =SUM(BT33:BT37) -> 67500000 | BU38: =IF(BR38=0,"",BS38/BR38) -> 0 | BV38: =SUM(BV33:BV37) -> 67500000 | BW38: =SUM(BW33:BW37) -> 0 | BX38: =SUM(BX33:BX37) -> 67500000 | BY38: =IF(BV38=0,"",BW38/BV38) -> 0 | BZ38: =SUM(BZ33:BZ37) -> 67500000 | CA38: =SUM(CA33:CA37) -> 0 | CB38: =SUM(CB33:CB37) -> 67500000 | CC38: =IF(BZ38=0,"",CA38/BZ38) -> 0 | CD38: =SUM(CD33:CD37) -> 67500000 | CE38: =SUM(CE33:CE37) -> 0 | CF38: =SUM(CF33:CF37) -> 67500000 | CG38: =IF(CD38=0,"",CE38/CD38) -> 0 | CH38: =SUM(CH33:CH37) -> 67500000 | CI38: =SUM(CI33:CI37) -> 0 | CJ38: =SUM(CJ33:CJ37) -> 67500000 | CK38: =IF(CH38=0,"",CI38/CH38) -> 0 | CL38: =SUM(CL33:CL37) -> 67500000 | CM38: =SUM(CM33:CM37) -> 0 | CN38: =SUM(CN33:CN37) -> 67500000 | CO38: =IF(CL38=0,"",CM38/CL38) -> 0
A39: OTROS Y VARIOS
A40: Otros gastos | B40: =IFERROR(AVERAGE(INDEX($B84:$W84,MATCH($B$3,$B$51:$W$51,0)-2):INDEX($B84:$W84,MATCH($B$3,$B$51:$W$51,0))),0) -> 37682173 | C40: =IFERROR(SLOPE(INDEX($B84:$W84,1):INDEX($B84:$W84,MATCH($B$3,$B$51:$W$51,0)),INDEX($B$50:$W$50,1):INDEX($B$50:$W$50,MATCH($B$3,$B$51:$W$51,0))),0) -> 8735954.6 | D40: =IF($B40=0,"",$C40/$B40) -> 0.23183256 | E40: =MAX(0,ROUND($B40+$C40*3,-3)) -> 63890000 | G40: =SUMIFS(TablaEgresos[Valor],TablaEgresos[Categoría],$A40,TablaEgresos[Mes],F$4) -> 1616605.3 | H40: =IF(F40="","",F40-G40) | I40: =IF(OR(F40="",F40=0),"",G40/F40) | K40: =SUMIFS(TablaEgresos[Valor],TablaEgresos[Categoría],$A40,TablaEgresos[Mes],J$4) -> 39505270 | L40: =IF(J40="","",J40-K40) | M40: =IF(OR(J40="",J40=0),"",K40/J40) | O40: =SUMIFS(TablaEgresos[Valor],TablaEgresos[Categoría],$A40,TablaEgresos[Mes],N$4) -> 44454558 | P40: =IF(N40="","",N40-O40) | Q40: =IF(OR(N40="",N40=0),"",O40/N40) | S40: =SUMIFS(TablaEgresos[Valor],TablaEgresos[Categoría],$A40,TablaEgresos[Mes],R$4) -> 29086691 | T40: =IF(R40="","",R40-S40) | U40: =IF(OR(R40="",R40=0),"",S40/R40) | V40: 19000000 | W40: =SUMIFS(TablaEgresos[Valor],TablaEgresos[Categoría],$A40,TablaEgresos[Mes],V$4) -> 10084789 | X40: =IF(V40="","",V40-W40) -> 8915210.7 | Y40: =IF(OR(V40="",V40=0),"",W40/V40) -> 0.53077839 | Z40: 5000000 | AA40: =SUMIFS(TablaEgresos[Valor],TablaEgresos[Categoría],$A40,TablaEgresos[Mes],Z$4) -> 0 | AB40: =IF(Z40="","",Z40-AA40) -> 5000000 | AC40: =IF(OR(Z40="",Z40=0),"",AA40/Z40) -> 0 | AD40: 5000000 | AE40: =SUMIFS(TablaEgresos[Valor],TablaEgresos[Categoría],$A40,TablaEgresos[Mes],AD$4) -> 0 | AF40: =IF(AD40="","",AD40-AE40) -> 5000000 | AG40: =IF(OR(AD40="",AD40=0),"",AE40/AD40) -> 0 | AH40: 5000000 | AI40: =SUMIFS(TablaEgresos[Valor],TablaEgresos[Categoría],$A40,TablaEgresos[Mes],AH$4) -> 0 | AJ40: =IF(AH40="","",AH40-AI40) -> 5000000 | AK40: =IF(OR(AH40="",AH40=0),"",AI40/AH40) -> 0 | AL40: 5000000 | AM40: =SUMIFS(TablaEgresos[Valor],TablaEgresos[Categoría],$A40,TablaEgresos[Mes],AL$4) -> 0 | AN40: =IF(AL40="","",AL40-AM40) -> 5000000 | AO40: =IF(OR(AL40="",AL40=0),"",AM40/AL40) -> 0 | AP40: 5000000 | AQ40: =SUMIFS(TablaEgresos[Valor],TablaEgresos[Categoría],$A40,TablaEgresos[Mes],AP$4) -> 0 | AR40: =IF(AP40="","",AP40-AQ40) -> 5000000 | AS40: =IF(OR(AP40="",AP40=0),"",AQ40/AP40) -> 0 | AT40: 5000000 | AU40: =SUMIFS(TablaEgresos[Valor],TablaEgresos[Categoría],$A40,TablaEgresos[Mes],AT$4) -> 0 | AV40: =IF(AT40="","",AT40-AU40) -> 5000000 | AW40: =IF(OR(AT40="",AT40=0),"",AU40/AT40) -> 0 | AX40: 5000000 | AY40: =SUMIFS(TablaEgresos[Valor],TablaEgresos[Categoría],$A40,TablaEgresos[Mes],AX$4) -> 0 | AZ40: =IF(AX40="","",AX40-AY40) -> 5000000 | BA40: =IF(OR(AX40="",AX40=0),"",AY40/AX40) -> 0 | BB40: 5000000 | BC40: =SUMIFS(TablaEgresos[Valor],TablaEgresos[Categoría],$A40,TablaEgresos[Mes],BB$4) -> 0 | BD40: =IF(BB40="","",BB40-BC40) -> 5000000 | BE40: =IF(OR(BB40="",BB40=0),"",BC40/BB40) -> 0 | BF40: 5000000 | BG40: =SUMIFS(TablaEgresos[Valor],TablaEgresos[Categoría],$A40,TablaEgresos[Mes],BF$4) -> 0 | BH40: =IF(BF40="","",BF40-BG40) -> 5000000 | BI40: =IF(OR(BF40="",BF40=0),"",BG40/BF40) -> 0 | BJ40: 5000000 | BK40: =SUMIFS(TablaEgresos[Valor],TablaEgresos[Categoría],$A40,TablaEgresos[Mes],BJ$4) -> 0 | BL40: =IF(BJ40="","",BJ40-BK40) -> 5000000 | BM40: =IF(OR(BJ40="",BJ40=0),"",BK40/BJ40) -> 0 | BN40: 5000000 | BO40: =SUMIFS(TablaEgresos[Valor],TablaEgresos[Categoría],$A40,TablaEgresos[Mes],BN$4) -> 0 | BP40: =IF(BN40="","",BN40-BO40) -> 5000000 | BQ40: =IF(OR(BN40="",BN40=0),"",BO40/BN40) -> 0 | BR40: 5000000 | BS40: =SUMIFS(TablaEgresos[Valor],TablaEgresos[Categoría],$A40,TablaEgresos[Mes],BR$4) -> 0 | BT40: =IF(BR40="","",BR40-BS40) -> 5000000 | BU40: =IF(OR(BR40="",BR40=0),"",BS40/BR40) -> 0 | BV40: 5000000 | BW40: =SUMIFS(TablaEgresos[Valor],TablaEgresos[Categoría],$A40,TablaEgresos[Mes],BV$4) -> 0 | BX40: =IF(BV40="","",BV40-BW40) -> 5000000 | BY40: =IF(OR(BV40="",BV40=0),"",BW40/BV40) -> 0 | BZ40: 5000000 | CA40: =SUMIFS(TablaEgresos[Valor],TablaEgresos[Categoría],$A40,TablaEgresos[Mes],BZ$4) -> 0 | CB40: =IF(BZ40="","",BZ40-CA40) -> 5000000 | CC40: =IF(OR(BZ40="",BZ40=0),"",CA40/BZ40) -> 0 | CD40: 5000000 | CE40: =SUMIFS(TablaEgresos[Valor],TablaEgresos[Categoría],$A40,TablaEgresos[Mes],CD$4) -> 0 | CF40: =IF(CD40="","",CD40-CE40) -> 5000000 | CG40: =IF(OR(CD40="",CD40=0),"",CE40/CD40) -> 0 | CH40: 5000000 | CI40: =SUMIFS(TablaEgresos[Valor],TablaEgresos[Categoría],$A40,TablaEgresos[Mes],CH$4) -> 0 | CJ40: =IF(CH40="","",CH40-CI40) -> 5000000 | CK40: =IF(OR(CH40="",CH40=0),"",CI40/CH40) -> 0 | CL40: 5000000 | CM40: =SUMIFS(TablaEgresos[Valor],TablaEgresos[Categoría],$A40,TablaEgresos[Mes],CL$4) -> 0 | CN40: =IF(CL40="","",CL40-CM40) -> 5000000 | CO40: =IF(OR(CL40="",CL40=0),"",CM40/CL40) -> 0
A41: Gastos notariales | B41: =IFERROR(AVERAGE(INDEX($B85:$W85,MATCH($B$3,$B$51:$W$51,0)-2):INDEX($B85:$W85,MATCH($B$3,$B$51:$W$51,0))),0) -> 117528.67 | C41: =IFERROR(SLOPE(INDEX($B85:$W85,1):INDEX($B85:$W85,MATCH($B$3,$B$51:$W$51,0)),INDEX($B$50:$W$50,1):INDEX($B$50:$W$50,MATCH($B$3,$B$51:$W$51,0))),0) -> 33590.2 | D41: =IF($B41=0,"",$C41/$B41) -> 0.28580431 | E41: =MAX(0,ROUND($B41+$C41*3,-3)) -> 218000 | G41: =SUMIFS(TablaEgresos[Valor],TablaEgresos[Categoría],$A41,TablaEgresos[Mes],F$4) -> 0 | H41: =IF(F41="","",F41-G41) | I41: =IF(OR(F41="",F41=0),"",G41/F41) | K41: =SUMIFS(TablaEgresos[Valor],TablaEgresos[Categoría],$A41,TablaEgresos[Mes],J$4) -> 180464 | L41: =IF(J41="","",J41-K41) | M41: =IF(OR(J41="",J41=0),"",K41/J41) | O41: =SUMIFS(TablaEgresos[Valor],TablaEgresos[Categoría],$A41,TablaEgresos[Mes],N$4) -> 0 | P41: =IF(N41="","",N41-O41) | Q41: =IF(OR(N41="",N41=0),"",O41/N41) | S41: =SUMIFS(TablaEgresos[Valor],TablaEgresos[Categoría],$A41,TablaEgresos[Mes],R$4) -> 172122 | T41: =IF(R41="","",R41-S41) | U41: =IF(OR(R41="",R41=0),"",S41/R41) | V41: 0 | W41: =SUMIFS(TablaEgresos[Valor],TablaEgresos[Categoría],$A41,TablaEgresos[Mes],V$4) -> 3686613 | X41: =IF(V41="","",V41-W41) -> -3686613 | Y41: =IF(OR(V41="",V41=0),"",W41/V41) | Z41: 0 | AA41: =SUMIFS(TablaEgresos[Valor],TablaEgresos[Categoría],$A41,TablaEgresos[Mes],Z$4) -> 0 | AB41: =IF(Z41="","",Z41-AA41) -> 0 | AC41: =IF(OR(Z41="",Z41=0),"",AA41/Z41) | AD41: 0 | AE41: =SUMIFS(TablaEgresos[Valor],TablaEgresos[Categoría],$A41,TablaEgresos[Mes],AD$4) -> 0 | AF41: =IF(AD41="","",AD41-AE41) -> 0 | AG41: =IF(OR(AD41="",AD41=0),"",AE41/AD41) | AH41: 0 | AI41: =SUMIFS(TablaEgresos[Valor],TablaEgresos[Categoría],$A41,TablaEgresos[Mes],AH$4) -> 0 | AJ41: =IF(AH41="","",AH41-AI41) -> 0 | AK41: =IF(OR(AH41="",AH41=0),"",AI41/AH41) | AL41: 0 | AM41: =SUMIFS(TablaEgresos[Valor],TablaEgresos[Categoría],$A41,TablaEgresos[Mes],AL$4) -> 0 | AN41: =IF(AL41="","",AL41-AM41) -> 0 | AO41: =IF(OR(AL41="",AL41=0),"",AM41/AL41) | AP41: 0 | AQ41: =SUMIFS(TablaEgresos[Valor],TablaEgresos[Categoría],$A41,TablaEgresos[Mes],AP$4) -> 0 | AR41: =IF(AP41="","",AP41-AQ41) -> 0 | AS41: =IF(OR(AP41="",AP41=0),"",AQ41/AP41) | AT41: 0 | AU41: =SUMIFS(TablaEgresos[Valor],TablaEgresos[Categoría],$A41,TablaEgresos[Mes],AT$4) -> 0 | AV41: =IF(AT41="","",AT41-AU41) -> 0 | AW41: =IF(OR(AT41="",AT41=0),"",AU41/AT41) | AX41: 0 | AY41: =SUMIFS(TablaEgresos[Valor],TablaEgresos[Categoría],$A41,TablaEgresos[Mes],AX$4) -> 0 | AZ41: =IF(AX41="","",AX41-AY41) -> 0 | BA41: =IF(OR(AX41="",AX41=0),"",AY41/AX41) | BB41: 0 | BC41: =SUMIFS(TablaEgresos[Valor],TablaEgresos[Categoría],$A41,TablaEgresos[Mes],BB$4) -> 0 | BD41: =IF(BB41="","",BB41-BC41) -> 0 | BE41: =IF(OR(BB41="",BB41=0),"",BC41/BB41) | BF41: 0 | BG41: =SUMIFS(TablaEgresos[Valor],TablaEgresos[Categoría],$A41,TablaEgresos[Mes],BF$4) -> 0 | BH41: =IF(BF41="","",BF41-BG41) -> 0 | BI41: =IF(OR(BF41="",BF41=0),"",BG41/BF41) | BJ41: 0 | BK41: =SUMIFS(TablaEgresos[Valor],TablaEgresos[Categoría],$A41,TablaEgresos[Mes],BJ$4) -> 0 | BL41: =IF(BJ41="","",BJ41-BK41) -> 0 | BM41: =IF(OR(BJ41="",BJ41=0),"",BK41/BJ41) | BN41: 0 | BO41: =SUMIFS(TablaEgresos[Valor],TablaEgresos[Categoría],$A41,TablaEgresos[Mes],BN$4) -> 0 | BP41: =IF(BN41="","",BN41-BO41) -> 0 | BQ41: =IF(OR(BN41="",BN41=0),"",BO41/BN41) | BR41: 0 | BS41: =SUMIFS(TablaEgresos[Valor],TablaEgresos[Categoría],$A41,TablaEgresos[Mes],BR$4) -> 0 | BT41: =IF(BR41="","",BR41-BS41) -> 0 | BU41: =IF(OR(BR41="",BR41=0),"",BS41/BR41) | BV41: 0 | BW41: =SUMIFS(TablaEgresos[Valor],TablaEgresos[Categoría],$A41,TablaEgresos[Mes],BV$4) -> 0 | BX41: =IF(BV41="","",BV41-BW41) -> 0 | BY41: =IF(OR(BV41="",BV41=0),"",BW41/BV41) | BZ41: 0 | CA41: =SUMIFS(TablaEgresos[Valor],TablaEgresos[Categoría],$A41,TablaEgresos[Mes],BZ$4) -> 0 | CB41: =IF(BZ41="","",BZ41-CA41) -> 0 | CC41: =IF(OR(BZ41="",BZ41=0),"",CA41/BZ41) | CD41: 0 | CE41: =SUMIFS(TablaEgresos[Valor],TablaEgresos[Categoría],$A41,TablaEgresos[Mes],CD$4) -> 0 | CF41: =IF(CD41="","",CD41-CE41) -> 0 | CG41: =IF(OR(CD41="",CD41=0),"",CE41/CD41) | CH41: 0 | CI41: =SUMIFS(TablaEgresos[Valor],TablaEgresos[Categoría],$A41,TablaEgresos[Mes],CH$4) -> 0 | CJ41: =IF(CH41="","",CH41-CI41) -> 0 | CK41: =IF(OR(CH41="",CH41=0),"",CI41/CH41) | CL41: 0 | CM41: =SUMIFS(TablaEgresos[Valor],TablaEgresos[Categoría],$A41,TablaEgresos[Mes],CL$4) -> 0 | CN41: =IF(CL41="","",CL41-CM41) -> 0 | CO41: =IF(OR(CL41="",CL41=0),"",CM41/CL41)
A42: Gastos bancarios | B42: =IFERROR(AVERAGE(INDEX($B86:$W86,MATCH($B$3,$B$51:$W$51,0)-2):INDEX($B86:$W86,MATCH($B$3,$B$51:$W$51,0))),0) -> 35414.667 | C42: =IFERROR(SLOPE(INDEX($B86:$W86,1):INDEX($B86:$W86,MATCH($B$3,$B$51:$W$51,0)),INDEX($B$50:$W$50,1):INDEX($B$50:$W$50,MATCH($B$3,$B$51:$W$51,0))),0) -> 16891.2 | D42: =IF($B42=0,"",$C42/$B42) -> 0.47695493 | E42: =MAX(0,ROUND($B42+$C42*3,-3)) -> 86000 | G42: =SUMIFS(TablaEgresos[Valor],TablaEgresos[Categoría],$A42,TablaEgresos[Mes],F$4) -> 0 | H42: =IF(F42="","",F42-G42) | I42: =IF(OR(F42="",F42=0),"",G42/F42) | K42: =SUMIFS(TablaEgresos[Valor],TablaEgresos[Categoría],$A42,TablaEgresos[Mes],J$4) -> 27457 | L42: =IF(J42="","",J42-K42) | M42: =IF(OR(J42="",J42=0),"",K42/J42) | O42: =SUMIFS(TablaEgresos[Valor],TablaEgresos[Categoría],$A42,TablaEgresos[Mes],N$4) -> 19996 | P42: =IF(N42="","",N42-O42) | Q42: =IF(OR(N42="",N42=0),"",O42/N42) | S42: =SUMIFS(TablaEgresos[Valor],TablaEgresos[Categoría],$A42,TablaEgresos[Mes],R$4) -> 58791 | T42: =IF(R42="","",R42-S42) | U42: =IF(OR(R42="",R42=0),"",S42/R42) | V42: 0 | W42: =SUMIFS(TablaEgresos[Valor],TablaEgresos[Categoría],$A42,TablaEgresos[Mes],V$4) -> 29701 | X42: =IF(V42="","",V42-W42) -> -29701 | Y42: =IF(OR(V42="",V42=0),"",W42/V42) | Z42: 300000 | AA42: =SUMIFS(TablaEgresos[Valor],TablaEgresos[Categoría],$A42,TablaEgresos[Mes],Z$4) -> 0 | AB42: =IF(Z42="","",Z42-AA42) -> 300000 | AC42: =IF(OR(Z42="",Z42=0),"",AA42/Z42) -> 0 | AD42: 300000 | AE42: =SUMIFS(TablaEgresos[Valor],TablaEgresos[Categoría],$A42,TablaEgresos[Mes],AD$4) -> 0 | AF42: =IF(AD42="","",AD42-AE42) -> 300000 | AG42: =IF(OR(AD42="",AD42=0),"",AE42/AD42) -> 0 | AH42: 300000 | AI42: =SUMIFS(TablaEgresos[Valor],TablaEgresos[Categoría],$A42,TablaEgresos[Mes],AH$4) -> 0 | AJ42: =IF(AH42="","",AH42-AI42) -> 300000 | AK42: =IF(OR(AH42="",AH42=0),"",AI42/AH42) -> 0 | AL42: 300000 | AM42: =SUMIFS(TablaEgresos[Valor],TablaEgresos[Categoría],$A42,TablaEgresos[Mes],AL$4) -> 0 | AN42: =IF(AL42="","",AL42-AM42) -> 300000 | AO42: =IF(OR(AL42="",AL42=0),"",AM42/AL42) -> 0 | AP42: 300000 | AQ42: =SUMIFS(TablaEgresos[Valor],TablaEgresos[Categoría],$A42,TablaEgresos[Mes],AP$4) -> 0 | AR42: =IF(AP42="","",AP42-AQ42) -> 300000 | AS42: =IF(OR(AP42="",AP42=0),"",AQ42/AP42) -> 0 | AT42: 300000 | AU42: =SUMIFS(TablaEgresos[Valor],TablaEgresos[Categoría],$A42,TablaEgresos[Mes],AT$4) -> 0 | AV42: =IF(AT42="","",AT42-AU42) -> 300000 | AW42: =IF(OR(AT42="",AT42=0),"",AU42/AT42) -> 0 | AX42: 300000 | AY42: =SUMIFS(TablaEgresos[Valor],TablaEgresos[Categoría],$A42,TablaEgresos[Mes],AX$4) -> 0 | AZ42: =IF(AX42="","",AX42-AY42) -> 300000 | BA42: =IF(OR(AX42="",AX42=0),"",AY42/AX42) -> 0 | BB42: 300000 | BC42: =SUMIFS(TablaEgresos[Valor],TablaEgresos[Categoría],$A42,TablaEgresos[Mes],BB$4) -> 0 | BD42: =IF(BB42="","",BB42-BC42) -> 300000 | BE42: =IF(OR(BB42="",BB42=0),"",BC42/BB42) -> 0 | BF42: 300000 | BG42: =SUMIFS(TablaEgresos[Valor],TablaEgresos[Categoría],$A42,TablaEgresos[Mes],BF$4) -> 0 | BH42: =IF(BF42="","",BF42-BG42) -> 300000 | BI42: =IF(OR(BF42="",BF42=0),"",BG42/BF42) -> 0 | BJ42: 300000 | BK42: =SUMIFS(TablaEgresos[Valor],TablaEgresos[Categoría],$A42,TablaEgresos[Mes],BJ$4) -> 0 | BL42: =IF(BJ42="","",BJ42-BK42) -> 300000 | BM42: =IF(OR(BJ42="",BJ42=0),"",BK42/BJ42) -> 0 | BN42: 300000 | BO42: =SUMIFS(TablaEgresos[Valor],TablaEgresos[Categoría],$A42,TablaEgresos[Mes],BN$4) -> 0 | BP42: =IF(BN42="","",BN42-BO42) -> 300000 | BQ42: =IF(OR(BN42="",BN42=0),"",BO42/BN42) -> 0 | BR42: 300000 | BS42: =SUMIFS(TablaEgresos[Valor],TablaEgresos[Categoría],$A42,TablaEgresos[Mes],BR$4) -> 0 | BT42: =IF(BR42="","",BR42-BS42) -> 300000 | BU42: =IF(OR(BR42="",BR42=0),"",BS42/BR42) -> 0 | BV42: 300000 | BW42: =SUMIFS(TablaEgresos[Valor],TablaEgresos[Categoría],$A42,TablaEgresos[Mes],BV$4) -> 0 | BX42: =IF(BV42="","",BV42-BW42) -> 300000 | BY42: =IF(OR(BV42="",BV42=0),"",BW42/BV42) -> 0 | BZ42: 300000 | CA42: =SUMIFS(TablaEgresos[Valor],TablaEgresos[Categoría],$A42,TablaEgresos[Mes],BZ$4) -> 0 | CB42: =IF(BZ42="","",BZ42-CA42) -> 300000 | CC42: =IF(OR(BZ42="",BZ42=0),"",CA42/BZ42) -> 0 | CD42: 300000 | CE42: =SUMIFS(TablaEgresos[Valor],TablaEgresos[Categoría],$A42,TablaEgresos[Mes],CD$4) -> 0 | CF42: =IF(CD42="","",CD42-CE42) -> 300000 | CG42: =IF(OR(CD42="",CD42=0),"",CE42/CD42) -> 0 | CH42: 300000 | CI42: =SUMIFS(TablaEgresos[Valor],TablaEgresos[Categoría],$A42,TablaEgresos[Mes],CH$4) -> 0 | CJ42: =IF(CH42="","",CH42-CI42) -> 300000 | CK42: =IF(OR(CH42="",CH42=0),"",CI42/CH42) -> 0 | CL42: 300000 | CM42: =SUMIFS(TablaEgresos[Valor],TablaEgresos[Categoría],$A42,TablaEgresos[Mes],CL$4) -> 0 | CN42: =IF(CL42="","",CL42-CM42) -> 300000 | CO42: =IF(OR(CL42="",CL42=0),"",CM42/CL42) -> 0
A43: Gastos financieros | B43: =IFERROR(AVERAGE(INDEX($B87:$W87,MATCH($B$3,$B$51:$W$51,0)-2):INDEX($B87:$W87,MATCH($B$3,$B$51:$W$51,0))),0) -> 3054.42 | C43: =IFERROR(SLOPE(INDEX($B87:$W87,1):INDEX($B87:$W87,MATCH($B$3,$B$51:$W$51,0)),INDEX($B$50:$W$50,1):INDEX($B$50:$W$50,MATCH($B$3,$B$51:$W$51,0))),0) -> -916.326 | D43: =IF($B43=0,"",$C43/$B43) -> -0.3 | E43: =MAX(0,ROUND($B43+$C43*3,-3)) -> 0 | G43: =SUMIFS(TablaEgresos[Valor],TablaEgresos[Categoría],$A43,TablaEgresos[Mes],F$4) -> 0 | H43: =IF(F43="","",F43-G43) | I43: =IF(OR(F43="",F43=0),"",G43/F43) | K43: =SUMIFS(TablaEgresos[Valor],TablaEgresos[Categoría],$A43,TablaEgresos[Mes],J$4) -> 9163.26 | L43: =IF(J43="","",J43-K43) | M43: =IF(OR(J43="",J43=0),"",K43/J43) | O43: =SUMIFS(TablaEgresos[Valor],TablaEgresos[Categoría],$A43,TablaEgresos[Mes],N$4) -> 0 | P43: =IF(N43="","",N43-O43) | Q43: =IF(OR(N43="",N43=0),"",O43/N43) | S43: =SUMIFS(TablaEgresos[Valor],TablaEgresos[Categoría],$A43,TablaEgresos[Mes],R$4) -> 0 | T43: =IF(R43="","",R43-S43) | U43: =IF(OR(R43="",R43=0),"",S43/R43) | V43: 0 | W43: =SUMIFS(TablaEgresos[Valor],TablaEgresos[Categoría],$A43,TablaEgresos[Mes],V$4) -> 0 | X43: =IF(V43="","",V43-W43) -> 0 | Y43: =IF(OR(V43="",V43=0),"",W43/V43) | Z43: 300000 | AA43: =SUMIFS(TablaEgresos[Valor],TablaEgresos[Categoría],$A43,TablaEgresos[Mes],Z$4) -> 0 | AB43: =IF(Z43="","",Z43-AA43) -> 300000 | AC43: =IF(OR(Z43="",Z43=0),"",AA43/Z43) -> 0 | AD43: 300000 | AE43: =SUMIFS(TablaEgresos[Valor],TablaEgresos[Categoría],$A43,TablaEgresos[Mes],AD$4) -> 0 | AF43: =IF(AD43="","",AD43-AE43) -> 300000 | AG43: =IF(OR(AD43="",AD43=0),"",AE43/AD43) -> 0 | AH43: 300000 | AI43: =SUMIFS(TablaEgresos[Valor],TablaEgresos[Categoría],$A43,TablaEgresos[Mes],AH$4) -> 0 | AJ43: =IF(AH43="","",AH43-AI43) -> 300000 | AK43: =IF(OR(AH43="",AH43=0),"",AI43/AH43) -> 0 | AL43: 300000 | AM43: =SUMIFS(TablaEgresos[Valor],TablaEgresos[Categoría],$A43,TablaEgresos[Mes],AL$4) -> 0 | AN43: =IF(AL43="","",AL43-AM43) -> 300000 | AO43: =IF(OR(AL43="",AL43=0),"",AM43/AL43) -> 0 | AP43: 300000 | AQ43: =SUMIFS(TablaEgresos[Valor],TablaEgresos[Categoría],$A43,TablaEgresos[Mes],AP$4) -> 0 | AR43: =IF(AP43="","",AP43-AQ43) -> 300000 | AS43: =IF(OR(AP43="",AP43=0),"",AQ43/AP43) -> 0 | AT43: 300000 | AU43: =SUMIFS(TablaEgresos[Valor],TablaEgresos[Categoría],$A43,TablaEgresos[Mes],AT$4) -> 0 | AV43: =IF(AT43="","",AT43-AU43) -> 300000 | AW43: =IF(OR(AT43="",AT43=0),"",AU43/AT43) -> 0 | AX43: 300000 | AY43: =SUMIFS(TablaEgresos[Valor],TablaEgresos[Categoría],$A43,TablaEgresos[Mes],AX$4) -> 0 | AZ43: =IF(AX43="","",AX43-AY43) -> 300000 | BA43: =IF(OR(AX43="",AX43=0),"",AY43/AX43) -> 0 | BB43: 300000 | BC43: =SUMIFS(TablaEgresos[Valor],TablaEgresos[Categoría],$A43,TablaEgresos[Mes],BB$4) -> 0 | BD43: =IF(BB43="","",BB43-BC43) -> 300000 | BE43: =IF(OR(BB43="",BB43=0),"",BC43/BB43) -> 0 | BF43: 300000 | BG43: =SUMIFS(TablaEgresos[Valor],TablaEgresos[Categoría],$A43,TablaEgresos[Mes],BF$4) -> 0 | BH43: =IF(BF43="","",BF43-BG43) -> 300000 | BI43: =IF(OR(BF43="",BF43=0),"",BG43/BF43) -> 0 | BJ43: 300000 | BK43: =SUMIFS(TablaEgresos[Valor],TablaEgresos[Categoría],$A43,TablaEgresos[Mes],BJ$4) -> 0 | BL43: =IF(BJ43="","",BJ43-BK43) -> 300000 | BM43: =IF(OR(BJ43="",BJ43=0),"",BK43/BJ43) -> 0 | BN43: 300000 | BO43: =SUMIFS(TablaEgresos[Valor],TablaEgresos[Categoría],$A43,TablaEgresos[Mes],BN$4) -> 0 | BP43: =IF(BN43="","",BN43-BO43) -> 300000 | BQ43: =IF(OR(BN43="",BN43=0),"",BO43/BN43) -> 0 | BR43: 300000 | BS43: =SUMIFS(TablaEgresos[Valor],TablaEgresos[Categoría],$A43,TablaEgresos[Mes],BR$4) -> 0 | BT43: =IF(BR43="","",BR43-BS43) -> 300000 | BU43: =IF(OR(BR43="",BR43=0),"",BS43/BR43) -> 0 | BV43: 300000 | BW43: =SUMIFS(TablaEgresos[Valor],TablaEgresos[Categoría],$A43,TablaEgresos[Mes],BV$4) -> 0 | BX43: =IF(BV43="","",BV43-BW43) -> 300000 | BY43: =IF(OR(BV43="",BV43=0),"",BW43/BV43) -> 0 | BZ43: 300000 | CA43: =SUMIFS(TablaEgresos[Valor],TablaEgresos[Categoría],$A43,TablaEgresos[Mes],BZ$4) -> 0 | CB43: =IF(BZ43="","",BZ43-CA43) -> 300000 | CC43: =IF(OR(BZ43="",BZ43=0),"",CA43/BZ43) -> 0 | CD43: 300000 | CE43: =SUMIFS(TablaEgresos[Valor],TablaEgresos[Categoría],$A43,TablaEgresos[Mes],CD$4) -> 0 | CF43: =IF(CD43="","",CD43-CE43) -> 300000 | CG43: =IF(OR(CD43="",CD43=0),"",CE43/CD43) -> 0 | CH43: 300000 | CI43: =SUMIFS(TablaEgresos[Valor],TablaEgresos[Categoría],$A43,TablaEgresos[Mes],CH$4) -> 0 | CJ43: =IF(CH43="","",CH43-CI43) -> 300000 | CK43: =IF(OR(CH43="",CH43=0),"",CI43/CH43) -> 0 | CL43: 300000 | CM43: =SUMIFS(TablaEgresos[Valor],TablaEgresos[Categoría],$A43,TablaEgresos[Mes],CL$4) -> 0 | CN43: =IF(CL43="","",CL43-CM43) -> 300000 | CO43: =IF(OR(CL43="",CL43=0),"",CM43/CL43) -> 0
A44: Impuestos | B44: =IFERROR(AVERAGE(INDEX($B88:$W88,MATCH($B$3,$B$51:$W$51,0)-2):INDEX($B88:$W88,MATCH($B$3,$B$51:$W$51,0))),0) -> 626312.33 | C44: =IFERROR(SLOPE(INDEX($B88:$W88,1):INDEX($B88:$W88,MATCH($B$3,$B$51:$W$51,0)),INDEX($B$50:$W$50,1):INDEX($B$50:$W$50,MATCH($B$3,$B$51:$W$51,0))),0) -> 191175.34 | D44: =IF($B44=0,"",$C44/$B44) -> 0.30523962 | E44: =MAX(0,ROUND($B44+$C44*3,-3)) -> 1200000 | G44: =SUMIFS(TablaEgresos[Valor],TablaEgresos[Categoría],$A44,TablaEgresos[Mes],F$4) -> 8247.76 | H44: =IF(F44="","",F44-G44) | I44: =IF(OR(F44="",F44=0),"",G44/F44) | K44: =SUMIFS(TablaEgresos[Valor],TablaEgresos[Categoría],$A44,TablaEgresos[Mes],J$4) -> 746212.48 | L44: =IF(J44="","",J44-K44) | M44: =IF(OR(J44="",J44=0),"",K44/J44) | O44: =SUMIFS(TablaEgresos[Valor],TablaEgresos[Categoría],$A44,TablaEgresos[Mes],N$4) -> 357732.21 | P44: =IF(N44="","",N44-O44) | Q44: =IF(OR(N44="",N44=0),"",O44/N44) | S44: =SUMIFS(TablaEgresos[Valor],TablaEgresos[Categoría],$A44,TablaEgresos[Mes],R$4) -> 774992.31 | T44: =IF(R44="","",R44-S44) | U44: =IF(OR(R44="",R44=0),"",S44/R44) | V44: 0 | W44: =SUMIFS(TablaEgresos[Valor],TablaEgresos[Categoría],$A44,TablaEgresos[Mes],V$4) -> 859232.27 | X44: =IF(V44="","",V44-W44) -> -859232.27 | Y44: =IF(OR(V44="",V44=0),"",W44/V44) | Z44: 2500000 | AA44: =SUMIFS(TablaEgresos[Valor],TablaEgresos[Categoría],$A44,TablaEgresos[Mes],Z$4) -> 0 | AB44: =IF(Z44="","",Z44-AA44) -> 2500000 | AC44: =IF(OR(Z44="",Z44=0),"",AA44/Z44) -> 0 | AD44: 2500000 | AE44: =SUMIFS(TablaEgresos[Valor],TablaEgresos[Categoría],$A44,TablaEgresos[Mes],AD$4) -> 0 | AF44: =IF(AD44="","",AD44-AE44) -> 2500000 | AG44: =IF(OR(AD44="",AD44=0),"",AE44/AD44) -> 0 | AH44: 2500000 | AI44: =SUMIFS(TablaEgresos[Valor],TablaEgresos[Categoría],$A44,TablaEgresos[Mes],AH$4) -> 0 | AJ44: =IF(AH44="","",AH44-AI44) -> 2500000 | AK44: =IF(OR(AH44="",AH44=0),"",AI44/AH44) -> 0 | AL44: 2500000 | AM44: =SUMIFS(TablaEgresos[Valor],TablaEgresos[Categoría],$A44,TablaEgresos[Mes],AL$4) -> 0 | AN44: =IF(AL44="","",AL44-AM44) -> 2500000 | AO44: =IF(OR(AL44="",AL44=0),"",AM44/AL44) -> 0 | AP44: 2500000 | AQ44: =SUMIFS(TablaEgresos[Valor],TablaEgresos[Categoría],$A44,TablaEgresos[Mes],AP$4) -> 0 | AR44: =IF(AP44="","",AP44-AQ44) -> 2500000 | AS44: =IF(OR(AP44="",AP44=0),"",AQ44/AP44) -> 0 | AT44: 2500000 | AU44: =SUMIFS(TablaEgresos[Valor],TablaEgresos[Categoría],$A44,TablaEgresos[Mes],AT$4) -> 0 | AV44: =IF(AT44="","",AT44-AU44) -> 2500000 | AW44: =IF(OR(AT44="",AT44=0),"",AU44/AT44) -> 0 | AX44: 2500000 | AY44: =SUMIFS(TablaEgresos[Valor],TablaEgresos[Categoría],$A44,TablaEgresos[Mes],AX$4) -> 0 | AZ44: =IF(AX44="","",AX44-AY44) -> 2500000 | BA44: =IF(OR(AX44="",AX44=0),"",AY44/AX44) -> 0 | BB44: 2500000 | BC44: =SUMIFS(TablaEgresos[Valor],TablaEgresos[Categoría],$A44,TablaEgresos[Mes],BB$4) -> 0 | BD44: =IF(BB44="","",BB44-BC44) -> 2500000 | BE44: =IF(OR(BB44="",BB44=0),"",BC44/BB44) -> 0 | BF44: 2500000 | BG44: =SUMIFS(TablaEgresos[Valor],TablaEgresos[Categoría],$A44,TablaEgresos[Mes],BF$4) -> 0 | BH44: =IF(BF44="","",BF44-BG44) -> 2500000 | BI44: =IF(OR(BF44="",BF44=0),"",BG44/BF44) -> 0 | BJ44: 2500000 | BK44: =SUMIFS(TablaEgresos[Valor],TablaEgresos[Categoría],$A44,TablaEgresos[Mes],BJ$4) -> 0 | BL44: =IF(BJ44="","",BJ44-BK44) -> 2500000 | BM44: =IF(OR(BJ44="",BJ44=0),"",BK44/BJ44) -> 0 | BN44: 2500000 | BO44: =SUMIFS(TablaEgresos[Valor],TablaEgresos[Categoría],$A44,TablaEgresos[Mes],BN$4) -> 0 | BP44: =IF(BN44="","",BN44-BO44) -> 2500000 | BQ44: =IF(OR(BN44="",BN44=0),"",BO44/BN44) -> 0 | BR44: 2500000 | BS44: =SUMIFS(TablaEgresos[Valor],TablaEgresos[Categoría],$A44,TablaEgresos[Mes],BR$4) -> 0 | BT44: =IF(BR44="","",BR44-BS44) -> 2500000 | BU44: =IF(OR(BR44="",BR44=0),"",BS44/BR44) -> 0 | BV44: 2500000 | BW44: =SUMIFS(TablaEgresos[Valor],TablaEgresos[Categoría],$A44,TablaEgresos[Mes],BV$4) -> 0 | BX44: =IF(BV44="","",BV44-BW44) -> 2500000 | BY44: =IF(OR(BV44="",BV44=0),"",BW44/BV44) -> 0 | BZ44: 2500000 | CA44: =SUMIFS(TablaEgresos[Valor],TablaEgresos[Categoría],$A44,TablaEgresos[Mes],BZ$4) -> 0 | CB44: =IF(BZ44="","",BZ44-CA44) -> 2500000 | CC44: =IF(OR(BZ44="",BZ44=0),"",CA44/BZ44) -> 0 | CD44: 2500000 | CE44: =SUMIFS(TablaEgresos[Valor],TablaEgresos[Categoría],$A44,TablaEgresos[Mes],CD$4) -> 0 | CF44: =IF(CD44="","",CD44-CE44) -> 2500000 | CG44: =IF(OR(CD44="",CD44=0),"",CE44/CD44) -> 0 | CH44: 2500000 | CI44: =SUMIFS(TablaEgresos[Valor],TablaEgresos[Categoría],$A44,TablaEgresos[Mes],CH$4) -> 0 | CJ44: =IF(CH44="","",CH44-CI44) -> 2500000 | CK44: =IF(OR(CH44="",CH44=0),"",CI44/CH44) -> 0 | CL44: 2500000 | CM44: =SUMIFS(TablaEgresos[Valor],TablaEgresos[Categoría],$A44,TablaEgresos[Mes],CL$4) -> 0 | CN44: =IF(CL44="","",CL44-CM44) -> 2500000 | CO44: =IF(OR(CL44="",CL44=0),"",CM44/CL44) -> 0
A45: Por clasificar | B45: =IFERROR(AVERAGE(INDEX($B89:$W89,MATCH($B$3,$B$51:$W$51,0)-2):INDEX($B89:$W89,MATCH($B$3,$B$51:$W$51,0))),0) -> 24802133 | C45: =IFERROR(SLOPE(INDEX($B89:$W89,1):INDEX($B89:$W89,MATCH($B$3,$B$51:$W$51,0)),INDEX($B$50:$W$50,1):INDEX($B$50:$W$50,MATCH($B$3,$B$51:$W$51,0))),0) -> 18462205 | D45: =IF($B45=0,"",$C45/$B45) -> 0.74437973 | E45: =MAX(0,ROUND($B45+$C45*3,-3)) -> 80189000 | G45: =SUMIFS(TablaEgresos[Valor],TablaEgresos[Categoría],$A45,TablaEgresos[Mes],F$4) -> 0 | H45: =IF(F45="","",F45-G45) | I45: =IF(OR(F45="",F45=0),"",G45/F45) | K45: =SUMIFS(TablaEgresos[Valor],TablaEgresos[Categoría],$A45,TablaEgresos[Mes],J$4) -> 3689043.9 | L45: =IF(J45="","",J45-K45) | M45: =IF(OR(J45="",J45=0),"",K45/J45) | O45: =SUMIFS(TablaEgresos[Valor],TablaEgresos[Categoría],$A45,TablaEgresos[Mes],N$4) -> 11920485 | P45: =IF(N45="","",N45-O45) | Q45: =IF(OR(N45="",N45=0),"",O45/N45) | S45: =SUMIFS(TablaEgresos[Valor],TablaEgresos[Categoría],$A45,TablaEgresos[Mes],R$4) -> 58796869 | T45: =IF(R45="","",R45-S45) | U45: =IF(OR(R45="",R45=0),"",S45/R45) | V45: 0 | W45: =SUMIFS(TablaEgresos[Valor],TablaEgresos[Categoría],$A45,TablaEgresos[Mes],V$4) -> 106000 | X45: =IF(V45="","",V45-W45) -> -106000 | Y45: =IF(OR(V45="",V45=0),"",W45/V45) | Z45: 0 | AA45: =SUMIFS(TablaEgresos[Valor],TablaEgresos[Categoría],$A45,TablaEgresos[Mes],Z$4) -> 0 | AB45: =IF(Z45="","",Z45-AA45) -> 0 | AC45: =IF(OR(Z45="",Z45=0),"",AA45/Z45) | AD45: 0 | AE45: =SUMIFS(TablaEgresos[Valor],TablaEgresos[Categoría],$A45,TablaEgresos[Mes],AD$4) -> 0 | AF45: =IF(AD45="","",AD45-AE45) -> 0 | AG45: =IF(OR(AD45="",AD45=0),"",AE45/AD45) | AH45: 0 | AI45: =SUMIFS(TablaEgresos[Valor],TablaEgresos[Categoría],$A45,TablaEgresos[Mes],AH$4) -> 0 | AJ45: =IF(AH45="","",AH45-AI45) -> 0 | AK45: =IF(OR(AH45="",AH45=0),"",AI45/AH45) | AL45: 0 | AM45: =SUMIFS(TablaEgresos[Valor],TablaEgresos[Categoría],$A45,TablaEgresos[Mes],AL$4) -> 0 | AN45: =IF(AL45="","",AL45-AM45) -> 0 | AO45: =IF(OR(AL45="",AL45=0),"",AM45/AL45) | AP45: 0 | AQ45: =SUMIFS(TablaEgresos[Valor],TablaEgresos[Categoría],$A45,TablaEgresos[Mes],AP$4) -> 0 | AR45: =IF(AP45="","",AP45-AQ45) -> 0 | AS45: =IF(OR(AP45="",AP45=0),"",AQ45/AP45) | AT45: 0 | AU45: =SUMIFS(TablaEgresos[Valor],TablaEgresos[Categoría],$A45,TablaEgresos[Mes],AT$4) -> 0 | AV45: =IF(AT45="","",AT45-AU45) -> 0 | AW45: =IF(OR(AT45="",AT45=0),"",AU45/AT45) | AX45: 0 | AY45: =SUMIFS(TablaEgresos[Valor],TablaEgresos[Categoría],$A45,TablaEgresos[Mes],AX$4) -> 0 | AZ45: =IF(AX45="","",AX45-AY45) -> 0 | BA45: =IF(OR(AX45="",AX45=0),"",AY45/AX45) | BB45: 0 | BC45: =SUMIFS(TablaEgresos[Valor],TablaEgresos[Categoría],$A45,TablaEgresos[Mes],BB$4) -> 0 | BD45: =IF(BB45="","",BB45-BC45) -> 0 | BE45: =IF(OR(BB45="",BB45=0),"",BC45/BB45) | BF45: 0 | BG45: =SUMIFS(TablaEgresos[Valor],TablaEgresos[Categoría],$A45,TablaEgresos[Mes],BF$4) -> 0 | BH45: =IF(BF45="","",BF45-BG45) -> 0 | BI45: =IF(OR(BF45="",BF45=0),"",BG45/BF45) | BJ45: 0 | BK45: =SUMIFS(TablaEgresos[Valor],TablaEgresos[Categoría],$A45,TablaEgresos[Mes],BJ$4) -> 0 | BL45: =IF(BJ45="","",BJ45-BK45) -> 0 | BM45: =IF(OR(BJ45="",BJ45=0),"",BK45/BJ45) | BN45: 0 | BO45: =SUMIFS(TablaEgresos[Valor],TablaEgresos[Categoría],$A45,TablaEgresos[Mes],BN$4) -> 0 | BP45: =IF(BN45="","",BN45-BO45) -> 0 | BQ45: =IF(OR(BN45="",BN45=0),"",BO45/BN45) | BR45: 0 | BS45: =SUMIFS(TablaEgresos[Valor],TablaEgresos[Categoría],$A45,TablaEgresos[Mes],BR$4) -> 0 | BT45: =IF(BR45="","",BR45-BS45) -> 0 | BU45: =IF(OR(BR45="",BR45=0),"",BS45/BR45) | BV45: 0 | BW45: =SUMIFS(TablaEgresos[Valor],TablaEgresos[Categoría],$A45,TablaEgresos[Mes],BV$4) -> 0 | BX45: =IF(BV45="","",BV45-BW45) -> 0 | BY45: =IF(OR(BV45="",BV45=0),"",BW45/BV45) | BZ45: 0 | CA45: =SUMIFS(TablaEgresos[Valor],TablaEgresos[Categoría],$A45,TablaEgresos[Mes],BZ$4) -> 0 | CB45: =IF(BZ45="","",BZ45-CA45) -> 0 | CC45: =IF(OR(BZ45="",BZ45=0),"",CA45/BZ45) | CD45: 0 | CE45: =SUMIFS(TablaEgresos[Valor],TablaEgresos[Categoría],$A45,TablaEgresos[Mes],CD$4) -> 0 | CF45: =IF(CD45="","",CD45-CE45) -> 0 | CG45: =IF(OR(CD45="",CD45=0),"",CE45/CD45) | CH45: 0 | CI45: =SUMIFS(TablaEgresos[Valor],TablaEgresos[Categoría],$A45,TablaEgresos[Mes],CH$4) -> 0 | CJ45: =IF(CH45="","",CH45-CI45) -> 0 | CK45: =IF(OR(CH45="",CH45=0),"",CI45/CH45) | CL45: 0 | CM45: =SUMIFS(TablaEgresos[Valor],TablaEgresos[Categoría],$A45,TablaEgresos[Mes],CL$4) -> 0 | CN45: =IF(CL45="","",CL45-CM45) -> 0 | CO45: =IF(OR(CL45="",CL45=0),"",CM45/CL45)
A46: Subtotal Otros | B46: =SUM(B40:B45) -> 63266616 | C46: =SUM(C40:C45) -> 27438900 | D46: =IF(B46=0,"",C46/B46) -> 0.43370266 | E46: =SUM(E40:E45) -> 145583000 | F46: =SUM(F40:F45) -> 0 | G46: =SUM(G40:G45) -> 1624853.1 | H46: =SUM(H40:H45) -> 0 | I46: =IF(F46=0,"",G46/F46) | J46: =SUM(J40:J45) -> 0 | K46: =SUM(K40:K45) -> 44157611 | L46: =SUM(L40:L45) -> 0 | M46: =IF(J46=0,"",K46/J46) | N46: =SUM(N40:N45) -> 0 | O46: =SUM(O40:O45) -> 56752771 | P46: =SUM(P40:P45) -> 0 | Q46: =IF(N46=0,"",O46/N46) | R46: =SUM(R40:R45) -> 0 | S46: =SUM(S40:S45) -> 88889466 | T46: =SUM(T40:T45) -> 0 | U46: =IF(R46=0,"",S46/R46) | V46: =SUM(V40:V45) -> 19000000 | W46: =SUM(W40:W45) -> 14766336 | X46: =SUM(X40:X45) -> 4233664.4 | Y46: =IF(V46=0,"",W46/V46) -> 0.77717556 | Z46: =SUM(Z40:Z45) -> 8100000 | AA46: =SUM(AA40:AA45) -> 0 | AB46: =SUM(AB40:AB45) -> 8100000 | AC46: =IF(Z46=0,"",AA46/Z46) -> 0 | AD46: =SUM(AD40:AD45) -> 8100000 | AE46: =SUM(AE40:AE45) -> 0 | AF46: =SUM(AF40:AF45) -> 8100000 | AG46: =IF(AD46=0,"",AE46/AD46) -> 0 | AH46: =SUM(AH40:AH45) -> 8100000 | AI46: =SUM(AI40:AI45) -> 0 | AJ46: =SUM(AJ40:AJ45) -> 8100000 | AK46: =IF(AH46=0,"",AI46/AH46) -> 0 | AL46: =SUM(AL40:AL45) -> 8100000 | AM46: =SUM(AM40:AM45) -> 0 | AN46: =SUM(AN40:AN45) -> 8100000 | AO46: =IF(AL46=0,"",AM46/AL46) -> 0 | AP46: =SUM(AP40:AP45) -> 8100000 | AQ46: =SUM(AQ40:AQ45) -> 0 | AR46: =SUM(AR40:AR45) -> 8100000 | AS46: =IF(AP46=0,"",AQ46/AP46) -> 0 | AT46: =SUM(AT40:AT45) -> 8100000 | AU46: =SUM(AU40:AU45) -> 0 | AV46: =SUM(AV40:AV45) -> 8100000 | AW46: =IF(AT46=0,"",AU46/AT46) -> 0 | AX46: =SUM(AX40:AX45) -> 8100000 | AY46: =SUM(AY40:AY45) -> 0 | AZ46: =SUM(AZ40:AZ45) -> 8100000 | BA46: =IF(AX46=0,"",AY46/AX46) -> 0 | BB46: =SUM(BB40:BB45) -> 8100000 | BC46: =SUM(BC40:BC45) -> 0 | BD46: =SUM(BD40:BD45) -> 8100000 | BE46: =IF(BB46=0,"",BC46/BB46) -> 0 | BF46: =SUM(BF40:BF45) -> 8100000 | BG46: =SUM(BG40:BG45) -> 0 | BH46: =SUM(BH40:BH45) -> 8100000 | BI46: =IF(BF46=0,"",BG46/BF46) -> 0 | BJ46: =SUM(BJ40:BJ45) -> 8100000 | BK46: =SUM(BK40:BK45) -> 0 | BL46: =SUM(BL40:BL45) -> 8100000 | BM46: =IF(BJ46=0,"",BK46/BJ46) -> 0 | BN46: =SUM(BN40:BN45) -> 8100000 | BO46: =SUM(BO40:BO45) -> 0 | BP46: =SUM(BP40:BP45) -> 8100000 | BQ46: =IF(BN46=0,"",BO46/BN46) -> 0 | BR46: =SUM(BR40:BR45) -> 8100000 | BS46: =SUM(BS40:BS45) -> 0 | BT46: =SUM(BT40:BT45) -> 8100000 | BU46: =IF(BR46=0,"",BS46/BR46) -> 0 | BV46: =SUM(BV40:BV45) -> 8100000 | BW46: =SUM(BW40:BW45) -> 0 | BX46: =SUM(BX40:BX45) -> 8100000 | BY46: =IF(BV46=0,"",BW46/BV46) -> 0 | BZ46: =SUM(BZ40:BZ45) -> 8100000 | CA46: =SUM(CA40:CA45) -> 0 | CB46: =SUM(CB40:CB45) -> 8100000 | CC46: =IF(BZ46=0,"",CA46/BZ46) -> 0 | CD46: =SUM(CD40:CD45) -> 8100000 | CE46: =SUM(CE40:CE45) -> 0 | CF46: =SUM(CF40:CF45) -> 8100000 | CG46: =IF(CD46=0,"",CE46/CD46) -> 0 | CH46: =SUM(CH40:CH45) -> 8100000 | CI46: =SUM(CI40:CI45) -> 0 | CJ46: =SUM(CJ40:CJ45) -> 8100000 | CK46: =IF(CH46=0,"",CI46/CH46) -> 0 | CL46: =SUM(CL40:CL45) -> 8100000 | CM46: =SUM(CM40:CM45) -> 0 | CN46: =SUM(CN40:CN45) -> 8100000 | CO46: =IF(CL46=0,"",CM46/CL46) -> 0
A47: TOTAL | B47: =B10+B23+B31+B38+B46 -> 1.5598924e+08 | C47: =C10+C23+C31+C38+C46 -> 43405853 | D47: =IF(B47=0,"",C47/B47) -> 0.27826184 | E47: =E10+E23+E31+E38+E46 -> 292736000 | F47: =F10+F23+F31+F38+F46 -> 0 | G47: =G10+G23+G31+G38+G46 -> 14827761 | H47: =H10+H23+H31+H38+H46 -> 0 | I47: =IF(F47=0,"",G47/F47) | J47: =J10+J23+J31+J38+J46 -> 0 | K47: =K10+K23+K31+K38+K46 -> 1.8995237e+08 | L47: =L10+L23+L31+L38+L46 -> 0 | M47: =IF(J47=0,"",K47/J47) | N47: =N10+N23+N31+N38+N46 -> 0 | O47: =O10+O23+O31+O38+O46 -> 82775934 | P47: =P10+P23+P31+P38+P46 -> 0 | Q47: =IF(N47=0,"",O47/N47) | R47: =R10+R23+R31+R38+R46 -> 0 | S47: =S10+S23+S31+S38+S46 -> 1.9523942e+08 | T47: =T10+T23+T31+T38+T46 -> 0 | U47: =IF(R47=0,"",S47/R47) | V47: =V10+V23+V31+V38+V46 -> 2.8967115e+08 | W47: =W10+W23+W31+W38+W46 -> 2.1769249e+08 | X47: =X10+X23+X31+X38+X46 -> 71978663 | Y47: =IF(V47=0,"",W47/V47) -> 0.75151594 | Z47: =Z10+Z23+Z31+Z38+Z46 -> 178473000 | AA47: =AA10+AA23+AA31+AA38+AA46 -> 0 | AB47: =AB10+AB23+AB31+AB38+AB46 -> 178473000 | AC47: =IF(Z47=0,"",AA47/Z47) -> 0 | AD47: =AD10+AD23+AD31+AD38+AD46 -> 328944312 | AE47: =AE10+AE23+AE31+AE38+AE46 -> 0 | AF47: =AF10+AF23+AF31+AF38+AF46 -> 328944312 | AG47: =IF(AD47=0,"",AE47/AD47) -> 0 | AH47: =AH10+AH23+AH31+AH38+AH46 -> 327503808 | AI47: =AI10+AI23+AI31+AI38+AI46 -> 0 | AJ47: =AJ10+AJ23+AJ31+AJ38+AJ46 -> 327503808 | AK47: =IF(AH47=0,"",AI47/AH47) -> 0 | AL47: =AL10+AL23+AL31+AL38+AL46 -> 434141507 | AM47: =AM10+AM23+AM31+AM38+AM46 -> 0 | AN47: =AN10+AN23+AN31+AN38+AN46 -> 434141507 | AO47: =IF(AL47=0,"",AM47/AL47) -> 0 | AP47: =AP10+AP23+AP31+AP38+AP46 -> 558473000 | AQ47: =AQ10+AQ23+AQ31+AQ38+AQ46 -> 0 | AR47: =AR10+AR23+AR31+AR38+AR46 -> 558473000 | AS47: =IF(AP47=0,"",AQ47/AP47) -> 0 | AT47: =AT10+AT23+AT31+AT38+AT46 -> 313406000 | AU47: =AU10+AU23+AU31+AU38+AU46 -> 0 | AV47: =AV10+AV23+AV31+AV38+AV46 -> 313406000 | AW47: =IF(AT47=0,"",AU47/AT47) -> 0 | AX47: =AX10+AX23+AX31+AX38+AX46 -> 322606000 | AY47: =AY10+AY23+AY31+AY38+AY46 -> 0 | AZ47: =AZ10+AZ23+AZ31+AZ38+AZ46 -> 322606000 | BA47: =IF(AX47=0,"",AY47/AX47) -> 0 | BB47: =BB10+BB23+BB31+BB38+BB46 -> 331806000 | BC47: =BC10+BC23+BC31+BC38+BC46 -> 0 | BD47: =BD10+BD23+BD31+BD38+BD46 -> 331806000 | BE47: =IF(BB47=0,"",BC47/BB47) -> 0 | BF47: =BF10+BF23+BF31+BF38+BF46 -> 341006000 | BG47: =BG10+BG23+BG31+BG38+BG46 -> 0 | BH47: =BH10+BH23+BH31+BH38+BH46 -> 341006000 | BI47: =IF(BF47=0,"",BG47/BF47) -> 0 | BJ47: =BJ10+BJ23+BJ31+BJ38+BJ46 -> 350206000 | BK47: =BK10+BK23+BK31+BK38+BK46 -> 0 | BL47: =BL10+BL23+BL31+BL38+BL46 -> 350206000 | BM47: =IF(BJ47=0,"",BK47/BJ47) -> 0 | BN47: =BN10+BN23+BN31+BN38+BN46 -> 359406000 | BO47: =BO10+BO23+BO31+BO38+BO46 -> 0 | BP47: =BP10+BP23+BP31+BP38+BP46 -> 359406000 | BQ47: =IF(BN47=0,"",BO47/BN47) -> 0 | BR47: =BR10+BR23+BR31+BR38+BR46 -> 368606000 | BS47: =BS10+BS23+BS31+BS38+BS46 -> 0 | BT47: =BT10+BT23+BT31+BT38+BT46 -> 368606000 | BU47: =IF(BR47=0,"",BS47/BR47) -> 0 | BV47: =BV10+BV23+BV31+BV38+BV46 -> 377806000 | BW47: =BW10+BW23+BW31+BW38+BW46 -> 0 | BX47: =BX10+BX23+BX31+BX38+BX46 -> 377806000 | BY47: =IF(BV47=0,"",BW47/BV47) -> 0 | BZ47: =BZ10+BZ23+BZ31+BZ38+BZ46 -> 387006000 | CA47: =CA10+CA23+CA31+CA38+CA46 -> 0 | CB47: =CB10+CB23+CB31+CB38+CB46 -> 387006000 | CC47: =IF(BZ47=0,"",CA47/BZ47) -> 0 | CD47: =CD10+CD23+CD31+CD38+CD46 -> 396206000 | CE47: =CE10+CE23+CE31+CE38+CE46 -> 0 | CF47: =CF10+CF23+CF31+CF38+CF46 -> 396206000 | CG47: =IF(CD47=0,"",CE47/CD47) -> 0 | CH47: =CH10+CH23+CH31+CH38+CH46 -> 405406000 | CI47: =CI10+CI23+CI31+CI38+CI46 -> 0 | CJ47: =CJ10+CJ23+CJ31+CJ38+CJ46 -> 405406000 | CK47: =IF(CH47=0,"",CI47/CH47) -> 0 | CL47: =CL10+CL23+CL31+CL38+CL46 -> 414606000 | CM47: =CM10+CM23+CM31+CM38+CM46 -> 0 | CN47: =CN10+CN23+CN31+CN38+CN46 -> 414606000 | CO47: =IF(CL47=0,"",CM47/CL47) -> 0
A50: HISTÓRICO EJECUTADO POR MES (auxiliar de tendencias) | B50: 1 | C50: =B50+1 -> 2 | D50: =C50+1 -> 3 | E50: =D50+1 -> 4 | F50: =E50+1 -> 5 | G50: =F50+1 -> 6 | H50: =G50+1 -> 7 | I50: =H50+1 -> 8 | J50: =I50+1 -> 9 | ... W50: =V50+1 -> 22
B51: =DATE(2026,3,1) -> 46082 | C51: =EDATE(B51,1) -> 46113 | D51: =EDATE(C51,1) -> 46143 | E51: =EDATE(D51,1) -> 46174 | F51: =EDATE(E51,1) -> 46204 | G51: =EDATE(F51,1) -> 46235 | H51: =EDATE(G51,1) -> 46266 | I51: =EDATE(H51,1) -> 46296 | J51: =EDATE(I51,1) -> 46327 | ... W51: =EDATE(V51,1) -> 46722
A52: =A11 -> OPERACIÓN
A53: =A12 -> Arriendos | B53: =SUMIFS(TablaEgresos[[Valor]:[Valor]],TablaEgresos[[Categoría]:[Categoría]],$A12,TablaEgresos[[Mes]:[Mes]],B$51) -> 0 | C53: =SUMIFS(TablaEgresos[[Valor]:[Valor]],TablaEgresos[[Categoría]:[Categoría]],$A12,TablaEgresos[[Mes]:[Mes]],C$51) -> 0 | D53: =SUMIFS(TablaEgresos[[Valor]:[Valor]],TablaEgresos[[Categoría]:[Categoría]],$A12,TablaEgresos[[Mes]:[Mes]],D$51) -> 0 | E53: =SUMIFS(TablaEgresos[[Valor]:[Valor]],TablaEgresos[[Categoría]:[Categoría]],$A12,TablaEgresos[[Mes]:[Mes]],E$51) -> 0 | F53: =SUMIFS(TablaEgresos[[Valor]:[Valor]],TablaEgresos[[Categoría]:[Categoría]],$A12,TablaEgresos[[Mes]:[Mes]],F$51) -> 0 | G53: =SUMIFS(TablaEgresos[[Valor]:[Valor]],TablaEgresos[[Categoría]:[Categoría]],$A12,TablaEgresos[[Mes]:[Mes]],G$51) -> 0 | H53: =SUMIFS(TablaEgresos[[Valor]:[Valor]],TablaEgresos[[Categoría]:[Categoría]],$A12,TablaEgresos[[Mes]:[Mes]],H$51) -> 0 | I53: =SUMIFS(TablaEgresos[[Valor]:[Valor]],TablaEgresos[[Categoría]:[Categoría]],$A12,TablaEgresos[[Mes]:[Mes]],I$51) -> 0 | ... W53: =SUMIFS(TablaEgresos[[Valor]:[Valor]],TablaEgresos[[Categoría]:[Categoría]],$A12,TablaEgresos[[Mes]:[Mes]],W$51) -> 0
A54: =A13 -> Tecnología y software | B54: =SUMIFS(TablaEgresos[[Valor]:[Valor]],TablaEgresos[[Categoría]:[Categoría]],$A13,TablaEgresos[[Mes]:[Mes]],B$51) -> 468019.13 | C54: =SUMIFS(TablaEgresos[[Valor]:[Valor]],TablaEgresos[[Categoría]:[Categoría]],$A13,TablaEgresos[[Mes]:[Mes]],C$51) -> 3648770.1 | D54: =SUMIFS(TablaEgresos[[Valor]:[Valor]],TablaEgresos[[Categoría]:[Categoría]],$A13,TablaEgresos[[Mes]:[Mes]],D$51) -> 4237309.4 | E54: =SUMIFS(TablaEgresos[[Valor]:[Valor]],TablaEgresos[[Categoría]:[Categoría]],$A13,TablaEgresos[[Mes]:[Mes]],E$51) -> 4025854.1 | F54: =SUMIFS(TablaEgresos[[Valor]:[Valor]],TablaEgresos[[Categoría]:[Categoría]],$A13,TablaEgresos[[Mes]:[Mes]],F$51) -> 4808607.4 | G54: =SUMIFS(TablaEgresos[[Valor]:[Valor]],TablaEgresos[[Categoría]:[Categoría]],$A13,TablaEgresos[[Mes]:[Mes]],G$51) -> 0 | H54: =SUMIFS(TablaEgresos[[Valor]:[Valor]],TablaEgresos[[Categoría]:[Categoría]],$A13,TablaEgresos[[Mes]:[Mes]],H$51) -> 0 | I54: =SUMIFS(TablaEgresos[[Valor]:[Valor]],TablaEgresos[[Categoría]:[Categoría]],$A13,TablaEgresos[[Mes]:[Mes]],I$51) -> 0 | ... W54: =SUMIFS(TablaEgresos[[Valor]:[Valor]],TablaEgresos[[Categoría]:[Categoría]],$A13,TablaEgresos[[Mes]:[Mes]],W$51) -> 0
A55: =A9 -> Seguros (Hunter) | B55: =SUMIFS(TablaEgresos[[Valor]:[Valor]],TablaEgresos[[Categoría]:[Categoría]],$A9,TablaEgresos[[Mes]:[Mes]],B$51) -> 0 | C55: =SUMIFS(TablaEgresos[[Valor]:[Valor]],TablaEgresos[[Categoría]:[Categoría]],$A9,TablaEgresos[[Mes]:[Mes]],C$51) -> 0 | D55: =SUMIFS(TablaEgresos[[Valor]:[Valor]],TablaEgresos[[Categoría]:[Categoría]],$A9,TablaEgresos[[Mes]:[Mes]],D$51) -> 0 | E55: =SUMIFS(TablaEgresos[[Valor]:[Valor]],TablaEgresos[[Categoría]:[Categoría]],$A9,TablaEgresos[[Mes]:[Mes]],E$51) -> 0 | F55: =SUMIFS(TablaEgresos[[Valor]:[Valor]],TablaEgresos[[Categoría]:[Categoría]],$A9,TablaEgresos[[Mes]:[Mes]],F$51) -> 0 | G55: =SUMIFS(TablaEgresos[[Valor]:[Valor]],TablaEgresos[[Categoría]:[Categoría]],$A9,TablaEgresos[[Mes]:[Mes]],G$51) -> 0 | H55: =SUMIFS(TablaEgresos[[Valor]:[Valor]],TablaEgresos[[Categoría]:[Categoría]],$A9,TablaEgresos[[Mes]:[Mes]],H$51) -> 0 | I55: =SUMIFS(TablaEgresos[[Valor]:[Valor]],TablaEgresos[[Categoría]:[Categoría]],$A9,TablaEgresos[[Mes]:[Mes]],I$51) -> 0 | ... W55: =SUMIFS(TablaEgresos[[Valor]:[Valor]],TablaEgresos[[Categoría]:[Categoría]],$A9,TablaEgresos[[Mes]:[Mes]],W$51) -> 0
A56: =A8 -> SOAT/Matrículas | B56: =SUMIFS(TablaEgresos[[Valor]:[Valor]],TablaEgresos[[Categoría]:[Categoría]],$A8,TablaEgresos[[Mes]:[Mes]],B$51) -> 0 | C56: =SUMIFS(TablaEgresos[[Valor]:[Valor]],TablaEgresos[[Categoría]:[Categoría]],$A8,TablaEgresos[[Mes]:[Mes]],C$51) -> 0 | D56: =SUMIFS(TablaEgresos[[Valor]:[Valor]],TablaEgresos[[Categoría]:[Categoría]],$A8,TablaEgresos[[Mes]:[Mes]],D$51) -> 0 | E56: =SUMIFS(TablaEgresos[[Valor]:[Valor]],TablaEgresos[[Categoría]:[Categoría]],$A8,TablaEgresos[[Mes]:[Mes]],E$51) -> 15581666 | F56: =SUMIFS(TablaEgresos[[Valor]:[Valor]],TablaEgresos[[Categoría]:[Categoría]],$A8,TablaEgresos[[Mes]:[Mes]],F$51) -> 10465680 | G56: =SUMIFS(TablaEgresos[[Valor]:[Valor]],TablaEgresos[[Categoría]:[Categoría]],$A8,TablaEgresos[[Mes]:[Mes]],G$51) -> 0 | H56: =SUMIFS(TablaEgresos[[Valor]:[Valor]],TablaEgresos[[Categoría]:[Categoría]],$A8,TablaEgresos[[Mes]:[Mes]],H$51) -> 0 | I56: =SUMIFS(TablaEgresos[[Valor]:[Valor]],TablaEgresos[[Categoría]:[Categoría]],$A8,TablaEgresos[[Mes]:[Mes]],I$51) -> 0 | ... W56: =SUMIFS(TablaEgresos[[Valor]:[Valor]],TablaEgresos[[Categoría]:[Categoría]],$A8,TablaEgresos[[Mes]:[Mes]],W$51) -> 0
A57: =A14 -> Mobiliario/planta/equipo | B57: =SUMIFS(TablaEgresos[[Valor]:[Valor]],TablaEgresos[[Categoría]:[Categoría]],$A14,TablaEgresos[[Mes]:[Mes]],B$51) -> 0 | C57: =SUMIFS(TablaEgresos[[Valor]:[Valor]],TablaEgresos[[Categoría]:[Categoría]],$A14,TablaEgresos[[Mes]:[Mes]],C$51) -> 0 | D57: =SUMIFS(TablaEgresos[[Valor]:[Valor]],TablaEgresos[[Categoría]:[Categoría]],$A14,TablaEgresos[[Mes]:[Mes]],D$51) -> 0 | E57: =SUMIFS(TablaEgresos[[Valor]:[Valor]],TablaEgresos[[Categoría]:[Categoría]],$A14,TablaEgresos[[Mes]:[Mes]],E$51) -> 0 | F57: =SUMIFS(TablaEgresos[[Valor]:[Valor]],TablaEgresos[[Categoría]:[Categoría]],$A14,TablaEgresos[[Mes]:[Mes]],F$51) -> 71100 | G57: =SUMIFS(TablaEgresos[[Valor]:[Valor]],TablaEgresos[[Categoría]:[Categoría]],$A14,TablaEgresos[[Mes]:[Mes]],G$51) -> 0 | H57: =SUMIFS(TablaEgresos[[Valor]:[Valor]],TablaEgresos[[Categoría]:[Categoría]],$A14,TablaEgresos[[Mes]:[Mes]],H$51) -> 0 | I57: =SUMIFS(TablaEgresos[[Valor]:[Valor]],TablaEgresos[[Categoría]:[Categoría]],$A14,TablaEgresos[[Mes]:[Mes]],I$51) -> 0 | ... W57: =SUMIFS(TablaEgresos[[Valor]:[Valor]],TablaEgresos[[Categoría]:[Categoría]],$A14,TablaEgresos[[Mes]:[Mes]],W$51) -> 0
A58: =A15 -> Servicios públicos y telecom | B58: =SUMIFS(TablaEgresos[[Valor]:[Valor]],TablaEgresos[[Categoría]:[Categoría]],$A15,TablaEgresos[[Mes]:[Mes]],B$51) -> 0 | C58: =SUMIFS(TablaEgresos[[Valor]:[Valor]],TablaEgresos[[Categoría]:[Categoría]],$A15,TablaEgresos[[Mes]:[Mes]],C$51) -> 0 | D58: =SUMIFS(TablaEgresos[[Valor]:[Valor]],TablaEgresos[[Categoría]:[Categoría]],$A15,TablaEgresos[[Mes]:[Mes]],D$51) -> 0 | E58: =SUMIFS(TablaEgresos[[Valor]:[Valor]],TablaEgresos[[Categoría]:[Categoría]],$A15,TablaEgresos[[Mes]:[Mes]],E$51) -> 0 | F58: =SUMIFS(TablaEgresos[[Valor]:[Valor]],TablaEgresos[[Categoría]:[Categoría]],$A15,TablaEgresos[[Mes]:[Mes]],F$51) -> 0 | G58: =SUMIFS(TablaEgresos[[Valor]:[Valor]],TablaEgresos[[Categoría]:[Categoría]],$A15,TablaEgresos[[Mes]:[Mes]],G$51) -> 0 | H58: =SUMIFS(TablaEgresos[[Valor]:[Valor]],TablaEgresos[[Categoría]:[Categoría]],$A15,TablaEgresos[[Mes]:[Mes]],H$51) -> 0 | I58: =SUMIFS(TablaEgresos[[Valor]:[Valor]],TablaEgresos[[Categoría]:[Categoría]],$A15,TablaEgresos[[Mes]:[Mes]],I$51) -> 0 | ... W58: =SUMIFS(TablaEgresos[[Valor]:[Valor]],TablaEgresos[[Categoría]:[Categoría]],$A15,TablaEgresos[[Mes]:[Mes]],W$51) -> 0
A59: =A16 -> Mercado y aseo | B59: =SUMIFS(TablaEgresos[[Valor]:[Valor]],TablaEgresos[[Categoría]:[Categoría]],$A16,TablaEgresos[[Mes]:[Mes]],B$51) -> 0 | C59: =SUMIFS(TablaEgresos[[Valor]:[Valor]],TablaEgresos[[Categoría]:[Categoría]],$A16,TablaEgresos[[Mes]:[Mes]],C$51) -> 312270 | D59: =SUMIFS(TablaEgresos[[Valor]:[Valor]],TablaEgresos[[Categoría]:[Categoría]],$A16,TablaEgresos[[Mes]:[Mes]],D$51) -> 212380 | E59: =SUMIFS(TablaEgresos[[Valor]:[Valor]],TablaEgresos[[Categoría]:[Categoría]],$A16,TablaEgresos[[Mes]:[Mes]],E$51) -> 559358 | F59: =SUMIFS(TablaEgresos[[Valor]:[Valor]],TablaEgresos[[Categoría]:[Categoría]],$A16,TablaEgresos[[Mes]:[Mes]],F$51) -> 106278 | G59: =SUMIFS(TablaEgresos[[Valor]:[Valor]],TablaEgresos[[Categoría]:[Categoría]],$A16,TablaEgresos[[Mes]:[Mes]],G$51) -> 0 | H59: =SUMIFS(TablaEgresos[[Valor]:[Valor]],TablaEgresos[[Categoría]:[Categoría]],$A16,TablaEgresos[[Mes]:[Mes]],H$51) -> 0 | I59: =SUMIFS(TablaEgresos[[Valor]:[Valor]],TablaEgresos[[Categoría]:[Categoría]],$A16,TablaEgresos[[Mes]:[Mes]],I$51) -> 0 | ... W59: =SUMIFS(TablaEgresos[[Valor]:[Valor]],TablaEgresos[[Categoría]:[Categoría]],$A16,TablaEgresos[[Mes]:[Mes]],W$51) -> 0
A60: =A17 -> Cafetería | B60: =SUMIFS(TablaEgresos[[Valor]:[Valor]],TablaEgresos[[Categoría]:[Categoría]],$A17,TablaEgresos[[Mes]:[Mes]],B$51) -> 0 | C60: =SUMIFS(TablaEgresos[[Valor]:[Valor]],TablaEgresos[[Categoría]:[Categoría]],$A17,TablaEgresos[[Mes]:[Mes]],C$51) -> 67308.47 | D60: =SUMIFS(TablaEgresos[[Valor]:[Valor]],TablaEgresos[[Categoría]:[Categoría]],$A17,TablaEgresos[[Mes]:[Mes]],D$51) -> 1516520.8 | E60: =SUMIFS(TablaEgresos[[Valor]:[Valor]],TablaEgresos[[Categoría]:[Categoría]],$A17,TablaEgresos[[Mes]:[Mes]],E$51) -> 1742701 | F60: =SUMIFS(TablaEgresos[[Valor]:[Valor]],TablaEgresos[[Categoría]:[Categoría]],$A17,TablaEgresos[[Mes]:[Mes]],F$51) -> 176200 | G60: =SUMIFS(TablaEgresos[[Valor]:[Valor]],TablaEgresos[[Categoría]:[Categoría]],$A17,TablaEgresos[[Mes]:[Mes]],G$51) -> 0 | H60: =SUMIFS(TablaEgresos[[Valor]:[Valor]],TablaEgresos[[Categoría]:[Categoría]],$A17,TablaEgresos[[Mes]:[Mes]],H$51) -> 0 | I60: =SUMIFS(TablaEgresos[[Valor]:[Valor]],TablaEgresos[[Categoría]:[Categoría]],$A17,TablaEgresos[[Mes]:[Mes]],I$51) -> 0 | ... W60: =SUMIFS(TablaEgresos[[Valor]:[Valor]],TablaEgresos[[Categoría]:[Categoría]],$A17,TablaEgresos[[Mes]:[Mes]],W$51) -> 0
